Workbook

Sheet linhas
A1: P.7 | B1: Importação de bens e serviços | C1: 001 | D1: =EXACT(B1,E1) -> TRUE | E1: Importação de bens e serviços
A2: P.6 | B2: Exportação de bens e serviços | C2: 002 | D2: =EXACT(B2,E2) -> TRUE | E2: Exportação de bens e serviços
A3: P.1 | B3: Produção | C3: 003 | D3: =EXACT(B3,E3) -> TRUE | E3: Produção
A4: P.11 | B4: Produção mercantil | C4: 004 | D4: =EXACT(B4,E4) -> TRUE | E4: Produção mercantil
A5: P.12 | B5: Produção não-mercantil | C5: 005 | D5: =EXACT(B5,E5) -> TRUE | E5: Produção não-mercantil
A6: P.2 | B6: Consumo intermediário | C6: 006 | D6: =EXACT(B6,E6) -> TRUE | E6: Consumo intermediário
A7: D.21-D.31 | B7: Impostos, líquidos de subsídios, sobre produtos | C7: 007 | D7: =EXACT(B7,E7) -> TRUE | E7: Impostos, líquidos de subsídios, sobre produtos
A8: S.1 | B8: Valor adicionado bruto/Produto interno bruto | C8: 008 | D8: =EXACT(B8,E8) -> TRUE | E8: Valor adicionado bruto/Produto interno bruto
A9: S.11 | B9: Saldo externo de bens e serviços | C9: 009 | D9: =EXACT(B9,E9) -> TRUE | E9: Saldo externo de bens e serviços
A10: D.1 | B10: Remuneração dos empregados | C10: 010 | D10: =EXACT(B10,E10) -> TRUE | E10: Remuneração dos empregados
A11: D.11 | B11: Ordenados e salários | C11: 011 | D11: =EXACT(B11,E11) -> TRUE | E11: Ordenados e salários
A12: D.12 | B12: Contribuições sociais dos empregadores | C12: 012 | D12: =EXACT(B12,E12) -> TRUE | E12: Contribuições sociais dos empregadores
... A34: D.62 | B34: Benefícios sociais, exceto transferências sociais em espécie | C34: 034 | D34: =EXACT(B34,E34) -> TRUE | E34: Benefícios sociais, exceto transferências sociais em espécie
A35: D.621 | C35: 035 | D35: =EXACT(B35,E35) -> FALSE | E35: Benefícios de seguridade social em numerário
A36: D.622 | B36: Benefícios sociais com constituição de fundos | C36: 036 | D36: =EXACT(B36,E36) -> TRUE | E36: Benefícios sociais com constituição de fundos
A37: D.623 | B37: Benefícios sociais sem constituição de fundos | C37: 037 | D37: =EXACT(B37,E37) -> TRUE | E37: Benefícios sociais sem constituição de fundos
A38: D.624 | B38: Benefícios de assistência social em numerário | C38: 038 | D38: =EXACT(B38,E38) -> TRUE | E38: Benefícios de assistência social em numerário
A39: D.7 | B39: Outras transferências correntes | C39: 039 | D39: =EXACT(B39,E39) -> TRUE | E39: Outras transferências correntes
A40: D.71 | B40: Prêmios líquidos de seguros não-vida | C40: 040 | D40: =EXACT(B40,E40) -> FALSE | E40: Prêmios líquidos de seguros não-vida
A41: D.72 | B41: Indenizações de seguros não-vida | C41: 041 | D41: =EXACT(B41,E41) -> FALSE | E41: Indenizações de seguros não-vida
A42: D.73 | B42: Transferências correntes entre administrações públicas | C42: 042 | D42: =EXACT(B42,E42) -> FALSE | E42: Transferências correntes entre administrações públicas
A43: D.74 | B43: Cooperação Internacional | C43: 043 | D43: =EXACT(B43,E43) -> FALSE | E43: Cooperação Internacional
A44: D.75 | B44: Transferências correntes diversas | C44: 044 | D44: =EXACT(B44,E44) -> FALSE | E44: Transferências correntes diversas
A45: S.6 | B45: Renda disponível bruta | C45: 045 | D45: =EXACT(B45,E45) -> TRUE | E45: Renda disponível bruta
A46: D.63 | B46: Transferências sociais em espécie | C46: 046 | D46: =EXACT(B46,E46) -> TRUE | E46: Transferências sociais em espécie
A47: B.7 | B47: Renda disponível bruta ajustada | C47: 047 | D47: =EXACT(B47,E47) -> FALSE | E47: Renda disponível bruta ajustada
... A62: S.10.1 | B62: Variações do patrimônio líquido resultantes de poupança e da transferência de capital | C62: 062 | D62: =EXACT(B62,E62) -> TRUE | E62: Variações do patrimônio líquido resultantes de poupança e da transferência de capital

Sheet setores
A1: 0S1 | B1: Total da economia
A2: 0S1001 | B2: Empresas não financeiras
A3: 0S1002FIN | B3: Empresas financeiras
A4: 0S1002SEG | B4: Seguro
A5: 0S1003 | B5: Administração pública
A6: 0S1004 | B6: Famílias
A7: 0S1005 | B7: Instituições s/ fins lucrativ a serviço das fam.
A8: 0S2 | B8: Resto do mundo

Sheet CEI
A1: Contas econômicas integradas - 2020
A3: Contas | B3: Total | C3: Registros correspondentes à | E3: S.1 Total da economia | F3: S.15 Insti- tuições sem fins de lucro a serviço das famílias | G3: S.14 Famílias | H3: S.13 Governo Geral | I3: S.12 Empresas finan- ceiras | J3: S.11 Empresas não- finan- ceiras | K3: Códigos | L3: Transações e saldos | M3: S.11 Empresas não- finan- ceiras | N3: S.12 Empresas finan- ceiras | O3: S.13 Governo Geral | P3: S.14 Famílias | Q3: S.15 Insti- tuições sem fins de lucro a serviço das famílias | R3: S.1 Total da economia | S3: Registros correspondentes à | U3: Total | V3: Contas
C4: Conta de bens e serviços (recursos) | D4: Conta do resto do mundo | S4: Conta do resto do mundo | T4: Conta de bens e serviços (usos)
A7: Contas correntes (1 000 000 R$) | M7: Contas correntes (1 000 000 R$)
A8: Usos | G8: 5034849 | H8: 1039939 | M8: Recursos
A9: 1. Produção/ conta externa de bens e serviços | B9: 1206009 | C9: 1206009 | D9: 0 | E9: 0 | F9: 0 | G9: 0 | H9: 0 | I9: 0 | J9: 0 | K9: P.7 | L9: Importação de bens e serviços | M9: 0 | N9: 0 | O9: 0 | P9: 0 | Q9: 0 | R9: 0 | S9: 1206009 | T9: 0 | U9: 1206009 | V9: 1. Produção/ conta externa de bens e serviços
B10: 1252049 | C10: 0 | D10: 1252049 | E10: 0 | F10: 0 | G10: 0 | H10: 0 | I10: 0 | J10: 0 | K10: P.6 | L10: Exportação de bens e serviços | M10: 0 | N10: 0 | O10: 0 | P10: 0 | Q10: 0 | R10: 0 | S10: 0 | T10: 1252049 | U10: 1252049
B11: 13306199 | C11: 13306199 | D11: 0 | E11: 0 | F11: 0 | G11: 0 | H11: 0 | I11: 0 | J11: 0 | K11: P.1 | L11: Produção | M11: 8940104 | N11: 695746 | O11: 1537130 | P11: 1961389 | Q11: 171830 | R11: 13306199 | S11: 0 | T11: 0 | U11: 13306199
B12: 11007523 | C12: 11007523 | D12: 0 | E12: 0 | F12: 0 | G12: 0 | H12: 0 | I12: 0 | J12: 0 | K12: P.11 | L12: Produção mercantil | M12: 8865336 | N12: 692217 | O12: 47224 | P12: 1335972 | Q12: 66774 | R12: 11007523 | S12: 0 | T12: 0 | U12: 11007523
B13: 2298676 | C13: 2298676 | D13: 0 | E13: 0 | F13: 0 | G13: 0 | H13: 0 | I13: 0 | J13: 0 | K13: P.13 | L13: Produção não-mercantil | M13: 74768 | N13: 3529 | O13: 1489906 | P13: 625417 | Q13: 105056 | R13: 2298676 | S13: 0 | T13: 0 | U13: 2298676
B14: 6711262 | C14: 0 | D14: 0 | E14: 6711262 | F14: 107730 | G14: 610289 | H14: 390230 | I14: 244573 | J14: 5358440 | K14: P.2 | L14: Consumo intermediário | M14: 0 | N14: 0 | O14: 0 | P14: 0 | Q14: 0 | R14: 0 | S14: 0 | T14: 6711262 | U14: 6711262
B15: 1014660 | C15: 1014660 | D15: 0 | E15: 0 | F15: 0 | G15: 0 | H15: 0 | I15: 0 | J15: 0 | K15: D.21-D.31 | L15: Impostos, líquidos de subsídios, sobre produtos | M15: 0 | N15: 0 | O15: 0 | P15: 0 | Q15: 0 | R15: 1014660 | S15: 0 | T15: 0 | U15: 1014660
B16: 7609597 | C16: 0 | D16: 0 | E16: 7609597 | F16: 64100 | G16: 1351100 | H16: 1146900 | I16: 451173 | J16: 3581664 | K16: B.1 | L16: Valor adicionado bruto/Produto interno bruto (1) | M16: 3581664 | N16: 451173 | O16: 1146900 | P16: 1351100 | Q16: 64100 | R16: 7609597 | S16: 0 | T16: 0 | U16: 7609597 | V16: 2.1.1. Geração da renda
B17: -46040 | C17: 0 | D17: -46040 | E17: 0 | F17: 0 | G17: 0 | H17: 0 | I17: 0 | J17: 0 | K17: B.11 | L17: Saldo externo de bens e serviços | M17: 0 | N17: 0 | O17: 0 | P17: 0 | Q17: 0 | R17: 0 | S17: -46040 | T17: 0 | U17: -46040
A18: 2.1.1. Geração da renda | B18: 3193644 | C18: 0 | D18: 1301 | E18: 3192343 | F18: 58323 | G18: 125701 | H18: 1029004 | I18: 181149 | J18: 1798166 | K18: D.1 | L18: Remuneração dos empregados | M18: 0 | N18: 0 | O18: 0 | P18: 3192936 | Q18: 0 | R18: 3192936 | S18: 708 | T18: 0 | U18: 3193644 | V18: 2.1.2. Alocação da renda primária
B19: 2533262 | C19: 0 | D19: 1301 | E19: 2531961 | F19: 49516 | G19: 122479 | H19: 780730 | I19: 140138 | J19: 1439098 | K19: D.11 | L19: Salários | M19: 0 | N19: 0 | O19: 0 | P19: 2532554 | Q19: 0 | R19: 2532554 | S19: 708 | T19: 0 | U19: 2533262
B20: 660382 | C20: 0 | D20: 0 | E20: 660382 | F20: 8807 | G20: 3222 | H20: 248274 | I20: 41011 | J20: 359068 | K20: D.12 | L20: Contribuições sociais dos empregadores | M20: 0 | N20: 0 | O20: 0 | P20: 660382 | Q20: 0 | R20: 660382 | S20: 0 | T20: 0 | U20: 660382
B21: 562617 | C21: 0 | D21: 0 | E21: 562617 | F21: 8807 | G21: 3222 | H21: 150509 | I21: 41011 | J21: 359068 | K21: D.121 | L21: Contribuições sociais efetivas | M21: 0 | N21: 0 | O21: 0 | P21: 562617 | Q21: 0 | R21: 562617 | S21: 0 | T21: 0 | U21: 562617
B22: 97765 | C22: 0 | D22: 0 | E22: 97765 | F22: 0 | G22: 0 | H22: 97765 | I22: 0 | J22: 0 | K22: D.122 | L22: Contribuições sociais imputadas | M22: 0 | N22: 0 | O22: 0 | P22: 97765 | Q22: 0 | R22: 97765 | S22: 0 | T22: 0 | U22: 97765
B23: 1101051 | C23: 0 | D23: 0 | E23: 1101051 | F23: 1037 | G23: -2272 | H23: 278 | I23: 9262 | J23: 78086 | K23: D.2-D.3 | L23: Impostos, líquidos de subsídios, sobre a produção e a importação | M23: 0 | N23: 0 | O23: 1101051 | P23: 0 | Q23: 0 | R23: 1101051 | S23: 0 | T23: 0 | U23: 1101051
B24: 1014660 | C24: 0 | D24: 0 | E24: 1014660 | F24: 0 | G24: 0 | H24: 0 | I24: 0 | J24: 0 | K24: D.21-D.31 | L24: Impostos, líquidos de subsídios, sobre produtos | M24: 0 | N24: 0 | O24: 1014660 | P24: 0 | Q24: 0 | R24: 1014660 | S24: 0 | T24: 0 | U24: 1014660
B25: 86391 | C25: 0 | D25: 0 | E25: 86391 | F25: 1037 | G25: -2272 | H25: 278 | I25: 9262 | J25: 78086 | K25: D.29-D.39 | L25: Outros impostos, líquidos de subsídios, sobre a produção | M25: 0 | N25: 0 | O25: 86391 | P25: 0 | Q25: 0 | R25: 86391 | S25: 0 | T25: 0 | U25: 86391
B26: 2682839 | C26: =B16-B18-B23+B17 -> 3268862 | D26: 0 | E26: 2682839 | F26: 4740 | G26: 594307 | H26: =O16-H18-H23 -> 117618 | I26: =I16-I18-I23 -> 260762 | J26: =M16-J18-J23 -> 1705412 | K26: B.2 | L26: Excedente operacional bruto | M26: 1705412 | N26: 260762 | O26: 117618 | P26: 594307 | Q26: 4740 | R26: 2682839 | S26: 0 | T26: 0 | U26: 2682839
B27: 633364 | C27: =SUM(B26:B27) -> 3316203 | D27: 0 | E27: 633364 | F27: 0 | G27: 633364 | I27: 0 | J27: 0 | K27: B.3 | L27: Rendimento misto bruto (rendimento de autônomos) | M27: 0 | N27: 0 | O27: 0 | P27: 633364 | Q27: 0 | R27: 633364 | S27: 0 | T27: 0 | U27: 633364
A28: 2.1.2. Alocação da renda primária | B28: 3029954 | C28: 0 | D28: 100439 | E28: 2929515 | F28: 116 | G28: 205684 | H28: 446981 | I28: 1323947 | J28: 952787 | K28: D.4 | L28: Rendas de propriedade | M28: 322910 | N28: 1348503 | O28: 268251 | P28: 819926 | Q28: 10573 | R28: 2770163 | S28: 259791 | T28: 0 | U28: 3029954
B29: 2028056 | D29: 32573 | E29: 1995483 | F29: 116 | G29: 205027 | H29: 446981 | I29: 1060460 | J29: 282899 | K29: D.41 | L29: Juros | M29: 246213 | N29: 1235025 | O29: 191053 | P29: 239016 | Q29: 10530 | R29: 1921837 | S29: 106219 | T29: 0 | U29: 2028056
B30: 805952 | C30: 0 | D30: 61731 | E30: 744221 | F30: 0 | G30: 0 | H30: 0 | I30: 164460 | J30: 579761 | K30: D.42 | L30: Rendas distribuídas das empresas | M30: 70354 | N30: 86283 | O30: 10278 | P30: 513540 | Q30: 0 | R30: 680455 | S30: 125497 | T30: 0 | U30: 805952
B31: 34173 | C31: 0 | D31: 6135 | E31: 28038 | F31: 0 | G31: 0 | H31: 0 | I31: 3562 | J31: 24476 | K31: D.43 | L31: Lucros reinvestidos de investimento estrangeiro direto | M31: 2842 | N31: 3293 | O31: 0 | P31: 0 | Q31: 0 | R31: 6135 | S31: 28038 | T31: 0 | U31: 34173
B32: 95465 | C32: 0 | D32: 0 | E32: 95465 | F32: 0 | G32: 0 | H32: 0 | I32: 95465 | J32: 0 | K32: D.44 | L32: Desembolsos por rendas de investimentos | M32: 3501 | N32: 23902 | O32: 612 | P32: 67370 | Q32: 43 | R32: 95428 | S32: 37 | T32: 0 | U32: 95465
B33: 6574 | C33: 0 | D33: 0 | E33: 6574 | F33: 0 | G33: 0 | H33: 0 | I33: 6574 | J33: 0 | K33: D.441 | L33: Rendimento de investimentos atribuído a detentores de apólices de seguros | M33: 1186 | N33: 1107 | O33: 65 | P33: 4136 | Q33: 43 | R33: 6537 | S33: 37 | T33: 0 | U33: 6574
B34: 56739 | C34: 0 | D34: 0 | E34: 56739 | F34: 0 | G34: 0 | H34: 0 | I34: 56739 | J34: 0 | K34: D.442 | L34: Rendimento de investimentos a pagar sobre direitos de pensão | M34: 0 | N34: 0 | O34: 0 | P34: 56739 | Q34: 0 | R34: 56739 | S34: 0 | T34: 0 | U34: 56739
B35: 32152 | C35: 0 | D35: 0 | E35: 32152 | F35: 0 | G35: 0 | H35: 0 | I35: 32152 | J35: 0 | K35: D.443 | L35: Rendimento de investimentos atribuído a acionistas de fundos de investimento | M35: 2315 | N35: 22795 | O35: 547 | P35: 6495 | Q35: 0 | R35: 32152 | S35: 0 | T35: 0 | U35: 32152
B36: 66308 | C36: 0 | D36: 0 | E36: 66308 | F36: 0 | G36: 657 | H36: 0 | I36: 0 | J36: 65651 | K36: D.45 | L36: Renda de recursos naturais | M36: 0 | N36: 0 | O36: 66308 | P36: 0 | Q36: 0 | R36: 66308 | S36: 0 | T36: 0 | U36: 66308
B37: 7450838 | C37: 0 | D37: 0 | E37: 7450838 | F37: 15197 | G37: 5034849 | H37: =O16+O23-H18-H23+O28-H28 -> 1039939 | I37: 285318 | J37: 1075535 | K37: B.5 | L37: Saldo das rendas primárias brutas/Renda nacional bruta (2) | M37: 1075535 | N37: 285318 | O37: 1039939 | P37: 5034849 | Q37: 15197 | R37: 7450838 | S37: 0 | T37: 0 | U37: 7450838 | V37: 2.2. Distribuição secundária da renda
A38: 2.2. Distribuição secundária da renda | B38: 625041 | C38: 0 | D38: 0 | E38: 625041 | F38: 584 | G38: 286229 | H38: 365 | I38: 42715 | J38: 295148 | K38: D.5 | L38: Impostos correntes sobre a renda, patrimônio, etc. | M38: 0 | N38: 0 | O38: 625041 | P38: 0 | Q38: 0 | R38: 625041 | S38: 0 | T38: 0 | U38: 625041
B39: 895266 | C39: 0 | D39: 0 | E39: 895266 | F39: 0 | G39: 895266 | H39: 0 | I39: 0 | J39: 0 | K39: D.61 | L39: Contribuições sociais | M39: 0 | N39: 94536 | O39: 800730 | P39: 0 | Q39: 0 | R39: 895266 | S39: 0 | T39: 0 | U39: 895266
B40: 562617 | C40: 0 | D40: 0 | E40: 562617 | F40: 0 | G40: 562617 | H40: 0 | I40: 0 | J40: 0 | K40: D.611 | L40: Contribuições sociais efetivas dos empregadores | M40: 0 | N40: 21236 | O40: 541381 | P40: 0 | Q40: 0 | R40: 562617 | S40: 0 | T40: 0 | U40: 562617
B41: 97765 | C41: 0 | D41: 0 | E41: 97765 | F41: 0 | G41: 97765 | H41: 0 | I41: 0 | J41: 0 | K41: D.612 | L41: Contribuições sociais imputadas dos empregadores | M41: 0 | N41: 0 | O41: 97765 | P41: 0 | Q41: 0 | R41: 97765 | S41: 0 | T41: 0 | U41: 97765
B42: 234884 | C42: 0 | D42: 0 | E42: 234884 | F42: 0 | G42: 234884 | H42: 0 | I42: 0 | J42: 0 | K42: D.613/614 | L42: Contribuições sociais efetivas das famílias/empregados e suplemento às contribuições sociais | M42: 0 | N42: 73300 | O42: 161584 | P42: 0 | Q42: 0 | R42: 234884 | S42: 0 | T42: 0 | U42: 234884
B43: 1827609 | C43: 0 | D43: 0 | E43: 1827609 | F43: 0 | G43: 0 | H43: 1752871 | I43: 74738 | J43: 0 | K43: D.62 | L43: Benefícios sociais, exceto transferências sociais em espécie | M43: 0 | N43: 0 | O43: 0 | P43: 1827609 | Q43: 0 | R43: 1827609 | S43: 0 | T43: 0 | U43: 1827609
B44: 742258 | C44: 0 | D44: 0 | E44: 742258 | F44: 0 | G44: 0 | H44: 742258 | I44: 0 | J44: 0 | K44: D.621 | L44: Benefícios de seguridade social em numerário | M44: 0 | N44: 0 | O44: 0 | P44: 742258 | Q44: 0 | R44: 742258 | S44: 0 | T44: 0 | U44: 742258
B45: 670737 | C45: 0 | D45: 0 | E45: 670737 | F45: 0 | G45: 0 | H45: 595999 | I45: 74738 | J45: 0 | K45: D.622 | L45: Outros benefícios de seguro social | M45: 0 | N45: 0 | O45: 0 | P45: 670737 | Q45: 0 | R45: 670737 | S45: 0 | T45: 0 | U45: 670737
B46: 414614 | C46: 0 | D46: 0 | E46: 414614 | F46: 0 | G46: 0 | H46: 414614 | I46: 0 | J46: 0 | K46: D.623 | L46: Benefícios de assistência social em numerário | M46: 0 | N46: 0 | O46: 0 | P46: 414614 | Q46: 0 | R46: 414614 | S46: 0 | T46: 0 | U46: 414614
B47: 1159362 | C47: 0 | D47: 26415 | E47: 1132947 | F47: 458 | G47: 112163 | H47: 844896 | I47: 80387 | J47: 95043 | K47: D.7 | L47: Outras transferências correntes | M47: 41947 | N47: 67100 | O47: 881244 | P47: 56381 | Q47: 97173 | R47: 1143845 | S47: 15517 | T47: 0 | U47: 1159362
B48: 62758 | C48: 0 | D48: 282 | E48: 62476 | F48: 458 | G48: 44995 | H48: 408 | I48: 2041 | J48: 14574 | K48: D.71 | L48: Prêmios líquidos de seguros não-vida | M48: 0 | N48: 61834 | O48: 0 | P48: 0 | Q48: 0 | R48: 61834 | S48: 924 | T48: 0 | U48: 62758
B49: 62758 | C49: 0 | D49: 27 | E49: 62731 | F49: 0 | G49: 0 | H49: 0 | I49: 62731 | J49: 0 | K49: D.72 | L49: Indenizações de seguros não-vida | M49: 29778 | N49: 856 | O49: 822 | P49: 30254 | Q49: 383 | R49: 62093 | S49: 665 | T49: 0 | U49: 62758
B50: 745989 | C50: 0 | D50: 0 | E50: 745989 | F50: 0 | G50: 0 | H50: 745989 | I50: 0 | J50: 0 | K50: D.73 | L50: Transferências correntes entre unidades do governo geral | M50: 0 | N50: 0 | O50: 745989 | P50: 0 | Q50: 0 | R50: 745989 | S50: 0 | T50: 0 | U50: 745989
... B52: 284978 | C52: 0 | D52: 24742 | E52: 260236 | F52: 0 | G52: 67168 | H52: 96984 | I52: 15615 | J52: 80469 | K52: D.75 | L52: Transferências correntes diversas | M52: 12169 | N52: 4410 | O52: 133069 | P52: 26127 | Q52: 96790 | R52: 272565 | S52: 12413 | T52: 0 | U52: 284978
B53: 7461736 | C53: 0 | D53: 0 | E53: 7461736 | F53: 111328 | G53: 5625181 | H53: =O37+O38+O39+O43+O47-H47-H43-H39-H38 -> 748822 | I53: 249114 | J53: 727291 | K53: B.6 | L53: Renda nacional disponível bruta | M53: 727291 | N53: 249114 | O53: 748822 | P53: 5625181 | Q53: 111328 | R53: 7461736 | S53: 0 | T53: 0 | U53: 7461736 | V53: 2.3. Redistribuição da renda em espécie
A54: 2.3. Redistribuição da renda em espécie | B54: 792009 | C54: 0 | D54: 0 | E54: 792009 | F54: 104919 | G54: 0 | H54: 687090 | I54: 0 | J54: 0 | K54: D.63 | L54: Transferências sociais em espécie | M54: 0 | N54: 0 | O54: 0 | P54: 792009 | Q54: 0 | R54: 792009 | S54: 0 | T54: 0 | U54: 792009
B55: 7461736 | C55: 0 | D55: 0 | E55: 7461736 | F55: 6409 | G55: 6417190 | H55: 61732 | I55: 249114 | J55: 727291 | K55: B.7 | L55: Renda disponível bruta ajustada | M55: 727291 | N55: 249114 | O55: 61732 | P55: 6417190 | Q55: 6409 | R55: 7461736 | S55: 0 | T55: 0 | U55: 7461736 | V55: 2.4. Uso da renda
A56: 2.4. Uso da renda | B56: 0 | C56: 0 | D56: 0 | E56: 0 | F56: 0 | G56: 0 | H56: 0 | I56: 0 | J56: 0 | K56: B.6 | L56: Renda nacional disponível bruta | M56: 727291 | N56: 249114 | O56: 748822 | P56: 5625181 | Q56: 111328 | R56: 7461736 | S56: 0 | T56: 0 | U56: 7461736
B57: 6337208 | C57: 0 | D57: 0 | E57: 6337208 | F57: 0 | G57: 5492094 | H57: 845114 | I57: 0 | J57: 0 | K57: P.4 | L57: Consumo final efetivo | M57: 0 | N57: 0 | O57: 0 | P57: 0 | Q57: 0 | R57: 0 | S57: 0 | T57: 6337208 | U57: 6337208
B58: 6337208 | C58: 0 | D58: 0 | E58: 6337208 | F58: 104919 | G58: 4700085 | H58: 1532204 | I58: 0 | J58: 0 | K58: P.3 | L58: Despesa de consumo final | M58: 0 | N58: 0 | O58: 0 | P58: 0 | Q58: 0 | R58: 0 | S58: 0 | T58: 6337208 | U58: 6337208
B59: 47061 | C59: 0 | D59: 0 | E59: 47061 | F59: 0 | G59: 0 | H59: 28647 | I59: 18414 | J59: 0 | K59: D.8 | L59: Ajustamento pela variação dos direitos de pensão | M59: 0 | N59: 0 | O59: 0 | P59: 47061 | Q59: 0 | R59: 47061 | S59: 0 | T59: 0 | U59: 47061
B60: 1124528 | C60: 0 | D60: 0 | E60: 1124528 | F60: 6409 | G60: =G55-G57-G59+P59 -> 972157 | H60: =H53-H58-H59 -> -812029 | I60: =I55-I59 -> 230700 | J60: 727291 | K60: B.8 | L60: Poupança bruta | M60: 0 | N60: 0 | O60: 0 | P60: 0 | Q60: 0 | R60: 0 | S60: 0 | T60: 0 | U60: 0
B61: 101821 | C61: 0 | D61: 101821 | E61: 0 | F61: 0 | H61: 0 | I61: 0 | J61: 0 | K61: B.12 | L61: Saldo externo corrente | M61: 0 | N61: 0 | O61: 0 | P61: 0 | Q61: 0 | R61: 0 | S61: 0 | T61: 0 | U61: 0
A62: Contas de acumulação (1 000 000 R$) | M62: Contas de acumulação (1 000 000 R$)
A63: Variações de ativos | M63: Variações de passivos e patrimônio líquido
A64: 3.1. Capital | B64: 0 | C64: 0 | D64: 0 | E64: 0 | F64: 0 | G64: 0 | H64: 0 | I64: 0 | J64: 0 | K64: B.8 | L64: Poupança bruta | M64: 727291 | N64: 230700 | O64: -812029 | P64: 972157 | Q64: 6409 | R64: 1124528 | S64: 0 | T64: 0 | U64: 1124528 | V64: 3.1. Capital
B65: 0 | C65: 0 | D65: 0 | E65: 0 | F65: 0 | G65: 0 | H65: 0 | I65: 0 | J65: 0 | K65: B.12 | L65: Saldo externo corrente | M65: 0 | N65: 0 | O65: 0 | P65: 0 | Q65: 0 | R65: 0 | S65: 101821 | T65: 0 | U65: 101821
B66: 1260227 | C66: 0 | D66: 0 | E66: 1260227 | F66: 4949 | G66: 405061 | H66: 139686 | I66: 13718 | J66: 696813 | K66: P.51 | L66: Formação bruta de capital fixo | M66: 0 | N66: 0 | O66: 0 | P66: 0 | Q66: 0 | R66: 0 | S66: 0 | T66: 1260227 | U66: 1260227
B67: -33878 | C67: 0 | D67: 0 | E67: -33878 | F67: 0 | G67: 0 | H67: 0 | I67: 0 | J67: -33878 | K67: P.52 | L67: Variação de estoques | M67: 0 | N67: 0 | O67: 0 | P67: 0 | Q67: 0 | R67: 0 | S67: 0 | T67: -33878 | U67: -33878
B68: 0 | C68: 0 | D68: 722 | E68: -722 | F68: 0 | G68: 0 | H68: -6588 | I68: 0 | J68: 5866 | K68: NP | L68: Aquisições líquidas de cessões de ativos não-produzidos | M68: 0 | N68: 0 | O68: 0 | P68: 0 | Q68: 0 | R68: 0 | S68: 0 | T68: 0 | U68: 0
B69: 0 | C69: 0 | D69: 0 | E69: 0 | F69: 0 | G69: 0 | H69: 0 | I69: 0 | J69: 0 | K69: D.9 | L69: Transferências de capital a receber | M69: 450 | N69: 0 | O69: 54239 | P69: 1597 | Q69: 2867 | R69: 59153 | S69: 251 | T69: 0 | U69: 59404
B70: 0 | C70: 0 | D70: 0 | E70: 0 | F70: 0 | G70: 0 | H70: 0 | I70: 0 | J70: 0 | K70: D.9 | L70: Transferências de capital a pagar | M70: -658 | N70: -65 | O70: -27121 | P70: -10748 | Q70: 0 | R70: -38592 | S70: -20812 | T70: 0 | U70: -59404
B71: 0 | C71: 0 | D71: 80538 | E71: -80538 | F71: 4327 | G71: 557945 | H71: -918009 | I71: 216917 | J71: =M64-J66-J67-J68+M69+M70 -> 58282 | K71: B.9 | L71: Capacidade (+) / Necessidade(-) líquida de financiamento | M71: 0 | N71: 0 | O71: 0 | P71: 0 | Q71: 0 | R71: 0 | S71: 0 | T71: 0 | U71: 0
B72: 0 | C72: 0 | D72: 0 | E72: 0 | F72: 0 | G72: 0 | H72: 0 | I72: 0 | J72: 0 | K72: B.10.1 | L72: Variações do patrimônio líquido resultantes de poupança e da transferência de capital | M72: 727083 | N72: 230635 | O72: -784911 | P72: 963006 | Q72: 9276 | R72: 1145089 | S72: 81260 | T72: 0 | U72: 1226349
A74: Contas | B74: Total | C74: Conta do resto do mundo | E74: S.1 Total da economia | F74: S.14/15 Famílias e Insti- tuições sem fins de lucro a serviço das famílias | H74: S.13 Governo Geral | I74: S.12 Empresas finan- ceiras | J74: S.11 Empresas não- finan- ceiras | K74: Códigos | L74: Transações e saldos | M74: S.11 Empresas não- finan- ceiras | N74: S.12 Empresas finan- ceiras | O74: S.13 Governo Geral | P74: S.14/15 Famílias e Insti- tuições sem fins de lucro a serviço das famílias | R74: S.1 Total da economia | S74: Conta do resto do mundo | U74: Total | V74: Contas
J78: =J80-M80 -> 58282.02
A79: Variações de ativos | M79: Variações de passivos e patrimônio líquido
A80: 3.2. Conta financeira | B80: =E80+D80 -> 3631117.3 | D80: -140248.04 | E80: 3771365.3 | F80: 732623.96 | H80: -266317.12 | I80: 2508396.5 | J80: 796661.97 | K80: F | L80: Aquisição líquida de ativos financeiros/Aquisição líquida de passivos | M80: 738379.95 | N80: 2291479.5 | O80: 651691.88 | P80: 170351.96 | R80: 3851903.3 | S80: -220786.03 | U80: =R80+S80 -> 3631117.3 | V80: 3.2. Conta financeira
B81: =E81+D81 -> 38.74 | D81: 0 | E81: 38.74 | F81: 0 | H81: 0 | I81: 38.74 | J81: 0 | K81: F.1 | L81: Ouro monetário e DES | M81: 0 | N81: 0 | O81: 0 | P81: 0 | R81: 0 | S81: 38.74 | U81: =R81+S81 -> 38.74
B82: =E82+D82 -> 266515.37 | D82: 3836.96 | E82: 262678.41 | F82: 356546.18 | H82: -364233.19 | I82: 120408.22 | J82: 149957.2 | K82: F.2 | L82: Numerário e depósitos | M82: 0 | N82: 163907.43 | O82: 6903.07 | P82: 0 | R82: 170810.5 | S82: 95704.89 | U82: =R82+S82 -> 266515.39
B83: =E83+D83 -> 89755.86 | D83: 0 | E83: 89755.86 | F83: 80391.68 | H83: 0 | I83: 9364.18 | J83: 0 | K83: F.21 | L83: Numerário | M83: 0 | N83: 89755.86 | O83: 0 | P83: 0 | R83: 89755.86 | S83: 0 | U83: =R83+S83 -> 89755.86
B84: =E84+D84 -> -156119.74 | D84: 3337.78 | E84: -159457.52 | F84: 47522.85 | H84: -367510.9 | I84: 65703.24 | J84: 94827.29 | K84: F.22 | L84: Depósito transferível | M84: 0 | N84: -244738.87 | O84: 0 | P84: 0 | R84: -244738.87 | S84: 88619.14 | U84: =R84+S84 -> -156119.73
B85: =E85+D85 -> 332879.25 | D85: 499.18 | E85: 332380.07 | F85: 228631.65 | H85: 3277.71 | I85: 45340.8 | J85: 55129.91 | K85: F.29 | L85: Outros depósitos | M85: 0 | N85: 318890.44 | O85: 6903.07 | P85: 0 | R85: 325793.51 | S85: 7085.75 | U85: =R85+S85 -> 332879.26
B86: =E86+D86 -> 1098347.8 | D86: 10607.55 | E86: 1087740.2 | F86: 181068.42 | H86: 4204.43 | I86: 534497.35 | J86: 367970.05 | K86: F.3 | L86: Títulos de dívidas | M86: 15866.38 | N86: 468794.66 | O86: 742000.17 | P86: 0 | R86: 1226661.2 | S86: -128313.41 | U86: =R86+S86 -> 1098347.8
B87: =E87+D87 -> 823925.29 | D87: 50890.63 | E87: 773034.66 | F87: 4651.61 | H87: 6486.81 | I87: 588471.38 | J87: 173424.86 | K87: F.31 | L87: Curto prazo | M87: 434.83 | N87: 234878.3 | O87: 587607.06 | P87: 0 | R87: 822920.19 | S87: 1005.11 | U87: =R87+S87 -> 823925.3
B88: =E88+D88 -> 274422.51 | D88: -40283.08 | E88: 314705.59 | F88: 176416.81 | H88: -2282.38 | I88: -53974.03 | J88: 194545.19 | K88: F.32 | L88: Longo prazo | M88: 15431.55 | N88: 233916.36 | O88: 154393.11 | P88: 0 | R88: 403741.02 | S88: -129318.52 | U88: =R88+S88 -> 274422.5
B89: =E89+D89 -> 1160492.5 | D89: -70888.03 | E89: 1231380.5 | F89: 392.6 | H89: 77166.1 | I89: 1216829.9 | J89: -63008.06 | K89: F.4 | L89: Empréstimos | M89: 309954.39 | N89: 640708.56 | O89: 45872.3 | P89: 159558.48 | R89: 1156093.7 | S89: 4398.73 | U89: =R89+S89 -> 1160492.5
B90: =E90+D90 -> 623682.91 | D90: -60148.54 | E90: 683831.45 | F90: 7.03 | H90: 458.16 | I90: 683014.72 | J90: 351.54 | K90: F.41 | L90: Curto prazo | M90: 32738.57 | N90: 604855.03 | O90: 351.71 | P90: -13597.55 | R90: 624347.76 | S90: -664.85 | U90: =R90+S90 -> 623682.91
B91: =E91+D91 -> 536809.55 | D91: -10739.49 | E91: 547549.04 | F91: 385.57 | H91: 76707.94 | I91: 533815.13 | J91: -63359.6 | K91: F.42 | L91: Longo prazo | M91: 277215.82 | N91: 35853.53 | O91: 45520.59 | P91: 173156.03 | R91: 531745.97 | S91: 5063.58 | U91: =R91+S91 -> 536809.55
B92: =E92+D92 -> 1192640.4 | D92: 87595.26 | E92: 1105045.2 | F92: 164152.54 | H92: 11849.39 | I92: 674099.1 | J92: 254944.13 | K92: F.5 | L92: Participações de capital e em fundos de investimentos | M92: 300967.19 | N92: 862294.48 | O92: 0 | P92: 0 | R92: 1163261.7 | S92: 29378.74 | U92: =R92+S92 -> 1192640.4
... B104: =E104+D104 -> -96794.25 | D104: 0 | E104: -96794.25 | F104: -78543.72 | H104: 4696.15 | I104: -47135.48 | J104: 24188.8 | K104: F.89 | L104: Outros | M104: 76129.36 | N104: 61950.27 | O104: -143083.66 | P104: 9116.2 | R104: 4112.17 | S104: -100906.43 | U104: =R104+S104 -> -96794.26
B105: =ROUND(E105+D105,0) -> 0 | D105: 80537.99 | E105: -80537.99 | F105: 562272 | H105: -918009 | I105: 216916.99 | J105: 58282.02 | K105: B.9 | L105: Capacidade (+) / Necessidade(-) líquida de financiamento
A107: Ativos | M107: Passivos e patrimônio líquido
A108: 3.3. Conta de patrimônio financeiro inicial | B108: =E108+D108 -> 55112252 | D108: 6790635 | E108: 48321617 | F108: 9047556 | H108: 4196601 | I108: 28360626 | J108: 6716834 | K108: AF | L108: Total de ativos financeiros/passivos | M108: 11817901 | N108: 29183980 | O108: 8128465 | P108: 2409987 | R108: 51540333 | S108: 3558629 | U108: =R108+S108 -> 55098962 | V108: 3.3. Conta de patrimônio financeiro inicial
B109: =E109+D109 -> 45699 | D109: 16090 | E109: 29609 | F109: 0 | H109: 0 | I109: 29609 | J109: 0 | K109: A F.1 | L109: Ouro monetário e DES | M109: 0 | N109: 16090 | O109: 0 | P109: 0 | R109: 16090 | S109: 16323 | U109: =R109+S109 -> 32413
B110: =E110+D110 -> 4662110 | D110: 2319 | E110: 4659791 | F110: 1792185 | H110: 1576769 | I110: 912533 | J110: 378304 | K110: A F.2 | L110: Numerário e depósitos | M110: 0 | N110: 4057241 | O110: 443220 | P110: 0 | R110: 4500461 | S110: 161649 | U110: =R110+S110 -> 4662110
B111: =E111+D111 -> 283050 | D111: 0 | E111: 283050 | F111: 227934 | H111: 0 | I111: 54945 | J111: 171 | K111: A F.21 | L111: Numerário | M111: 0 | N111: 280685 | O111: 0 | P111: 0 | R111: 280685 | S111: 2365 | U111: =R111+S111 -> 283050
B112: =E112+D112 -> 1696873 | D112: 2303 | E112: 1694570 | F112: 95514 | H112: 1486884 | I112: 42465 | J112: 69707 | K112: A F.22 | L112: Depósito transferível | M112: 0 | N112: 1666528 | O112: 0 | P112: 0 | R112: 1666528 | S112: 30346 | U112: =R112+S112 -> 1696874
B113: =E113+D113 -> 2682187 | D113: 16 | E113: 2682171 | F113: 1468737 | H113: 89885 | I113: 815123 | J113: 308426 | K113: A F.29 | L113: Outros depósitos | M113: 0 | N113: 2110028 | O113: 443220 | P113: 0 | R113: 2553248 | S113: 128938 | U113: =R113+S113 -> 2682186
B114: =E114+D114 -> 11159145 | D114: 806978 | E114: 10352167 | F114: 855237 | H114: 112465 | I114: 8739111 | J114: 645354 | K114: A F.3 | L114: Títulos de dívidas | M114: 672520 | N114: 2443166 | O114: 6665333 | P114: 0 | R114: 9781019 | S114: 1378125 | U114: =R114+S114 -> 11159144
B115: =E115+D115 -> 1534426 | D115: 119469 | E115: 1414957 | F115: 102473 | H115: 14268 | I115: 1100457 | J115: 197759 | K115: A F.31 | L115: Curto prazo | M115: 11797 | N115: 460210 | O115: 1044340 | P115: 0 | R115: 1516347 | S115: 18079 | U115: =R115+S115 -> 1534426
B116: =E116+D116 -> 9624719 | D116: 687509 | E116: 8937210 | F116: 752764 | H116: 98197 | I116: 7638654 | J116: 447595 | K116: A F.32 | L116: Longo prazo | M116: 660723 | N116: 1982956 | O116: 5620993 | P116: 0 | R116: 8264672 | S116: 1360046 | U116: =R116+S116 -> 9624718
B117: =E117+D117 -> 9595462 | D117: 1352369 | E117: 8243093 | F117: 10581 | H117: 1700645 | I117: 6190849 | J117: 341018 | K117: A F.4 | L117: Empréstimos | M117: 2228168 | N117: 3897485 | O117: 978251 | P117: 2373288 | R117: 9477192 | S117: 118268 | U117: =R117+S117 -> 9595460
B118: =E118+D118 -> 3204862 | D118: 468379 | E118: 2736483 | F118: 485 | H118: 31810 | I118: 2670559 | J118: 33629 | K118: A F.41 | L118: Curto prazo | M118: 464832 | N118: 2494611 | O118: 39885 | P118: 196467 | R118: 3195795 | S118: 9066 | U118: =R118+S118 -> 3204861
B119: =E119+D119 -> 6390600 | D119: 883990 | E119: 5506610 | F119: 10096 | H119: 1668835 | I119: 3520290 | J119: 307389 | K119: A F.42 | L119: Longo prazo | M119: 1763336 | N119: 1402874 | O119: 938366 | P119: 2176821 | R119: 6281397 | S119: 109202 | U119: =R119+S119 -> 6390599
B120: =E120+D120 -> 24843791 | D120: 4042053 | E120: 20801738 | F120: 4290789 | H120: 802684 | I120: 11207969 | J120: 4500296 | K120: A F.5 | L120: Participações de capital e em fundos de investimentos | M120: 7955427 | N120: 15197659 | O120: 0 | P120: 0 | R120: 23153086 | S120: 1690705 | U120: =R120+S120 -> 24843791
...

Sheet CEIResumida
D2: S.14 Famílias | F2: S.13 Governo Geral | H2: S.12 Empresas finan- ceiras | J2: S.11 Empresas não- finan- ceiras | L2: Setor externo
D6: Entrada | E6: Saída | F6: Entrada | G6: Saída | H6: Entrada | I6: Saída | J6: Entrada | K6: Saída | L6: Entrada | M6: Saída
C7: Valor adicionado bruto/Produto interno bruto (1) | D7: =CEI!G16+CEI!F16 -> 1415200 | F7: =CEI!H16 -> 1146900 | H7: =CEI!I16+SimulTRU!I19 -> 518661 | J7: =CEI!J16+CEI!C15-SimulTRU!I19 -> 4528836 | L7: =CEI!S9 -> 1206009 | M7: =CEI!T10 -> 1252049 | N7: =SUM(D7:J7) -> 7609597 | O7: =CEI!B16 -> 7609597
C8: =CEI!L16 -> Valor adicionado bruto/Produto interno bruto (1) | D8: =SUM(CEI!P19:Q19) -> 2532554 | E8: =SUM(CEI!F19:G19) -> 171995 | G8: =CEI!H19 -> 780730 | I8: =CEI!I19 -> 140138 | K8: =CEI!J19 -> 1439098 | L8: =CEI!S18 -> 708 | M8: =CEI!D19 -> 1301 | N8: =D8+F8+H8+J8+L8-M8-K8-I8-G8-E8 -> 0
C9: =CEI!L21 -> Contribuições sociais efetivas | D9: =CEI!P21 -> 562617 | E9: =CEI!F21+CEI!G21 -> 12029 | G9: =CEI!H21 -> 150509 | I9: =CEI!I21 -> 41011 | K9: =CEI!J20 -> 359068 | N9: =D9+F9+H9+J9+L9-M9-K9-I9-G9-E9 -> 0
C10: Contribuições sociais inputadas | D10: =CEI!P22 -> 97765 | G10: =CEI!H22 -> 97765
C11: Impostos, líquidos de subsídios, sobre produtos | F11: =CEI!O24 -> 1014660 | I11: =SimulTRU!I19 -> 67488 | K11: =F11-I11 -> 947172 | N11: =D11+F11+H11+J11+L11-M11-K11-I11-G11-E11 -> 1.4551915e-11
C12: Outros impostos, líquidos de subsídios, sobre a produção | E12: =CEI!G25+CEI!F25 -> -1235 | F12: =CEI!O25 -> 86391 | G12: =CEI!H25 -> 278 | I12: =CEI!I25 -> 9262 | K12: =CEI!J25 -> 78086 | N12: =D12+F12+H12+J12+L12-M12-K12-I12-G12-E12 -> 0
C13: =CEI!L29 -> Juros | D13: =CEI!P29+CEI!Q29 -> 249546 | E13: =SUM(CEI!F29:G29) -> 205143 | F13: =CEI!O29 -> 191053 | G13: =CEI!H29 -> 446981 | H13: =CEI!N29 -> 1235025 | I13: =CEI!I29 -> 1060460 | J13: =CEI!M29 -> 246213 | K13: =CEI!J29 -> 282899 | L13: =CEI!S29 -> 106219 | M13: =CEI!D29 -> 32573 | N13: =D13+F13+H13+J13+L13-M13-K13-I13-G13-E13 -> 0
C14: =CEI!L30 -> Rendas distribuídas das empresas | D14: =SUM(CEI!P30:Q32) -> 580953 | E14: =SUM(CEI!F30:G36) -> 657 | F14: =SUM(CEI!O30:O32)+CEI!O36 -> 77198 | G14: 0 | H14: =CEI!N30+CEI!N31+CEI!N32 -> 113478 | I14: =SUM(CEI!I30:I32) -> 263487 | J14: =CEI!M30+CEI!M31+CEI!M32 -> 76697 | K14: =CEI!J30+CEI!J31+CEI!J36 -> 669888 | L14: =CEI!S30+CEI!S31+CEI!S32 -> 153572 | M14: =CEI!D30+CEI!D31 -> 67866 | N14: =D14+F14+H14+J14+L14-M14-K14-I14-G14-E14 -> 0
C15: =CEI!L31 -> Lucros reinvestidos de investimento estrangeiro direto | N15: =D15+F15+H15+J15+L15-M15-K15-I15-G15-E15 -> 0
C16: =CEI!L32 -> Desembolsos por rendas de investimentos | N16: =D16+F16+H16+J16+L16-M16-K16-I16-G16-E16 -> 0
C17: =CEI!L33 -> Rendimento de investimentos atribuído a detentores de apólices de seguros | N17: =D17+F17+H17+J17+L17-M17-K17-I17-G17-E17 -> 0
C18: =CEI!L37 -> Saldo das rendas primárias brutas/Renda nacional bruta (2) | D18: =SUM(D7:D17)-SUM(E7:E17) -> 5050046 | F18: =SUM(F7:F17)-SUM(G7:G17) -> 1039939 | H18: =SUM(H7:H17)-SUM(I7:I17) -> 285318 | J18: =SUM(J7:J17)-SUM(K7:K17) -> 1075535 | L18: =SUM(L7:L17)-SUM(M7:M17) -> 112719 | N18: =SUM(D18:K18) -> 7450838 | O18: =CEI!E37 -> 7450838
C20: Check | D20: =CEI!F37+CEI!G37 -> 5050046 | F20: =CEI!H37 -> 1039939 | H20: =CEI!I37 -> 285318 | J20: =CEI!J37 -> 1075535 | N20: =SUM(D20:M20) -> 7450838
D21: Entrada | E21: Saída | F21: Entrada | G21: Saída | H21: Entrada | I21: Saída | J21: Entrada | K21: Saída | L21: Entrada | M21: Saída
C22: Impostos correntes sobre a renda, patrimônio, etc. | E22: =SUM(CEI!F38:G38) -> 286813 | F22: =CEI!O38 -> 625041 | G22: =CEI!H38 -> 365 | I22: =CEI!I38 -> 42715 | K22: =CEI!J38 -> 295148 | N22: =D22+F22+H22+J22+L22-M22-K22-I22-G22-E22 -> 0
C23: Contribuições sociais | E23: =CEI!G39+CEI!F39 -> 895266 | F23: =CEI!O39 -> 800730 | H23: =CEI!N39 -> 94536 | N23: =D23+F23+H23+J23+L23-M23-K23-I23-G23-E23 -> 0
C24: Benefícios sociais, exceto transferências sociais em espécie | N24: =D24+F24+H24+J24+L24-M24-K24-I24-G24-E24 -> 0
C25: =CEI!L44 -> Benefícios de seguridade social em numerário | D25: =CEI!P44+CEI!Q44 -> 742258 | F25: =CEI!O44 -> 0 | G25: =CEI!H44 -> 742258 | I25: =CEI!I44 -> 0
C26: =CEI!L45 -> Outros benefícios de seguro social | D26: =CEI!P45+CEI!Q45 -> 670737 | F26: =CEI!O45 -> 0 | G26: =CEI!H45 -> 595999 | I26: =CEI!I45 -> 74738
C27: =CEI!L46 -> Benefícios de assistência social em numerário | D27: =CEI!P46+CEI!Q46 -> 414614 | F27: =CEI!O46 -> 0 | G27: =CEI!H46 -> 414614 | I27: =CEI!I46 -> 0
C28: Outras transferências correntes | D28: =CEI!P47+CEI!Q47 -> 153554 | E28: =CEI!G47+CEI!F47 -> 112621 | F28: =CEI!O47 -> 881244 | G28: =CEI!H47 -> 844896 | H28: =CEI!N47 -> 67100 | I28: =CEI!I47 -> 80387 | J28: =CEI!M47 -> 41947 | K28: =CEI!J47 -> 95043 | L28: =CEI!S47 -> 15517 | M28: =CEI!D47 -> 26415 | N28: =D28+F28+H28+J28+L28-M28-K28-I28-G28-E28 -> 0
C29: Renda nacional disponível bruta | D29: =D18+SUM(D22:D28)-SUM(E22:E28) -> 5736509 | F29: =F18+SUM(F22:F28)-SUM(G22:G28) -> 748822 | H29: =H18+SUM(H22:H28)-SUM(I22:I28) -> 249114 | J29: =J18+SUM(J22:J28)-SUM(K22:K28) -> 727291 | L29: =L18+SUM(L22:L28)-SUM(M22:M28) -> 101821 | N29: =D29+F29+H29+J29+L29-M29-K29-I29-G29-E29 -> 7563557
C30: Check | D30: =CEI!F53+CEI!G53 -> 5736509 | F30: =CEI!H53 -> 748822 | H30: =CEI!I53 -> 249114 | J30: =CEI!J53 -> 727291 | L30: =CEI!D61 -> 101821 | N30: =D30+F30+H30+J30+L30-M30-K30-I30-G30-E30 -> 7563557
D31: Entrada | E31: Saída | F31: Entrada | G31: Saída | H31: Entrada | I31: Saída | J31: Entrada | K31: Saída | L31: Entrada | M31: Saída
C32: Consumo final efetivo | E32: =CEI!G58+CEI!F58 -> 4805004 | G32: =CEI!H58 -> 1532204 | N32: =D32+F32+H32+J32+L32-M32-K32-I32-G32-E32 -> -6337208
C33: Ajustamento pela variação dos direitos de pensão | D33: =CEI!P59 -> 47061 | G33: =CEI!H59 -> 28647 | I33: =CEI!I59 -> 18414 | N33: =D33+F33+H33+J33+L33-M33-K33-I33-G33-E33 -> 0
C34: Poupança bruta | D34: =D29+SUM(D32:D33)-SUM(E32:E33) -> 978566 | F34: =F29+SUM(F32:F33)-SUM(G32:G33) -> -812029 | H34: =H29+SUM(H32:H33)-SUM(I32:I33) -> 230700 | J34: =J29+SUM(J32:J33)-SUM(K32:K33) -> 727291 | L34: =L29+SUM(L32:L33)-SUM(M32:M33) -> 101821 | N34: =D34+F34+H34+J34+L34-M34-K34-I34-G34-E34 -> 1226349
D35: Entrada | E35: Saída | F35: Entrada | G35: Saída | H35: Entrada | I35: Saída | J35: Entrada | K35: Saída | L35: Entrada | M35: Saída
C36: Formação bruta de capital fixo | E36: =CEI!F66+CEI!G66 -> 410010 | G36: =CEI!H66 -> 139686 | I36: =CEI!I66 -> 13718 | K36: =CEI!J66 -> 696813 | N36: =D36+F36+H36+J36+L36-M36-K36-I36-G36-E36 -> -1260227
C37: Variação de estoques | K37: =CEI!J67 -> -33878 | N37: =D37+F37+H37+J37+L37-M37-K37-I37-G37-E37 -> 33878
C38: Aquisições líquidas de cessões de ativos não-produzidos // Transferências | D38: =SUM(CEI!P68:Q70) -> -6284 | E38: =SUM(CEI!F68:G70) -> 0 | F38: =SUM(CEI!O68:O70) -> 27118 | G38: =SUM(CEI!H68:H70) -> -6588 | H38: =SUM(CEI!N68:N71) -> -65 | I38: =SUM(CEI!I68:I70) -> 0 | J38: =SUM(CEI!M68:M70) -> -208 | K38: =SUM(CEI!J68:J70) -> 5866 | L38: =SUM(CEI!S68:S71) -> -20561 | M38: =SUM(CEI!D68:D70) -> 722 | N38: =D38+F38+H38+J38+L38-M38-K38-I38-G38-E38 -> 0
C39: Capacidade (+) / Necessidade(-) líquida de financiamento | D39: =D34+SUM(D36:D38)-SUM(E36:E38) -> 562272 | F39: =F34+SUM(F36:F38)-SUM(G36:G38) -> -918009 | H39: =H34+SUM(H36:H38)-SUM(I36:I38) -> 216917 | J39: =J34+SUM(J36:J38)-SUM(K36:K38) -> 58282 | L39: =L34+SUM(L36:L38)-SUM(M36:M38) -> 80538 | N39: =D39+F39+H39+J39+L39-M39-K39-I39-G39-E39 -> 0
C40: Check | D40: =CEI!F71+CEI!G71 -> 562272 | F40: =CEI!H71 -> -918009 | H40: =CEI!I71 -> 216917 | J40: =CEI!J71 -> 58282 | L40: =CEI!D71 -> 80538 | N40: =SUM(D40:M40) -> 0
D42: S.14 Famílias | F42: S.13 Governo Geral | H42: S.12 Empresas finan- ceiras | J42: S.11 Empresas não- finan- ceiras | L42: Setor externo
D46: Entrada | E46: Saída | F46: Entrada | G46: Saída | H46: Entrada | I46: Saída | J46: Entrada | K46: Saída | L46: Entrada | M46: Saída | O46: VA preço mercado | P46: VA preço básico
C47: Valor adicionado bruto/Produto interno bruto (1) | D47: =D7 -> 1415200 | E47: =E7 -> 0 | F47: =F7 -> 1146900 | G47: =G7 -> 0 | H47: =H7 -> 518661 | I47: =I7 -> 0 | J47: =J7 -> 4528836 | K47: =K7 -> 0 | ... M47: =M7 -> 1252049 | N47: =D47+F47+H47+J47+L47-M47-K47-I47-G47-E47 -> 7563557 | O47: =H47+J47+D47+F47 -> 7609597 | P47: =O47-K51 -> 6662425
C48: Salários | D48: =D8 -> 2532554 | E48: =E8 -> 171995 | F48: =F8 -> 0 | G48: =G8 -> 780730 | H48: =H8 -> 0 | I48: =I8 -> 140138 | J48: =J8 -> 0 | K48: =K8 -> 1439098 | ... M48: =M8 -> 1301 | N48: =D48+F48+H48+J48+L48-M48-K48-I48-G48-E48 -> 0
C49: =C9 -> Contribuições sociais efetivas | D49: =D9 -> 562617 | E49: =E9 -> 12029 | F49: =F9 -> 0 | G49: =G9 -> 150509 | H49: =H9 -> 0 | I49: =I9 -> 41011 | J49: =J9 -> 0 | ... M49: =M9 -> 0 | N49: =D49+F49+H49+J49+L49-M49-K49-I49-G49-E49 -> 0
C50: Contribuições sociais inputadas | D50: =D10 -> 97765 | E50: =E10 -> 0 | F50: =F10 -> 0 | G50: =G10 -> 97765 | H50: =H10 -> 0 | I50: =I10 -> 0 | J50: =J10 -> 0 | K50: =K10 -> 0 | ... M50: =M10 -> 0
C51: Impostos, líquidos de subsídios, sobre produtos | D51: =D11 -> 0 | E51: =E11 -> 0 | F51: =F11 -> 1014660 | G51: =G11 -> 0 | H51: =H11 -> 0 | I51: =I11 -> 67488 | J51: =J11 -> 0 | K51: =K11 -> 947172 | ... M51: =M11 -> 0 | N51: =D51+F51+H51+J51+L51-M51-K51-I51-G51-E51 -> 1.4551915e-11
C52: Outros impostos, líquidos de subsídios, sobre a produção | D52: =D12 -> 0 | E52: =E12 -> -1235 | F52: =F12 -> 86391 | G52: =G12 -> 278 | H52: =H12 -> 0 | I52: =I12 -> 9262 | J52: =J12 -> 0 | K52: =K12 -> 78086 | ... M52: =M12 -> 0 | N52: =D52+F52+H52+J52+L52-M52-K52-I52-G52-E52 -> 0
C53: Juros | D53: =D13 -> 249546 | E53: =E13 -> 205143 | F53: =F13 -> 191053 | G53: =G13 -> 446981 | H53: =H13 -> 1235025 | I53: =I13 -> 1060460 | J53: =J13 -> 246213 | K53: =K13 -> 282899 | ... M53: =M13 -> 32573 | N53: =D53+F53+H53+J53+L53-M53-K53-I53-G53-E53 -> 0
C54: Rendas distribuídas das empresas | D54: =D14 -> 580953 | E54: =E14 -> 657 | F54: =F14 -> 77198 | G54: =G14 -> 0 | H54: =H14 -> 113478 | I54: =I14 -> 263487 | J54: =J14 -> 76697 | K54: =K14 -> 669888 | ... M54: =M14 -> 67866 | N54: =D54+F54+H54+J54+L54-M54-K54-I54-G54-E54 -> 0
C55: Lucros reinvestidos de investimento estrangeiro direto | D55: =D15 -> 0 | E55: =E15 -> 0 | F55: =F15 -> 0 | G55: =G15 -> 0 | H55: =H15 -> 0 | I55: =I15 -> 0 | J55: =J15 -> 0 | K55: =K15 -> 0 | ... M55: =M15 -> 0 | N55: =D55+F55+H55+J55+L55-M55-K55-I55-G55-E55 -> 0
C56: Desembolsos por rendas de investimentos | D56: =D16 -> 0 | E56: =E16 -> 0 | F56: =F16 -> 0 | G56: =G16 -> 0 | H56: =H16 -> 0 | I56: =I16 -> 0 | J56: =J16 -> 0 | K56: =K16 -> 0 | ... M56: =M16 -> 0 | N56: =D56+F56+H56+J56+L56-M56-K56-I56-G56-E56 -> 0
C57: Renda de recursos naturais | D57: =D17 -> 0 | E57: =E17 -> 0 | F57: =F17 -> 0 | G57: =G17 -> 0 | H57: =H17 -> 0 | I57: =I17 -> 0 | J57: =J17 -> 0 | K57: =K17 -> 0 | ... M57: =M17 -> 0 | N57: =D57+F57+H57+J57+L57-M57-K57-I57-G57-E57 -> 0
C58: Impostos correntes sobre a renda, patrimônio, etc. | D58: =D22 -> 0 | E58: =E22 -> 286813 | F58: =F22 -> 625041 | G58: =G22 -> 365 | H58: =H22 -> 0 | I58: =I22 -> 42715 | J58: =J22 -> 0 | K58: =K22 -> 295148 | ... M58: =M22 -> 0 | N58: =D58+F58+H58+J58+L58-M58-K58-I58-G58-E58 -> 0
C59: Contribuições sociais | D59: =D23 -> 0 | E59: =E23 -> 895266 | F59: =F23 -> 800730 | G59: =G23 -> 0 | H59: =H23 -> 94536 | I59: =I23 -> 0 | J59: =J23 -> 0 | K59: =K23 -> 0 | ... M59: =M23 -> 0 | N59: =D59+F59+H59+J59+L59-M59-K59-I59-G59-E59 -> 0
C60: Benefícios de seguridade social em numerário // Seguro desemprego, bolsa família | D60: =D25+D27 -> 1156872 | E60: =E25+E27 -> 0 | F60: =F25+F27 -> 0 | G60: =G25+G27 -> 1156872 | H60: =H25+H27 -> 0 | I60: =I25+I27 -> 0 | J60: =J25+J27 -> 0 | K60: =K25+K27 -> 0 | ... M60: =M25+M27 -> 0 | N60: =D60+F60+H60+J60+L60-M60-K60-I60-G60-E60 -> 0
C61: Outros benefícios de seguro social // Previdência | D61: =D26 -> 670737 | E61: =E26 -> 0 | F61: =F26 -> 0 | G61: =G26 -> 595999 | H61: =H26 -> 0 | I61: =I26 -> 74738 | J61: =J26 -> 0 | K61: =K26 -> 0 | ... M61: =M26 -> 0 | N61: =D61+F61+H61+J61+L61-M61-K61-I61-G61-E61 -> 0
C62: Outras transferências correntes | D62: =D28 -> 153554 | E62: =E28 -> 112621 | F62: =F28 -> 881244 | G62: =G28 -> 844896 | H62: =H28 -> 67100 | I62: =I28 -> 80387 | J62: =J28 -> 41947 | K62: =K28 -> 95043 | ... M62: =M28 -> 26415 | N62: =D62+F62+H62+J62+L62-M62-K62-I62-G62-E62 -> 0
C63: Consumo final efetivo | D63: =D32 -> 0 | E63: =E32 -> 4805004 | F63: =F32 -> 0 | G63: =G32 -> 1532204 | H63: =H32 -> 0 | I63: =I32 -> 0 | J63: =J32 -> 0 | K63: =K32 -> 0 | ... M63: =M32 -> 0 | N63: =D63+F63+H63+J63+L63-M63-K63-I63-G63-E63 -> -6337208
C64: Ajustamento pela variação dos direitos de pensão | D64: =D33 -> 47061 | E64: =E33 -> 0 | F64: =F33 -> 0 | G64: =G33 -> 28647 | H64: =H33 -> 0 | I64: =I33 -> 18414 | J64: =J33 -> 0 | K64: =K33 -> 0 | ... M64: =M33 -> 0 | N64: =D64+F64+H64+J64+L64-M64-K64-I64-G64-E64 -> 0
C65: Formação bruta de capital fixo | D65: =D36 -> 0 | E65: =E36 -> 410010 | F65: =F36 -> 0 | G65: =G36 -> 139686 | H65: =H36 -> 0 | I65: =I36 -> 13718 | J65: =J36 -> 0 | K65: =K36 -> 696813 | ... M65: =M36 -> 0 | N65: =D65+F65+H65+J65+L65-M65-K65-I65-G65-E65 -> -1260227
C66: Variação de estoques | D66: =D37 -> 0 | E66: =E37 -> 0 | F66: =F37 -> 0 | G66: =G37 -> 0 | H66: =H37 -> 0 | I66: =I37 -> 0 | J66: =J37 -> 0 | K66: =K37 -> -33878 | ... M66: =M37 -> 0 | N66: =D66+F66+H66+J66+L66-M66-K66-I66-G66-E66 -> 33878
C67: Aquisições líquidas de cessões de ativos não-produzidos | D67: =D38 -> -6284 | E67: =E38 -> 0 | F67: =F38 -> 27118 | G67: =G38 -> -6588 | H67: =H38 -> -65 | I67: =I38 -> 0 | J67: =J38 -> -208 | K67: =K38 -> 5866 | L67: =SUM(CEI!S68:S70) -> -20561 | M67: =SUM(CEI!D68:D70) -> 722 | N67: =D67+F67+H67+J67+L67-M67-K67-I67-G67-E67 -> 0
C68: Capacidade (+) / Necessidade(-) líquida de financiamento | D68: =SUM(D47:D67)-SUM(E47:E67) -> 562272 | F68: =SUM(F47:F67)-SUM(G47:G67) -> -918009 | H68: =SUM(H47:H67)-SUM(I47:I67) -> 216917 | J68: =SUM(J47:J67)-SUM(K47:K67) -> 58282 | L68: =SUM(L47:L67)-SUM(M47:M67) -> 80538 | N68: =D68+F68+H68+J68+L68-M68-K68-I68-G68-E68 -> 0
S69: 09 Atividades financeiras, de seguros e serviços relacionados
C70: VA - salários e contr | D70: =D47-E48-E49 -> 1231176 | F70: =F47-G48-G49 -> 215661 | J70: Outros impostos | K70: =E52+G52 -> -957
D75: S.14 Famílias | F75: S.13 Governo Geral | H75: S.12 Empresas finan- ceiras | J75: S.11 Empresas não- finan- ceiras | L75: Setor externo | S75: Famílias | T75: Total
R76: Produção | S76: 5 157 | T76: 700 903
R77: Produção mercantil | S77: 5 157 | T77: 697 374
R78: Produção não-mercantil | S78: 0 | T78: 3 529
D79: Entrada | E79: Saída | F79: Entrada | G79: Saída | H79: Entrada | I79: Saída | J79: Entrada | K79: Saída | L79: Entrada | M79: Saída | O79: VA preço mercado | P79: VA preço básico | R79: Consumo intermediário | S79: 1 780 | T79: 246 353
C80: Valor adicionado bruto/Produto interno bruto (1) | E80: =E47 -> 0 | G80: =G47 -> 0 | H80: =H47+S80 -> 522038 | I80: =I47 -> 0 | J80: =J47+D47+F47-S80 -> 7087559 | K80: =K47 -> 0 | L80: =L47 -> 1206009 | M80: =M47 -> 1252049 | N80: =D80+F80+H80+J80+L80-M80-K80-I80-G80-E80 -> 7563557 | O80: =H80+J80 -> 7609597 | P80: =O80-K84 -> 6662425 | R80: Valor adicionado bruto | S80: 3377 | T80: 454 550
C81: Salários | D81: =D48+L48-M48 -> 2531961 | E81: 0 | F81: =F48 -> 0 | H81: =H48 -> 0 | I81: =I48+S82 -> 140274 | J81: =J48 -> 0 | K81: =K48+E48+G48-S82 -> 2391687 | L81: 0 | M81: 0 | N81: =D81+F81+H81+J81+L81-M81-K81-I81-G81-E81 -> 0 | R81: Remuneração dos empregados | S81: 136 | T81: 181 285
C82: Contribuições sociais efetivas | D82: =D49 -> 562617 | E82: 0 | F82: =F49 -> 0 | H82: =H49 -> 0 | I82: =I49 -> 41011 | J82: =J49 -> 0 | K82: =K49+E49+G49 -> 521606 | L82: =L49 -> 0 | M82: =M49 -> 0 | N82: =D82+F82+H82+J82+L82-M82-K82-I82-G82-E82 -> 0 | R82: Salários | S82: 136 | T82: 140 274
C83: Contribuições sociais inputadas | D83: 0 | E83: =E50 -> 0 | F83: =F50 -> 0 | G83: 0 | H83: =H50 -> 0 | I83: =I50 -> 0 | J83: =J50 -> 0 | K83: =K50 -> 0 | L83: =L50 -> 0 | M83: =M50 -> 0 | N83: =D83+F83+H83+J83+L83-M83-K83-I83-G83-E83 -> 0
C84: Impostos, líquidos de subsídios, sobre produtos | D84: =D51 -> 0 | E84: =E51 -> 0 | F84: =F51 -> 1014660 | G84: =G51 -> 0 | H84: =H51 -> 0 | I84: =I51 -> 67488 | J84: =J51 -> 0 | K84: =K51 -> 947172 | ... M84: =M51 -> 0 | N84: =D84+F84+H84+J84+L84-M84-K84-I84-G84-E84 -> 1.4551915e-11 | R84: Contribuições sociais dos empregadores | S84: 0 | T84: 41 011
C85: Outros impostos, líquidos de subsídios, sobre a produção | D85: =D52 -> 0 | E85: 0 | F85: =F52 -> 86391 | G85: 0 | H85: =H52 -> 0 | I85: =I52 -> 9262 | J85: =J52 -> 0 | K85: =K52+G52+E52 -> 77129 | L85: =L52 -> 0 | M85: =M52 -> 0 | N85: =D85+F85+H85+J85+L85-M85-K85-I85-G85-E85 -> 0 | R85: Outros impostos, líquidos de subsídios, sobre a produção | S85: 0 | T85: 9 262
C86: Juros | D86: =D53 -> 249546 | E86: =E53 -> 205143 | F86: =F53 -> 191053 | G86: =G53 -> 446981 | H86: =H53 -> 1235025 | I86: =I53 -> 1060460 | J86: =J53 -> 246213 | K86: =K53 -> 282899 | ... M86: =M53 -> 32573 | N86: =D86+F86+H86+J86+L86-M86-K86-I86-G86-E86 -> 0 | R86: Excedente operacional bruto | S86: 0 | T86: 260 762
C87: Rendas distribuídas das empresas | D87: =D54+D70-E54+F54 -> 1888670 | E87: 0 | F87: 0 | G87: =G54 -> 0 | H87: 0 | I87: =I54-H54+S87 -> 153250 | J87: 0 | K87: =K54+D70-J54-S87 -> 1821126 | L87: =L54-M54 -> 85706 | M87: 0 | N87: =D87+F87+H87+J87+L87-M87-K87-I87-G87-E87 -> 0 | R87: Rendimento misto bruto | S87: 3241 | T87: 3 241
C88: Lucros reinvestidos de investimento estrangeiro direto | D88: =D55 -> 0 | E88: =E55 -> 0 | F88: =F55 -> 0 | G88: =G55 -> 0 | H88: =H55 -> 0 | I88: =I55 -> 0 | J88: =J55 -> 0 | K88: =K55 -> 0 | ... M88: =M55 -> 0 | N88: =D88+F88+H88+J88+L88-M88-K88-I88-G88-E88 -> 0 | R88: Ocupações | S88: 89 346 | T88: 1 410 816
C89: Desembolsos por rendas de investimentos | D89: =D56 -> 0 | E89: =E56 -> 0 | F89: =F56 -> 0 | G89: =G56 -> 0 | H89: =H56 -> 0 | I89: =I56 -> 0 | J89: =J56 -> 0 | K89: =K56 -> 0 | ... M89: =M56 -> 0 | N89: =D89+F89+H89+J89+L89-M89-K89-I89-G89-E89 -> 0
C90: Renda de recursos naturais | D90: =D57 -> 0 | E90: =E57 -> 0 | F90: =F57 -> 0 | G90: =G57 -> 0 | H90: =H57 -> 0 | I90: =I57 -> 0 | J90: =J57 -> 0 | K90: =K57 -> 0 | ... M90: =M57 -> 0 | N90: =D90+F90+H90+J90+L90-M90-K90-I90-G90-E90 -> 0
C91: Impostos correntes sobre a renda, patrimônio, // Contribuições sociais // Outras transferências | D91: =D58 -> 0 | E91: =E58+F54+E52 -> 362776 | F91: =F58+F70+F54-G58+E52-K70 -> 917257 | G91: 0 | H91: =H58 -> 0 | I91: =I58 -> 42715 | J91: =J58 -> 0 | K91: =K58+F70-K70 -> 511766 | L91: =L58 -> 0 | M91: =M58 -> 0 | N91: =D91+F91+H91+J91+L91-M91-K91-I91-G91-E91 -> 0
C92: Contribuições sociais | D92: =D59 -> 0 | E92: =E59 -> 895266 | F92: =F59 -> 800730 | G92: =G59 -> 0 | H92: =H59 -> 94536 | I92: =I59 -> 0 | J92: =J59 -> 0 | K92: =K59 -> 0 | ... M92: =M59 -> 0 | N92: =D92+F92+H92+J92+L92-M92-K92-I92-G92-E92 -> 0
C93: Benefícios de seguridade social em numerário // Seguro desemprego, bolsa família | D93: =D60+D50 -> 1254637 | E93: =E60 -> 0 | F93: =F60 -> 0 | G93: =G60+G50 -> 1254637 | H93: =H60 -> 0 | I93: =I60 -> 0 | J93: =J60 -> 0 | K93: =K60 -> 0 | L93: =L60 -> 0 | M93: =M60 -> 0 | N93: =D93+F93+H93+J93+L93-M93-K93-I93-G93-E93 -> 0
C94: Outros benefícios de seguro social // Previdência | D94: =D61+D64 -> 717798 | E94: =E61 -> 0 | F94: =F61 -> 0 | G94: =G61+G64 -> 624646 | H94: =H61 -> 0 | I94: =I61+I64 -> 93152 | J94: =J61 -> 0 | K94: =K61 -> 0 | L94: =L61 -> 0 | M94: =M61 -> 0 | N94: =D94+F94+H94+J94+L94-M94-K94-I94-G94-E94 -> 0
C95: Outras transferências correntes | D95: =D62-E62+D67+(M48-L48) -> 35242 | E95: 0 | F95: =F62-G62+F67-G67 -> 70054 | G95: 0 | H95: 0 | I95: =I62-H62-H67 -> 13352 | J95: 0 | K95: =K62-J62+K67-J67 -> 59170 | L95: 0 | M95: =M62-L62-L67+M67+M48-L48 -> 32774 | N95: =D95+F95+H95+J95+L95-M95-K95-I95-G95-E95 -> 0
C96: Consumo final efetivo | D96: =D63 -> 0 | E96: =E63 -> 4805004 | F96: =F63 -> 0 | G96: =G63 -> 1532204 | H96: =H63 -> 0 | I96: =I63 -> 0 | J96: =J63 -> 0 | K96: =K63 -> 0 | ... M96: =M63 -> 0 | N96: =D96+F96+H96+J96+L96-M96-K96-I96-G96-E96 -> -6337208
C97: Ajustamento pela variação dos direitos de pensão | D97: 0 | E97: =E64 -> 0 | F97: =F64 -> 0 | G97: 0 | H97: =H64 -> 0 | J97: =J64 -> 0 | K97: =K64 -> 0 | L97: =L64 -> 0 | M97: =M64 -> 0 | N97: =D97+F97+H97+J97+L97-M97-K97-I97-G97-E97 -> 0
C98: Formação bruta de capital fixo | D98: =D65 -> 0 | E98: =E65 -> 410010 | F98: =F65 -> 0 | G98: =G65 -> 139686 | H98: =H65 -> 0 | I98: =I65 -> 13718 | J98: =J65 -> 0 | K98: =K65 -> 696813 | ... M98: =M65 -> 0 | N98: =D98+F98+H98+J98+L98-M98-K98-I98-G98-E98 -> -1260227
C99: Variação de estoques | D99: =D66 -> 0 | E99: =E66 -> 0 | F99: =F66 -> 0 | G99: =G66 -> 0 | H99: =H66 -> 0 | I99: =I66 -> 0 | J99: =J66 -> 0 | K99: =K66 -> -33878 | ... M99: =M66 -> 0 | N99: =D99+F99+H99+J99+L99-M99-K99-I99-G99-E99 -> 33878
C100: Aquisições líquidas de cessões de ativos não-produzidos | D100: 0 | E100: =E67 -> 0 | H100: 0 | I100: =I67 -> 0 | J100: 0 | K100: 0 | L100: 0 | M100: 0 | N100: =D100+F100+H100+J100+L100-M100-K100-I100-G100-E100 -> 0
C101: Capacidade (+) / Necessidade(-) líquida de financiamento | D101: =SUM(D80:D100)-SUM(E80:E100) -> 562272 | F101: =SUM(F80:F100)-SUM(G80:G100) -> -918009 | H101: =SUM(H80:H100)-SUM(I80:I100) -> 216917 | J101: =SUM(J80:J100)-SUM(K80:K100) -> 58282 | L101: =SUM(L80:L100)-SUM(M80:M100) -> 80538 | N101: =D101+F101+H101+J101+L101-M101-K101-I101-G101-E101 -> 0
C103: Check | D103: =D68-D101 -> 0 | F103: =F68-F101 -> 0 | H103: =H68-H101 -> 0 | J103: =J68-J101 -> 0 | L103: =L68-L101 -> 0
C105: Ajustes: | H105: Ajustes
C106: Famílias sem VA. Valor todo para empresas não-financeiras e financeiras | H106: VA, salários e contribuições de famílias e governo para empresas não financeiras e financeiras
C107: Famílias sem custo com salários e contribuições sociais. Valores distribuidos para empresas, seguindo proporção observada nas famílias | H107: Compensado c/ empresas pagando + rendas para famílias
C108: Setor externo sem pagar ou receber salários. Valores enviados para famílias | H108: Compensado governo com pagamento de impostos das empresas
C109: Governo e família não pagam Outros impostos sobre produção | H109: Rendas das empresas para governo dirigido para famílias. Compensado com aumento de tributos das famílias pago para governo
C110: Famílias apenas recebem renda de empresas. Não pagam. | H110: Outras transferências é considerado apenas o saldo
C111: Governo não recebe renda de empresas. Isso é compensado supondo que tudo é dirigido às famílias e elas pagam o governo na forma de IR. | H111: Aquisições líquidas de cessões de ativos em outras transferências
C112: Empresas apenas pagam renda para outros setores. Sem fluxos intraempresas de lucros. | H112: Sem impostos sobre prod para governo e famílioas
C113: Setor externo apenas recebe lucros, sem saída de setor externo (entrada de K no país) | H113: Ajustamento direito de pensão dentro de benegício previdência
C114: Empresas não pagam benefícios sociais. Feito apenas por governo. Isso é compensado com despesa de benefícios das empresas se tornando pagamento de imposto ao governo. Por sua vez, despesas do governo com benefícios é aumentada
C115: Outras transferências é assumido que existe apenas saída ou entrada (é calculado o saldo do fluxo)
...

Sheet Python
B1: Household | C1: Household | D1: Gov | E1: Gov | F1: Ffirms | G1: Ffirms | H1: Firms | I1: Firms | J1: ExtSector | K1: ExtSector
B2: Entrada | C2: Saída | D2: Entrada | E2: Saída | F2: Entrada | G2: Saída | H2: Entrada | I2: Saída | J2: Entrada | K2: Saída
A3: Valor adicionado bruto/Produto interno bruto (1) | C3: 0 | E3: 0 | F3: 522038 | G3: 0 | H3: 7087559 | I3: 0 | J3: 1206009 | K3: 1252049
A4: Salários | B4: 2531961 | C4: 0 | D4: 0 | F4: 0 | G4: 140274 | H4: 0 | I4: 2391687 | J4: 0 | K4: 0
A5: Contribuições sociais efetivas | B5: 562617 | C5: 0 | D5: 0 | F5: 0 | G5: 41011 | H5: 0 | I5: 521606 | J5: 0 | K5: 0
A6: Contribuições sociais inputadas | B6: 0 | C6: 0 | D6: 0 | E6: 0 | F6: 0 | G6: 0 | H6: 0 | I6: 0 | J6: 0 | K6: 0
A7: Impostos, líquidos de subsídios, sobre produtos | B7: 0 | C7: 0 | D7: 1014660 | E7: 0 | F7: 0 | G7: 67488 | H7: 0 | I7: 947172 | J7: 0 | K7: 0
A8: Outros impostos, líquidos de subsídios, sobre a produção | B8: 0 | C8: 0 | D8: 86391 | E8: 0 | F8: 0 | G8: 9262 | H8: 0 | I8: 77129 | J8: 0 | K8: 0
A9: Juros | B9: 249546 | C9: 205143 | D9: 191053 | E9: 446981 | F9: 1235025 | G9: 1060460 | H9: 246213 | I9: 282899 | J9: 106219 | K9: 32573
A10: Rendas distribuídas das empresas | B10: 1888670 | C10: 0 | D10: 0 | E10: 0 | F10: 0 | G10: 153250 | H10: 0 | I10: 1821126 | J10: 85706 | K10: 0
A11: Lucros reinvestidos de investimento estrangeiro direto | B11: 0 | C11: 0 | D11: 0 | E11: 0 | F11: 0 | G11: 0 | H11: 0 | I11: 0 | J11: 0 | K11: 0
A12: Desembolsos por rendas de investimentos | B12: 0 | C12: 0 | D12: 0 | E12: 0 | F12: 0 | G12: 0 | H12: 0 | I12: 0 | J12: 0 | K12: 0
A13: Renda de recursos naturais | B13: 0 | C13: 0 | D13: 0 | E13: 0 | F13: 0 | G13: 0 | H13: 0 | I13: 0 | J13: 0 | K13: 0
A14: Impostos correntes sobre a renda, patrimônio, // Contribuições sociais // Outras transferências | B14: 0 | C14: 362776 | D14: 917257 | E14: 0 | F14: 0 | G14: 42715 | H14: 0 | I14: 511766 | J14: 0 | K14: 0
A15: Contribuições sociais | B15: 0 | C15: 895266 | D15: 800730 | E15: 0 | F15: 94536 | G15: 0 | H15: 0 | I15: 0 | J15: 0 | K15: 0
A16: Benefícios de seguridade social em numerário // Seguro desemprego, bolsa família | B16: 1254637 | C16: 0 | D16: 0 | E16: 1254637 | F16: 0 | G16: 0 | H16: 0 | I16: 0 | J16: 0 | K16: 0
A17: Outros benefícios de seguro social // Previdência | B17: 717798 | C17: 0 | D17: 0 | E17: 624646 | F17: 0 | G17: 93152 | H17: 0 | I17: 0 | J17: 0 | K17: 0
... A19: Consumo final efetivo | B19: 0 | C19: 4805004 | D19: 0 | E19: 1532204 | F19: 0 | G19: 0 | H19: 0 | I19: 0 | J19: 0 | K19: 0
A20: Ajustamento pela variação dos direitos de pensão | B20: 0 | C20: 0 | D20: 0 | E20: 0 | F20: 0 | H20: 0 | I20: 0 | J20: 0 | K20: 0
A21: Formação bruta de capital fixo | B21: 0 | C21: 410010 | D21: 0 | E21: 139686 | F21: 0 | G21: 13718 | H21: 0 | I21: 696813 | J21: 0 | K21: 0
A22: Variação de estoques | B22: 0 | C22: 0 | D22: 0 | E22: 0 | F22: 0 | G22: 0 | H22: 0 | I22: -33878 | J22: 0 | K22: 0
A23: Aquisições líquidas de cessões de ativos não-produzidos | B23: 0 | C23: 0 | F23: 0 | G23: 0 | H23: 0 | I23: 0 | J23: 0 | K23: 0
A24: Capacidade (+) / Necessidade(-) líquida de financiamento | B24: =SUM(B3:B23)-SUM(C3:C23) -> 562272 | D24: =SUM(D3:D23)-SUM(E3:E23) -> -918009 | F24: =SUM(F3:F23)-SUM(G3:G23) -> 216917 | H24: =SUM(H3:H23)-SUM(I3:I23) -> 58282 | J24: =SUM(J3:J23)-SUM(K3:K23) -> 80538

Sheet ParâmetrosCEI
C2: S.14 Famílias | E2: S.13 Governo Geral | G2: S.12 Empresas finan- ceiras | I2: S.11 Empresas não- finan- ceiras | K2: Setor externo
C6: Entrada | D6: Saída | E6: Entrada | F6: Saída | G6: Entrada | H6: Saída | I6: Entrada | J6: Saída | K6: Entrada | L6: Saída | N6: VA preço mercado | O6: VA preço básico
B7: Valor adicionado bruto/Produto interno bruto (1) | C7: =CEIResumida!D80 -> 0 | D7: =CEIResumida!E80 -> 0 | E7: =CEIResumida!F80 -> 0 | F7: =CEIResumida!G80 -> 0 | G7: =CEIResumida!H80 -> 522038 | H7: =CEIResumida!I80 -> 0 | I7: =CEIResumida!J80 -> 7087559 | J7: =CEIResumida!K80 -> 0 | ... L7: =CEIResumida!M80 -> 1252049 | N7: =G7+I7 -> 7609597 | O7: =N7-J11 -> 6662425
A8: Tabela de Usos e Recursos - específico por setor - geração de renda | B8: Salários | C8: =CEIResumida!D81 -> 2531961 | D8: =CEIResumida!E81 -> 0 | E8: =CEIResumida!F81 -> 0 | F8: =CEIResumida!G81 -> 0 | G8: =CEIResumida!H81 -> 0 | H8: =CEIResumida!I81 -> 140274 | I8: =CEIResumida!J81 -> 0 | J8: =CEIResumida!K81 -> 2391687 | ... L8: =CEIResumida!M81 -> 0
B9: Contribuições sociais efetivas | C9: =CEIResumida!D82 -> 562617 | D9: =CEIResumida!E82 -> 0 | E9: =CEIResumida!F82 -> 0 | F9: =CEIResumida!G82 -> 0 | G9: =CEIResumida!H82 -> 0 | H9: =CEIResumida!I82 -> 41011 | I9: =CEIResumida!J82 -> 0 | J9: =CEIResumida!K82 -> 521606 | ... L9: =CEIResumida!M82 -> 0
B10: Contribuições sociais inputadas | C10: =CEIResumida!D83 -> 0 | D10: =CEIResumida!E83 -> 0 | E10: =CEIResumida!F83 -> 0 | F10: =CEIResumida!G83 -> 0 | G10: =CEIResumida!H83 -> 0 | H10: =CEIResumida!I83 -> 0 | I10: =CEIResumida!J83 -> 0 | J10: =CEIResumida!K83 -> 0 | ... L10: =CEIResumida!M83 -> 0
B11: Impostos, líquidos de subsídios, sobre produtos | C11: =CEIResumida!D84 -> 0 | D11: =CEIResumida!E84 -> 0 | E11: =CEIResumida!F84 -> 1014660 | F11: =CEIResumida!G84 -> 0 | G11: =CEIResumida!H84 -> 0 | H11: =CEIResumida!I84 -> 67488 | I11: =CEIResumida!J84 -> 0 | J11: =CEIResumida!K84 -> 947172 | ... L11: =CEIResumida!M84 -> 0
B12: Outros impostos, líquidos de subsídios, sobre a produção | C12: =CEIResumida!D85 -> 0 | D12: =CEIResumida!E85 -> 0 | E12: =CEIResumida!F85 -> 86391 | F12: =CEIResumida!G85 -> 0 | G12: =CEIResumida!H85 -> 0 | H12: =CEIResumida!I85 -> 9262 | I12: =CEIResumida!J85 -> 0 | J12: =CEIResumida!K85 -> 77129 | ... L12: =CEIResumida!M85 -> 0
A13: Alocação primária do excedente | B13: Juros | C13: =CEIResumida!D86 -> 249546 | D13: =CEIResumida!E86 -> 205143 | E13: =CEIResumida!F86 -> 191053 | F13: =CEIResumida!G86 -> 446981 | G13: =CEIResumida!H86 -> 1235025 | H13: =CEIResumida!I86 -> 1060460 | I13: =CEIResumida!J86 -> 246213 | J13: =CEIResumida!K86 -> 282899 | ... L13: =CEIResumida!M86 -> 32573
B14: Rendas distribuídas das empresas | C14: =CEIResumida!D87 -> 1888670 | D14: =CEIResumida!E87 -> 0 | E14: =CEIResumida!F87 -> 0 | F14: =CEIResumida!G87 -> 0 | G14: =CEIResumida!H87 -> 0 | H14: =CEIResumida!I87 -> 153250 | I14: =CEIResumida!J87 -> 0 | J14: =CEIResumida!K87 -> 1821126 | ... L14: =CEIResumida!M87 -> 0
B15: Lucros reinvestidos de investimento estrangeiro direto | C15: =CEIResumida!D88 -> 0 | D15: =CEIResumida!E88 -> 0 | E15: =CEIResumida!F88 -> 0 | F15: =CEIResumida!G88 -> 0 | G15: =CEIResumida!H88 -> 0 | H15: =CEIResumida!I88 -> 0 | I15: =CEIResumida!J88 -> 0 | J15: =CEIResumida!K88 -> 0 | ... L15: =CEIResumida!M88 -> 0
B16: Desembolsos por rendas de investimentos | C16: =CEIResumida!D89 -> 0 | D16: =CEIResumida!E89 -> 0 | E16: =CEIResumida!F89 -> 0 | F16: =CEIResumida!G89 -> 0 | G16: =CEIResumida!H89 -> 0 | H16: =CEIResumida!I89 -> 0 | I16: =CEIResumida!J89 -> 0 | J16: =CEIResumida!K89 -> 0 | ... L16: =CEIResumida!M89 -> 0
B17: Renda de recursos naturais | C17: =CEIResumida!D90 -> 0 | D17: =CEIResumida!E90 -> 0 | E17: =CEIResumida!F90 -> 0 | F17: =CEIResumida!G90 -> 0 | G17: =CEIResumida!H90 -> 0 | H17: =CEIResumida!I90 -> 0 | I17: =CEIResumida!J90 -> 0 | J17: =CEIResumida!K90 -> 0 | ... L17: =CEIResumida!M90 -> 0
A18: Alocação secundária | B18: Impostos correntes sobre a renda, patrimônio, // Contribuições sociais // Outras transferências | C18: =CEIResumida!D91 -> 0 | D18: =CEIResumida!E91 -> 362776 | E18: =CEIResumida!F91 -> 917257 | F18: =CEIResumida!G91 -> 0 | G18: =CEIResumida!H91 -> 0 | H18: =CEIResumida!I91 -> 42715 | I18: =CEIResumida!J91 -> 0 | J18: =CEIResumida!K91 -> 511766 | ... L18: =CEIResumida!M91 -> 0
B19: Contribuições sociais | C19: =CEIResumida!D92 -> 0 | D19: =CEIResumida!E92 -> 895266 | E19: =CEIResumida!F92 -> 800730 | F19: =CEIResumida!G92 -> 0 | G19: =CEIResumida!H92 -> 94536 | H19: =CEIResumida!I92 -> 0 | I19: =CEIResumida!J92 -> 0 | J19: =CEIResumida!K92 -> 0 | ... L19: =CEIResumida!M92 -> 0
B20: Benefícios de seguridade social em numerário // Seguro desemprego, bolsa família | C20: =CEIResumida!D93 -> 1254637 | D20: =CEIResumida!E93 -> 0 | E20: =CEIResumida!F93 -> 0 | F20: =CEIResumida!G93 -> 1254637 | G20: =CEIResumida!H93 -> 0 | H20: =CEIResumida!I93 -> 0 | I20: =CEIResumida!J93 -> 0 | J20: =CEIResumida!K93 -> 0 | ... L20: =CEIResumida!M93 -> 0
B21: Outros benefícios de seguro social // Previdência | C21: =CEIResumida!D94 -> 717798 | D21: =CEIResumida!E94 -> 0 | E21: =CEIResumida!F94 -> 0 | F21: =CEIResumida!G94 -> 624646 | G21: =CEIResumida!H94 -> 0 | H21: =CEIResumida!I94 -> 93152 | I21: =CEIResumida!J94 -> 0 | J21: =CEIResumida!K94 -> 0 | ... L21: =CEIResumida!M94 -> 0
B22: Outras transferências correntes | C22: =CEIResumida!D95 -> 35242 | D22: =CEIResumida!E95 -> 0 | E22: =CEIResumida!F95 -> 70054 | F22: =CEIResumida!G95 -> 0 | G22: =CEIResumida!H95 -> 0 | H22: =CEIResumida!I95 -> 13352 | I22: =CEIResumida!J95 -> 0 | J22: =CEIResumida!K95 -> 59170 | ... L22: =CEIResumida!M95 -> 32774
A23: Usos da renda | B23: Consumo final efetivo | C23: =CEIResumida!D96 -> 0 | D23: =CEIResumida!E96 -> 4805004 | E23: =CEIResumida!F96 -> 0 | F23: =CEIResumida!G96 -> 1532204 | G23: =CEIResumida!H96 -> 0 | H23: =CEIResumida!I96 -> 0 | I23: =CEIResumida!J96 -> 0 | J23: =CEIResumida!K96 -> 0 | ... L23: =CEIResumida!M96 -> 0
B24: Ajustamento pela variação dos direitos de pensão | C24: =CEIResumida!D97 -> 0 | D24: =CEIResumida!E97 -> 0 | E24: =CEIResumida!F97 -> 0 | F24: =CEIResumida!G97 -> 0 | G24: =CEIResumida!H97 -> 0 | H24: =CEIResumida!I97 -> 0 | I24: =CEIResumida!J97 -> 0 | J24: =CEIResumida!K97 -> 0 | ... L24: =CEIResumida!M97 -> 0
B25: Formação bruta de capital fixo | C25: =CEIResumida!D98 -> 0 | D25: =CEIResumida!E98 -> 410010 | E25: =CEIResumida!F98 -> 0 | F25: =CEIResumida!G98 -> 139686 | G25: =CEIResumida!H98 -> 0 | H25: =CEIResumida!I98 -> 13718 | I25: =CEIResumida!J98 -> 0 | J25: =CEIResumida!K98 -> 696813 | ... L25: =CEIResumida!M98 -> 0
B26: Variação de estoques | C26: =CEIResumida!D99 -> 0 | D26: =CEIResumida!E99 -> 0 | E26: =CEIResumida!F99 -> 0 | F26: =CEIResumida!G99 -> 0 | G26: =CEIResumida!H99 -> 0 | H26: =CEIResumida!I99 -> 0 | I26: =CEIResumida!J99 -> 0 | J26: =CEIResumida!K99 -> -33878 | ... L26: =CEIResumida!M99 -> 0
B27: Aquisições líquidas de cessões de ativos não-produzidos | C27: =CEIResumida!D100 -> 0 | D27: =CEIResumida!E100 -> 0 | E27: =CEIResumida!F100 -> 0 | F27: =CEIResumida!G100 -> 0 | G27: =CEIResumida!H100 -> 0 | H27: =CEIResumida!I100 -> 0 | I27: =CEIResumida!J100 -> 0 | J27: =CEIResumida!K100 -> 0 | ... L27: =CEIResumida!M100 -> 0
B28: Capacidade (+) / Necessidade(-) líquida de financiamento | C28: =SUM(C7:C27)-SUM(D7:D27) -> 562272 | E28: =SUM(E7:E27)-SUM(F7:F27) -> -918009 | G28: =SUM(G7:G27)-SUM(H7:H27) -> 216917 | I28: =SUM(I7:I27)-SUM(J7:J27) -> 58282 | K28: =SUM(K7:K27)-SUM(L7:L27) -> 80538
B29: Check | C29: 562272 | E29: -918009 | G29: 149429 | I29: 125770 | K29: 80538
C35: S.14 Famílias | E35: S.13 Governo Geral | G35: S.12 Empresas finan- ceiras | I35: S.11 Empresas não- finan- ceiras | K35: Setor externo
C39: Entrada | D39: Saída | E39: Entrada | F39: Saída | G39: Entrada | H39: Saída | I39: Entrada | J39: Saída | K39: Entrada | L39: Saída | N39: VA preço mercado | O39: VA preço básico
B40: Valor adicionado bruto/Produto interno bruto (1) | N40: =G40+I40 -> 0 | O40: =N40-J44 -> 0
A41: Tabela de Usos e Recursos - específico por setor - geração de renda | B41: Salários
B42: Contribuições sociais efetivas
B43: Contribuições sociais inputadas
B44: Impostos, líquidos de subsídios, sobre produtos
B45: Outros impostos, líquidos de subsídios, sobre a produção
A46: Alocação primária do excedente | B46: Juros | C46: =CEIResumida!D86/CEIResumida!D141 -> 0.2591493 | D46: =CEIResumida!E86/CEIResumida!E141 -> 0.085190471 | E46: =CEIResumida!F86/CEIResumida!F141 -> 0.10513893 | F46: =CEIResumida!G86/CEIResumida!G141 -> 0.05816093 | G46: =CEIResumida!H86/CEIResumida!H141 -> 0.076863062 | H46: =CEIResumida!I86/CEIResumida!I141 -> 0.13700196 | I46: =CEIResumida!J86/CEIResumida!J141 -> 0.13780614 | J46: =CEIResumida!K86/CEIResumida!K141 -> 0.073535822 | ... L46: =CEIResumida!M86/CEIResumida!M141 -> 0.019355107
B47: Rendas distribuídas das empresas | C47: =C14/(C14+K14) -> 0.95659084 | H47: =H14/(SUM(G7:G13)-SUM(H7:H13)-H18-H22) -> 0.40065255 | J47: =J14/(SUM(I7:I13)-SUM(J7:J13)-J18-J22) -> 0.71631798 | K47: =1-C47 -> 0.043409158
B48: Lucros reinvestidos de investimento estrangeiro direto
B49: Desembolsos por rendas de investimentos
B50: Renda de recursos naturais
A51: Alocação secundária | B51: Impostos correntes sobre a renda, patrimônio, // Contribuições sociais // Outras transferências | D51: =D18/(SUM(C7:C13)-SUM(D7:D13)) -> 0.11557126 | H51: =H18/(SUM(G7:G13)-SUM(H7:H13)) -> 0.097396527 | J51: =J18/(SUM(I7:I13)-SUM(J7:J13)) -> 0.16438167
B52: Contribuições sociais
B53: Benefícios de seguridade social em numerário // Seguro desemprego, bolsa família
B54: Outros benefícios de seguro social // Previdência
B55: Outras transferências correntes
A56: Usos da renda | B56: Consumo final efetivo | D56: =D23/(SUM(C8:C22)-SUM(D8:D22)) -> 0.8317061
B57: Ajustamento pela variação dos direitos de pensão
B58: Formação bruta de capital fixo | D58: =D25/(SUM(C8:C22)-SUM(D8:D22)) -> 0.07096931 | J58: =J25/I7 -> 0.098314949
B59: Variação de estoques
B60: Aquisições líquidas de cessões de ativos não-produzidos
B61: Capacidade (+) / Necessidade(-) líquida de financiamento
B62: Check | C62: 562272 | E62: -918009 | G62: 216917 | I62: 58282 | K62: 80538

Sheet Original
A1: Tabela de recursos e usos - 2020 - valores correntes
A3: I - Tabela de recursos de bens e serviços
Y4: Valores correntes em 1 000 000 R$
A5: Descrição do produto | B5: Oferta de bens e serviços | K5: Produção das atividades | X5: Total da economia | Y5: Impor- tação de bens e serviços (2)
B6: Oferta total a preço de con- sumidor | C6: Margem de comércio | D6: Margem de trans- porte | E6: Imposto de impor- tação | F6: IPI | G6: ICMS | H6: Outros impostos menos subsídios | I6: Total de impostos líquidos de subsídios | J6: Oferta total a preço básico | K6: Agrope- cuária | L6: Indústrias extrativas | M6: Indústrias de transfor- mação | N6: Eletricida- de e gás, água, esgoto e gestão de resíduos | O6: Cons- trução | P6: Comércio | Q6: Trans- porte, armaze- nagem e correio | R6: Informação e comu- nicação | S6: Atividades financeiras, de seguros e serviços relacio- nados | T6: Ativi- dades imobi- liárias | U6: Outras atividades de serviços | V6: Adminis- tração, defesa, saúde e educação públicas e seguridade social | W6: Total do produto
A11: Agropecuária | B11: =C11+D11+I11+J11 -> 938989 | C11: 101814 | D11: 17919 | E11: 468 | F11: 0 | G11: 11727 | H11: 6061 | I11: =SUM(E11:H11) -> 18256 | J11: =SUM(W11,Y11) -> 801000 | K11: 777589 | L11: 0 | M11: 0 | N11: 0 | O11: 0 | P11: 172 | Q11: 106 | R11: 0 | S11: 0 | T11: 0 | U11: 0 | V11: 602 | W11: =SUM(K11:V11) -> 778469 | Y11: 22531
A12: Indústrias extrativas | B12: =C12+D12+I12+J12 -> 474641 | C12: 22876 | D12: 8440 | E12: 30 | F12: 0 | G12: 1455 | H12: 3223 | I12: =SUM(E12:H12) -> 4708 | J12: =SUM(W12,Y12) -> 438617 | K12: 317 | L12: 401704 | M12: 1854 | N12: 0 | O12: 0 | P12: 320 | Q12: 0 | R12: 0 | S12: 0 | T12: 0 | U12: 0 | V12: 15 | W12: =SUM(K12:V12) -> 404210 | Y12: 34407
A13: Indústrias de transformação | B13: =C13+D13+I13+J13 -> 6468662 | C13: 1045722 | D13: 71220 | E13: 45158 | F13: 55894 | G13: 379582 | H13: 152570 | I13: =SUM(E13:H13) -> 633204 | J13: =SUM(W13,Y13) -> 4718516 | K13: 9930 | L13: 6125 | M13: 3702844 | N13: 0 | O13: 54 | P13: 91539 | Q13: 147 | R13: 657 | S13: 0 | T13: 0 | U13: 4150 | V13: 2011 | W13: =SUM(K13:V13) -> 3817457 | Y13: 901059
A14: Eletricidade e gás, água, esgoto e gestão de resíduos | B14: =C14+D14+I14+J14 -> 532996 | C14: 4732 | D14: 0 | E14: 0 | F14: 0 | G14: 57829 | H14: 13475 | I14: =SUM(E14:H14) -> 71304 | J14: =SUM(W14,Y14) -> 456960 | K14: 0 | L14: 0 | M14: 0 | N14: 441537 | O14: 0 | P14: 0 | Q14: 0 | R14: 0 | S14: 0 | T14: 0 | U14: 0 | V14: 7972 | W14: =SUM(K14:V14) -> 449509 | Y14: 7451
A15: Construção | B15: =C15+D15+I15+J15 -> 683264 | C15: 0 | D15: 0 | E15: 0 | F15: 0 | G15: 0 | H15: 31512 | I15: =SUM(E15:H15) -> 31512 | J15: =SUM(W15,Y15) -> 651752 | K15: 7719 | L15: 33321 | M15: 0 | N15: 0 | O15: 607286 | P15: 0 | Q15: 0 | R15: 0 | S15: 0 | T15: 0 | U15: 0 | V15: 1 | W15: =SUM(K15:V15) -> 648327 | Y15: 3425
A16: Comércio | B16: =C16+D16+I16+J16 -> 140737 | C16: -1186683 | D16: 0 | E16: 0 | F16: 0 | G16: 0 | H16: 2617 | I16: =SUM(E16:H16) -> 2617 | J16: =SUM(W16,Y16) -> 1324803 | K16: 0 | L16: 32 | M16: 24811 | N16: 34 | O16: 12 | P16: 1288917 | Q16: 830 | R16: 3788 | S16: 0 | T16: 0 | U16: 2678 | V16: 330 | W16: =SUM(K16:V16) -> 1321432 | Y16: 3371
A17: Transporte, armazenagem e correio | B17: =C17+D17+I17+J17 -> 568288 | C17: 0 | D17: -97641 | E17: 0 | F17: 0 | G17: 10588 | H17: 19326 | I17: =SUM(E17:H17) -> 29914 | J17: =SUM(W17,Y17) -> 636015 | K17: 0 | L17: 0 | M17: 0 | N17: 458 | O17: 0 | P17: 3008 | Q17: 611351 | R17: 0 | S17: 0 | T17: 0 | U17: 95 | V17: 4668 | W17: =SUM(K17:V17) -> 619580 | Y17: 16435
A18: Informação e comunicação | B18: =C18+D18+I18+J18 -> 535541 | C18: 11539 | D18: 62 | E18: 12 | F18: 0 | G18: 38831 | H18: 17569 | I18: =SUM(E18:H18) -> 56412 | J18: =SUM(W18,Y18) -> 467528 | K18: 0 | L18: 0 | M18: 0 | N18: 0 | O18: 0 | P18: 1047 | Q18: 48 | R18: 426997 | S18: 1248 | T18: 0 | U18: 137 | V18: 2089 | W18: =SUM(K18:V18) -> 431566 | Y18: 35962
A19: Atividades financeiras, de seguros e serviços relacionados | B19: =C19+D19+I19+J19 -> 800076 | C19: 0 | D19: 0 | E19: 0 | F19: 0 | G19: 0 | H19: 67488 | I19: =SUM(E19:H19) -> 67488 | J19: =SUM(W19,Y19) -> 732588 | K19: 0 | L19: 0 | M19: 0 | N19: 0 | O19: 0 | P19: 0 | Q19: 0 | R19: 0 | S19: 687862 | T19: 0 | U19: 0 | V19: 434 | W19: =SUM(K19:V19) -> 688296 | Y19: 44292
A20: Atividades imobiliárias | B20: =C20+D20+I20+J20 -> 793035 | C20: 0 | D20: 0 | E20: 0 | F20: 0 | G20: 0 | H20: 1248 | I20: =SUM(E20:H20) -> 1248 | J20: =SUM(W20,Y20) -> 791787 | K20: 92 | L20: 670 | M20: 26394 | N20: 12370 | O20: 3762 | P20: 2639 | Q20: 5161 | R20: 1526 | S20: 9080 | T20: 711631 | U20: 8689 | V20: 2641 | W20: =SUM(K20:V20) -> 784655 | Y20: 7132
A21: Outras atividades de serviços | B21: =C21+D21+I21+J21 -> 2125358 | C21: 0 | D21: 0 | E21: 3 | F21: 0 | G21: 23099 | H21: 74895 | I21: =SUM(E21:H21) -> 97997 | J21: =SUM(W21,Y21) -> 2027361 | K21: 114 | L21: 179 | M21: 13473 | N21: 342 | O21: 1387 | P21: 16909 | Q21: 11258 | R21: 2680 | S21: 2713 | T21: 0 | U21: 1797276 | V21: 51086 | W21: =SUM(K21:V21) -> 1897417 | Y21: 129944
A22: Administração, defesa, saúde e educação públicas e seguridade social | B22: =C22+D22+I22+J22 -> 1465281 | C22: 0 | D22: 0 | E22: 0 | F22: 0 | G22: 0 | H22: 0 | I22: =SUM(E22:H22) -> 0 | J22: =SUM(W22,Y22) -> 1465281 | K22: 0 | L22: 0 | M22: 0 | N22: 0 | O22: 0 | P22: 0 | Q22: 0 | R22: 0 | S22: 0 | T22: 0 | U22: 0 | V22: 1465281 | W22: =SUM(K22:V22) -> 1465281 | Y22: 0
A24: Total | B24: =SUM(B11:B22) -> 15526868 | C24: =SUM(C11:C22) -> 0 | D24: =SUM(D11:D22) -> 0 | E24: =SUM(E11:E22) -> 45671 | F24: =SUM(F11:F22) -> 55894 | G24: =SUM(G11:G22) -> 523111 | H24: =SUM(H11:H22) -> 389984 | I24: =SUM(I11:I22) -> 1014660 | ... W24: =SUM(W11:W22) -> 13306199 | Y24: =SUM(Y11:Y23) -> 1206009
A26: Fonte: IBGE, Diretoria de Pesquisas, Coordenação de Contas Nacionais.
A31: II - Tabela de usos de bens e serviços
AF32: Valores correntes em 1 000 000 R$
A33: Descrição do produto | B33: Oferta total a preço de con- sumidor | C33: Margem de comércio | D33: Margem de trans- porte | E33: Imposto de impor- tação | F33: IPI | G33: ICMS | H33: Outros impostos | I33: Total de impostos | J33: Oferta total a preço básico | K33: Consumo intermediário das atividades | X33: PIB / Total da economia (1) | Y33: Demanda final | AF33: De- manda total
K34: Agrope- cuária | L34: Indústrias extrativas | M34: Indústrias de transfor- mação | N34: Eletricida- de e gás, água, esgoto e gestão de resíduos | O34: Cons- trução | P34: Comércio | Q34: Trans- porte, armaze- nagem e correio | R34: Informação e comu- nicação | S34: Atividades financeiras, de seguros e serviços relacio- nados | T34: Ativi- dades imobi- liárias | U34: Outras atividades de serviços | V34: Adminis- tração, defesa, saúde e educação públicas e seguridade social | W34: Total do produto | Y34: Expor- tação de bens e serviços (3) | Z34: Consu- mo do governo | AA34: Consu- mo das ISFLSF | AB34: Consu- mo das famílias | AC34: Forma- ção bruta de capi- tal fixo | AD34: Varia- ção de estoque | AE34: De- manda final
A39: Agropecuária | B39: =B11 -> 938989 | K39: 46529 | L39: 2 | M39: 385354 | N39: 69 | O39: 1088 | P39: 16888 | Q39: 0 | R39: 0 | S39: 0 | T39: 0 | U39: 11153 | V39: 3683 | W39: =SUM(K39:V39) -> 464766 | Y39: 241683 | Z39: 230 | AA39: 0 | AB39: =SUM(AH39:AI39) -> 212694 | AC39: 22310 | AD39: -2694 | AE39: =SUM(Y39:AD39) -> 474223 | AF39: =W39+AE39 -> 938989 | AH39: 0 | AI39: 212694 | AK39: =AE39-AB39 -> 261529
A40: Indústrias extrativas | B40: =B12 -> 474641 | K40: 874 | L40: 16121 | M40: 198222 | N40: 12854 | O40: 9589 | P40: 121 | Q40: 6 | R40: 0 | S40: 0 | T40: 551 | U40: 86 | V40: 149 | W40: =SUM(K40:V40) -> 238573 | Y40: 253114 | Z40: 0 | AA40: 0 | AB40: =SUM(AH40:AI40) -> 0 | AC40: 10455 | AD40: -27501 | AE40: =SUM(Y40:AD40) -> 236068 | AF40: =W40+AE40 -> 474641 | AH40: 0 | AI40: 0 | AK40: =AE40-AB40 -> 236068
A41: Indústrias de transformação | B41: =B13 -> 6468662 | K41: 264935 | L41: 117877 | M41: 1817709 | N41: 39415 | O41: 232483 | P41: 143692 | Q41: 168628 | R41: 24714 | S41: 9572 | T41: 11292 | U41: 261506 | V41: 85762 | W41: =SUM(K41:V41) -> 3177585 | Y41: 611468 | Z41: 9716 | AA41: 0 | AB41: =SUM(AH41:AI41) -> 2148705 | AC41: 523356 | AD41: -2168 | AE41: =SUM(Y41:AD41) -> 3291077 | AF41: =W41+AE41 -> 6468662 | AH41: 0 | AI41: 2148705 | AK41: =AE41-AB41 -> 1142372
A42: Eletricidade e gás, água, esgoto e gestão de resíduos | B42: =B14 -> 532996 | K42: 19060 | L42: 4165 | M42: 57562 | N42: 142663 | O42: 1100 | P42: 35518 | Q42: 5222 | R42: 4434 | S42: 3647 | T42: 1676 | U42: 44360 | V42: 27071 | W42: =SUM(K42:V42) -> 346478 | Y42: 2 | Z42: 0 | AA42: 0 | AB42: =SUM(AH42:AI42) -> 186576 | AC42: 0 | AD42: -60 | AE42: =SUM(Y42:AD42) -> 186518 | AF42: =W42+AE42 -> 532996 | AH42: 0 | AI42: 186576 | AK42: =AE42-AB42 -> -58
A43: Construção | B43: =B15 -> 683264 | K43: 346 | L43: 7040 | M43: 3483 | N43: 6090 | O43: 64476 | P43: 1281 | Q43: 2108 | R43: 5076 | S43: 1156 | T43: 2074 | U43: 5894 | V43: 24150 | W43: =SUM(K43:V43) -> 123174 | Y43: 3481 | Z43: 0 | AA43: 0 | AB43: =SUM(AH43:AI43) -> 0 | AC43: 556609 | AD43: 0 | AE43: =SUM(Y43:AD43) -> 560090 | AF43: =W43+AE43 -> 683264 | AH43: 0 | AI43: 0 | AK43: =AE43-AB43 -> 560090
A44: Comércio | B44: =B16 -> 140737 | K44: 353 | L44: 2486 | M44: 43753 | N44: 1300 | O44: 493 | P44: 12404 | Q44: 8467 | R44: 3711 | S44: 146 | T44: 25 | U44: 3481 | V44: 3530 | W44: =SUM(K44:V44) -> 80149 | Y44: 4676 | Z44: 0 | AA44: 0 | AB44: =SUM(AH44:AI44) -> 55912 | AC44: 0 | AD44: 0 | AE44: =SUM(Y44:AD44) -> 60588 | AF44: =W44+AE44 -> 140737 | AH44: 0 | AI44: 55912 | AK44: =AE44-AB44 -> 4676
A45: Transporte, armazenagem e correio | B45: =B17 -> 568288 | K45: 12900 | L45: 36580 | M45: 150873 | N45: 5229 | O45: 3050 | P45: 81866 | Q45: 90333 | R45: 2762 | S45: 5947 | T45: 329 | U45: 22063 | V45: 12154 | W45: =SUM(K45:V45) -> 424086 | Y45: 34419 | Z45: 0 | AA45: 0 | AB45: =SUM(AH45:AI45) -> 109783 | AC45: 0 | AD45: 0 | AE45: =SUM(Y45:AD45) -> 144202 | AF45: =W45+AE45 -> 568288 | AH45: 0 | AI45: 109783 | AK45: =AE45-AB45 -> 34419
A46: Informação e comunicação | B46: =B18 -> 535541 | K46: 63 | L46: 1830 | M46: 22246 | N46: 3243 | O46: 1755 | P46: 25118 | Q46: 6656 | R46: 56654 | S46: 34169 | T46: 1273 | U46: 77971 | V46: 37213 | W46: =SUM(K46:V46) -> 268191 | Y46: 15282 | Z46: 0 | AA46: 0 | AB46: =SUM(AH46:AI46) -> 152610 | AC46: 100913 | AD46: -1455 | AE46: =SUM(Y46:AD46) -> 267350 | AF46: =W46+AE46 -> 535541 | AH46: 0 | AI46: 152610 | AK46: =AE46-AB46 -> 114740
A47: Atividades financeiras, de seguros e serviços relacionados | B47: =B19 -> 800076 | K47: 12145 | L47: 8823 | M47: 68105 | N47: 11655 | O47: 9620 | P47: 37998 | Q47: 16729 | R47: 14335 | S47: 111389 | T47: 28083 | U47: 31616 | V47: 60811 | W47: =SUM(K47:V47) -> 411309 | Y47: 6943 | Z47: 2165 | AA47: 0 | AB47: =SUM(AH47:AI47) -> 379659 | AC47: 0 | AD47: 0 | AE47: =SUM(Y47:AD47) -> 388767 | AF47: =W47+AE47 -> 800076 | AH47: 0 | AI47: 379659 | AK47: =AE47-AB47 -> 9108
A48: Atividades imobiliárias | B48: =B20 -> 793035 | K48: 27 | L48: 745 | M48: 8979 | N48: 1618 | O48: 1498 | P48: 59453 | Q48: 6412 | R48: 6456 | S48: 6844 | T48: 2942 | U48: 45392 | V48: 4778 | W48: =SUM(K48:V48) -> 145144 | Y48: 4688 | Z48: 0 | AA48: 0 | AB48: =SUM(AH48:AI48) -> 643203 | AC48: 0 | AD48: 0 | AE48: =SUM(Y48:AD48) -> 647891 | AF48: =W48+AE48 -> 793035 | AH48: 0 | AI48: 643203 | AK48: =AE48-AB48 -> 4688
A49: Outras atividades de serviços | B49: =B21 -> 2125358 | K49: 3908 | L49: 52747 | M49: 199401 | N49: 21493 | O49: 19428 | P49: 164866 | Q49: 51101 | R49: 79932 | S49: 73483 | T49: 7373 | U49: 227146 | V49: 130929 | W49: =SUM(K49:V49) -> 1031807 | Y49: 76293 | Z49: 54812 | AA49: 0 | AB49: =SUM(AH49:AI49) -> 915862 | AC49: 46584 | AD49: 0 | AE49: =SUM(Y49:AD49) -> 1093551 | AF49: =W49+AE49 -> 2125358 | AH49: 104919 | AI49: 810943 | AK49: =AE49-AB49 -> 177689
A50: Administração, defesa, saúde e educação públicas e seguridade social | B50: =B22 -> 1465281 | K50: 0 | L50: 0 | M50: 0 | N50: 0 | O50: 0 | P50: 0 | Q50: 0 | R50: 0 | S50: 0 | T50: 0 | U50: 0 | V50: 0 | W50: =SUM(K50:V50) -> 0 | Y50: 0 | Z50: 1465281 | AA50: 0 | AB50: =SUM(AH50:AI50) -> 0 | AC50: 0 | AD50: 0 | AE50: =SUM(Y50:AD50) -> 1465281 | AF50: =W50+AE50 -> 1465281 | AH50: 0 | AI50: 0 | AK50: =AE50-AB50 -> 1465281
A51: Total | B51: =SUM(B39:B50) -> 15526868 | K51: =SUM(K39:K50) -> 361140 | L51: =SUM(L39:L50) -> 248416 | M51: =SUM(M39:M50) -> 2955687 | N51: =SUM(N39:N50) -> 245629 | O51: =SUM(O39:O50) -> 344580 | P51: =SUM(P39:P50) -> 579205 | Q51: =SUM(Q39:Q50) -> 355662 | R51: =SUM(R39:R50) -> 198074 | ... V51: =SUM(V39:V50) -> 390230 | W51: =SUM(K51:V51) -> 6711262 | Y51: =SUM(Y39:Y50) -> 1252049 | Z51: =SUM(Z39:Z50) -> 1532204 | AA51: =SUM(AA39:AA50) -> 0 | AB51: =SUM(AH51:AI51) -> 4805004 | AC51: =SUM(AC39:AC50) -> 1260227 | AD51: =SUM(AD39:AD50) -> -33878 | AE51: =SUM(Y51:AD51) -> 8815606 | AF51: =W51+AE51 -> 15526868 | AH51: =SUM(AH39:AH50) -> 104919 | AI51: =SUM(AI39:AI50) -> 4700085 | AK51: =AE51-AB51 -> 4010602
A52: Componentes do valor adicionado
A54: Valor adicionado bruto ( PIB ) | I54: =I24 -> 1014660 | K54: =K24-K51 -> 434621 | L54: =L24-L51 -> 193615 | M54: =M24-M51 -> 813689 | N54: =N24-N51 -> 209112 | O54: =O24-O51 -> 267921 | P54: =P24-P51 -> 825346 | Q54: =Q24-Q51 -> 273239 | R54: =R24-R51 -> 237574 | ... V54: =V24-V51 -> 1146900 | W54: =SUM(K54:V54) -> 6594937 | X54: =I54+W54 -> 7609597
A55: Remunerações | K55: 56426 | L55: 31030 | M55: 431907 | N55: 42340 | O55: 110214 | P55: 404268 | Q55: 144416 | R55: 106305 | S55: 181285 | T55: 9024 | U55: 646179 | V55: 1028949 | W55: =SUM(K55:V55) -> 3192343 | X55: =I55+W55 -> 3192343 | AA55: TABELA DE RECURSOS E USOS
A56: Salários | K56: 48460 | L56: 23545 | M56: 342665 | N56: 31380 | O56: 90262 | P56: 322109 | Q56: 115820 | R56: 84430 | S56: 140274 | T56: 7050 | U56: 545236 | V56: 780730 | W56: =SUM(K56:V56) -> 2531961 | X56: =I56+W56 -> 2531961
A57: Contribuições sociais efetivas | K57: 7966 | L57: 7485 | M57: 89242 | N57: 10960 | O57: 19952 | P57: 82159 | Q57: 28596 | R57: 21875 | S57: 41011 | T57: 1974 | U57: 100943 | V57: 150454 | W57: =SUM(K57:V57) -> 562617 | X57: =I57+W57 -> 562617 | AA57: I - Tabela de recursos de bens e serviços
A58: Previdência oficial /FGTS | K58: 7966 | L58: 6442 | M58: 85542 | N58: 9203 | O58: 19642 | P58: 81427 | Q58: 27010 | R58: 20152 | S58: 34959 | T58: 1927 | U58: 99114 | V58: 147997 | W58: =SUM(K58:V58) -> 541381 | X58: =I58+W58 -> 541381 | AB58: Oferta A = | AC58: Produção A1 + | AD58: Importação A2
A59: Previdência privada | K59: 0 | L59: 1043 | M59: 3700 | N59: 1757 | O59: 310 | P59: 732 | Q59: 1586 | R59: 1723 | S59: 6052 | T59: 47 | U59: 1829 | V59: 2457 | W59: =SUM(K59:V59) -> 21236 | X59: =I59+W59 -> 21236
A60: Contribuições sociais imputadas | K60: 0 | L60: 0 | M60: 0 | N60: 0 | O60: 0 | P60: 0 | Q60: 0 | R60: 0 | S60: 0 | T60: 0 | U60: 0 | V60: 97765 | W60: =SUM(K60:V60) -> 97765 | X60: =I60+W60 -> 97765
A61: Excedente operacional bruto e rendimento misto bruto | K61: 380742 | L61: 159960 | M61: 353922 | N61: 162640 | O61: 154409 | P61: 408143 | Q61: 123266 | R61: 125590 | S61: 264003 | T61: 646363 | U61: 419492 | V61: 117673 | W61: =SUM(K61:V61) -> 3316203 | X61: =I61+W61 -> 3316203 | AA61: II - Tabela de usos de bens e serviços
A62: Rendimento misto bruto | K62: 203321 | L62: 246 | M62: 26998 | N62: 1342 | O62: 65864 | P62: 82745 | Q62: 29289 | R62: 11697 | S62: 3241 | T62: 4446 | U62: 204175 | V62: 0 | W62: =SUM(K62:V62) -> 633364 | X62: =I62+W62 -> 633364 | AB62: Oferta A = | AC62: Consumo interme- diário B1 + | AD62: Demanda final B2
A63: Excedente operacional bruto (EOB) | K63: 177421 | L63: 159714 | M63: 326924 | N63: 161298 | O63: 88545 | P63: 325398 | Q63: 93977 | R63: 113893 | S63: 260762 | T63: 641917 | U63: 215317 | V63: 117673 | W63: =SUM(K63:V63) -> 2682839 | X63: =I63+W63 -> 2682839
A64: Impostos líquidos de subsídios sobre a produção e a importação | I64: =I65+I66 -> 1014660 | K64: =SUM(K65:K68) -> -2547 | L64: =SUM(L65:L68) -> 2625 | M64: =SUM(M65:M68) -> 27860 | N64: =SUM(N65:N68) -> 4132 | O64: =SUM(O65:O68) -> 3298 | P64: =SUM(P65:P68) -> 12935 | Q64: =SUM(Q65:Q68) -> 5557 | R64: =SUM(R65:R68) -> 5679 | ... V64: =SUM(V65:V68) -> 278 | W64: =SUM(K64:V64) -> 86391 | X64: =I64+W64 -> 1101051
A65: Impostos sobre produtos | I65: 1020210 | W65: =SUM(K65:V65) -> 0 | X65: =I65+W65 -> 1020210
A66: Subsídios sobre produtos | I66: -5550 | W66: =SUM(K66:V66) -> 0 | X66: =I66+W66 -> -5550
A67: Outros impostos sobre a produção | K67: 3036 | L67: 2656 | M67: 28537 | N67: 4186 | O67: 3429 | P67: 13168 | Q67: 6169 | R67: 5702 | S67: 9262 | T67: 626 | U67: 17439 | V67: 278 | W67: =SUM(K67:V67) -> 94488 | X67: =I67+W67 -> 94488 | AB67: Componentes do valor adicionado C
A68: Outros subsídios à produção | K68: -5583 | L68: -31 | M68: -677 | N68: -54 | O68: -131 | P68: -233 | Q68: -612 | R68: -23 | S68: 0 | T68: 0 | U68: -753 | V68: 0 | W68: =SUM(K68:V68) -> -8097 | X68: =I68+W68 -> -8097
A69: Valor da produção | K69: =K24 -> 795761 | L69: =L24 -> 442031 | M69: =M24 -> 3769376 | N69: =N24 -> 454741 | O69: =O24 -> 612501 | P69: =P24 -> 1404551 | Q69: =Q24 -> 628901 | R69: =R24 -> 435648 | ... V69: =V24 -> 1537130 | W69: =SUM(K69:V69) -> 13306199 | X69: =I69+W69 -> 13306199
A70: Fator trabalho (ocupações) | K70: 12560399 | L70: 212274 | M70: 10560359 | N70: 742087 | O70: 7047825 | P70: 17613390 | Q70: 4932125 | R70: 1405295 | S70: 1410816 | T70: 502337 | U70: 30453062 | V70: 11814707 | W70: =SUM(K70:V70) -> 99254676 | X70: =I70+W70 -> 99254676
K71: {=TRANSPOSE(B39:B51)} -> 938989 | L71: 474641 | M71: 6468662 | N71: 532996 | O71: 683264 | P71: 140737 | Q71: 568288 | R71: 535541 | S71: 800076 | T71: 793035 | U71: 2125358 | V71: 1465281 | W71: 15526868
A72: Fonte: IBGE, Diretoria de Pesquisas, Coordenação de Contas Nacionais.
A73: (1) O PIB corresponde à soma do valor adicionado a preços básicos das atividades econômicas mais o total dos impostos, líquido de subsídios, sobre produtos. (2) Importação de bens e serviços líquida de ajuste CIF/FOB. (3) Exportação de bens e serviços acrescida de ajuste CIF/FOB.

Sheet ParâmeetrosTRU
A1: Tabela de recursos e usos - 2020 - valores correntes
A3: I - Tabela de recursos de bens e serviços
Y4: Valores correntes em 1 000 000 R$
A5: Descrição do produto | B5: Oferta de bens e serviços | K5: Produção das atividades | X5: Total da economia | Y5: Impor- tação de bens e serviços (2)
B6: Oferta total a preço de con- sumidor | C6: Margem de comércio | D6: Margem de trans- porte | E6: Imposto de impor- tação | F6: IPI | G6: ICMS | H6: Outros impostos menos subsídios | I6: Total de impostos líquidos de subsídios | J6: Oferta total a preço básico | K6: Agrope- cuária | L6: Indústrias extrativas | M6: Indústrias de transfor- mação | N6: Eletricida- de e gás, água, esgoto e gestão de resíduos | O6: Cons- trução | P6: Comércio | Q6: Trans- porte, armaze- nagem e correio | R6: Informação e comu- nicação | S6: Atividades financeiras, de seguros e serviços relacio- nados | T6: Ativi- dades imobi- liárias | U6: Outras atividades de serviços | V6: Adminis- tração, defesa, saúde e educação públicas e seguridade social | W6: Total do produto
A11: Agropecuária | B11: =C11+D11+I11+J11 -> 1 | C11: =Original!C11/Original!$B11 -> 0.10842939 | D11: =Original!D11/Original!$B11 -> 0.019083291 | I11: =Original!I11/Original!$B11 -> 0.019442187 | J11: =Original!J11/Original!$B11 -> 0.85304514 | K11: =Original!K11/Original!$B11 -> 0.828113 | L11: =Original!L11/Original!$B11 -> 0 | M11: =Original!M11/Original!$B11 -> 0 | N11: =Original!N11/Original!$B11 -> 0 | O11: =Original!O11/Original!$B11 -> 0 | P11: =Original!P11/Original!$B11 -> 0.00018317573 | ... V11: =Original!V11/Original!$B11 -> 0.00064111507 | X11: =Original!X11/Original!$B11 -> 0 | Y11: =Original!Y11/Original!$B11 -> 0.023994956
A12: Indústrias extrativas | B12: =C12+D12+I12+J12 -> 1 | C12: =Original!C12/Original!$B12 -> 0.048196426 | D12: =Original!D12/Original!$B12 -> 0.01778186 | E12: =Original!E12/Original!$B12 -> 6.3205665e-05 | F12: =Original!F12/Original!$B12 -> 0 | G12: =Original!G12/Original!$B12 -> 0.0030654747 | H12: =Original!H12/Original!$B12 -> 0.0067903953 | I12: =Original!I12/Original!$B12 -> 0.0099190757 | J12: =Original!J12/Original!$B12 -> 0.92410264 | ... V12: =Original!V12/Original!$B12 -> 3.1602832e-05 | X12: =Original!X12/Original!$B12 -> 0 | Y12: =Original!Y12/Original!$B12 -> 0.072490577
A13: Indústrias de transformação | B13: =C13+D13+I13+J13 -> 1 | C13: =Original!C13/Original!$B13 -> 0.16165971 | D13: =Original!D13/Original!$B13 -> 0.011010005 | E13: =Original!E13/Original!$B13 -> 0.0069810418 | F13: =Original!F13/Original!$B13 -> 0.0086407359 | G13: =Original!G13/Original!$B13 -> 0.058680141 | H13: =Original!H13/Original!$B13 -> 0.023586021 | I13: =Original!I13/Original!$B13 -> 0.09788794 | J13: =Original!J13/Original!$B13 -> 0.72944235 | ... V13: =Original!V13/Original!$B13 -> 0.00031088346 | X13: =Original!X13/Original!$B13 -> 0 | Y13: =Original!Y13/Original!$B13 -> 0.13929604
A14: Eletricidade e gás, água, esgoto e gestão de resíduos | B14: =C14+D14+I14+J14 -> 1 | C14: =Original!C14/Original!$B14 -> 0.0088781154 | D14: =Original!D14/Original!$B14 -> 0 | E14: =Original!E14/Original!$B14 -> 0 | F14: =Original!F14/Original!$B14 -> 0 | G14: =Original!G14/Original!$B14 -> 0.108498 | H14: =Original!H14/Original!$B14 -> 0.025281616 | I14: =Original!I14/Original!$B14 -> 0.13377962 | J14: =Original!J14/Original!$B14 -> 0.85734227 | ... V14: =Original!V14/Original!$B14 -> 0.01495696 | X14: =Original!X14/Original!$B14 -> 0 | Y14: =Original!Y14/Original!$B14 -> 0.013979467
A15: Construção | B15: =C15+D15+I15+J15 -> 1 | C15: =Original!C15/Original!$B15 -> 0 | D15: =Original!D15/Original!$B15 -> 0 | E15: =Original!E15/Original!$B15 -> 0 | F15: =Original!F15/Original!$B15 -> 0 | G15: =Original!G15/Original!$B15 -> 0 | H15: =Original!H15/Original!$B15 -> 0.046119801 | I15: =Original!I15/Original!$B15 -> 0.046119801 | J15: =Original!J15/Original!$B15 -> 0.9538802 | ... V15: =Original!V15/Original!$B15 -> 1.4635631e-06 | X15: =Original!X15/Original!$B15 -> 0 | Y15: =Original!Y15/Original!$B15 -> 0.0050127037
A16: Comércio | B16: =C16+D16+I16+J16 -> 1 | C16: =Original!C16/Original!$B16 -> -8.4319191 | D16: =Original!D16/Original!$B16 -> 0 | E16: =Original!E16/Original!$B16 -> 0 | F16: =Original!F16/Original!$B16 -> 0 | G16: =Original!G16/Original!$B16 -> 0 | H16: =Original!H16/Original!$B16 -> 0.018594968 | I16: =Original!I16/Original!$B16 -> 0.018594968 | J16: =Original!J16/Original!$B16 -> 9.4133241 | ... V16: =Original!V16/Original!$B16 -> 0.0023447992 | X16: =Original!X16/Original!$B16 -> 0 | Y16: =Original!Y16/Original!$B16 -> 0.023952479
A17: Transporte, armazenagem e correio | B17: =C17+D17+I17+J17 -> 1 | C17: =Original!C17/Original!$B17 -> 0 | D17: =Original!D17/Original!$B17 -> -0.17181605 | E17: =Original!E17/Original!$B17 -> 0 | F17: =Original!F17/Original!$B17 -> 0 | G17: =Original!G17/Original!$B17 -> 0.018631398 | H17: =Original!H17/Original!$B17 -> 0.034007405 | I17: =Original!I17/Original!$B17 -> 0.052638803 | J17: =Original!J17/Original!$B17 -> 1.1191772 | ... V17: =Original!V17/Original!$B17 -> 0.0082141449 | X17: =Original!X17/Original!$B17 -> 0 | Y17: =Original!Y17/Original!$B17 -> 0.028920195
A18: Informação e comunicação | B18: =C18+D18+I18+J18 -> 1 | C18: =Original!C18/Original!$B18 -> 0.021546436 | D18: =Original!D18/Original!$B18 -> 0.00011577078 | E18: =Original!E18/Original!$B18 -> 2.2407248e-05 | F18: =Original!F18/Original!$B18 -> 0 | G18: =Original!G18/Original!$B18 -> 0.072507987 | H18: =Original!H18/Original!$B18 -> 0.032806078 | I18: =Original!I18/Original!$B18 -> 0.10533647 | J18: =Original!J18/Original!$B18 -> 0.87300132 | ... V18: =Original!V18/Original!$B18 -> 0.0039007284 | X18: =Original!X18/Original!$B18 -> 0 | Y18: =Original!Y18/Original!$B18 -> 0.067150788
A19: Atividades financeiras, de seguros e serviços relacionados | B19: =C19+D19+I19+J19 -> 1 | C19: =Original!C19/Original!$B19 -> 0 | D19: =Original!D19/Original!$B19 -> 0 | E19: =Original!E19/Original!$B19 -> 0 | F19: =Original!F19/Original!$B19 -> 0 | G19: =Original!G19/Original!$B19 -> 0 | H19: =Original!H19/Original!$B19 -> 0.084351987 | I19: =Original!I19/Original!$B19 -> 0.084351987 | J19: =Original!J19/Original!$B19 -> 0.91564801 | ... V19: =Original!V19/Original!$B19 -> 0.00054244847 | X19: =Original!X19/Original!$B19 -> 0 | Y19: =Original!Y19/Original!$B19 -> 0.055359741
A20: Atividades imobiliárias | B20: =C20+D20+I20+J20 -> 1 | C20: =Original!C20/Original!$B20 -> 0 | D20: =Original!D20/Original!$B20 -> 0 | E20: =Original!E20/Original!$B20 -> 0 | F20: =Original!F20/Original!$B20 -> 0 | G20: =Original!G20/Original!$B20 -> 0 | H20: =Original!H20/Original!$B20 -> 0.001573701 | I20: =Original!I20/Original!$B20 -> 0.001573701 | J20: =Original!J20/Original!$B20 -> 0.9984263 | ... V20: =Original!V20/Original!$B20 -> 0.0033302439 | X20: =Original!X20/Original!$B20 -> 0 | Y20: =Original!Y20/Original!$B20 -> 0.0089932979
A21: Outras atividades de serviços | B21: =C21+D21+I21+J21 -> 1 | C21: =Original!C21/Original!$B21 -> 0 | D21: =Original!D21/Original!$B21 -> 0 | E21: =Original!E21/Original!$B21 -> 1.4115269e-06 | F21: =Original!F21/Original!$B21 -> 0 | G21: =Original!G21/Original!$B21 -> 0.010868287 | H21: =Original!H21/Original!$B21 -> 0.035238769 | I21: =Original!I21/Original!$B21 -> 0.046108467 | J21: =Original!J21/Original!$B21 -> 0.95389153 | ... V21: =Original!V21/Original!$B21 -> 0.024036421 | X21: =Original!X21/Original!$B21 -> 0 | Y21: =Original!Y21/Original!$B21 -> 0.061139817
A22: Administração, defesa, saúde e educação públicas e seguridade social | B22: =C22+D22+I22+J22 -> 1 | C22: =Original!C22/Original!$B22 -> 0 | D22: =Original!D22/Original!$B22 -> 0 | E22: =Original!E22/Original!$B22 -> 0 | F22: =Original!F22/Original!$B22 -> 0 | G22: =Original!G22/Original!$B22 -> 0 | H22: =Original!H22/Original!$B22 -> 0 | I22: =Original!I22/Original!$B22 -> 0 | J22: =Original!J22/Original!$B22 -> 1 | ... V22: =Original!V22/Original!$B22 -> 1 | X22: =Original!X22/Original!$B22 -> 0 | Y22: =Original!Y22/Original!$B22 -> 0
A24: Total | B24: =C24+D24+I24+J24 -> 1 | C24: =Original!C24/Original!$B24 -> 0 | D24: =Original!D24/Original!$B24 -> 0 | E24: =Original!E24/Original!$B24 -> 0.0029414174 | F24: =Original!F24/Original!$B24 -> 0.0035998245 | G24: =Original!G24/Original!$B24 -> 0.033690697 | H24: =Original!H24/Original!$B24 -> 0.02511672 | I24: =Original!I24/Original!$B24 -> 0.065348659 | J24: =Original!J24/Original!$B24 -> 0.93465134 | ... V24: =Original!V24/Original!$B24 -> 0.098998072 | X24: =Original!X24/Original!$B24 -> 0 | Y24: =Original!Y24/Original!$B24 -> 0.077672393
A26: Fonte: IBGE, Diretoria de Pesquisas, Coordenação de Contas Nacionais.
A31: II - Tabela de usos de bens e serviços
AF32: Valores correntes em 1 000 000 R$
A33: Descrição do produto | B33: Oferta total a preço de con- sumidor | C33: Margem de comércio | D33: Margem de trans- porte | E33: Imposto de impor- tação | F33: IPI | G33: ICMS | H33: Outros impostos | I33: Total de impostos | J33: Oferta total a preço básico | K33: Consumo intermediário das atividades | X33: PIB / Total da economia (1) | Y33: Demanda final | AF33: De- manda total
K34: Agrope- cuária | L34: Indústrias extrativas | M34: Indústrias de transfor- mação | N34: Eletricida- de e gás, água, esgoto e gestão de resíduos | O34: Cons- trução | P34: Comércio | Q34: Trans- porte, armaze- nagem e correio | R34: Informação e comu- nicação | S34: Atividades financeiras, de seguros e serviços relacio- nados | T34: Ativi- dades imobi- liárias | U34: Outras atividades de serviços | V34: Adminis- tração, defesa, saúde e educação públicas e seguridade social | W34: Total do produto | Y34: Expor- tação de bens e serviços (3) | Z34: Consu- mo do governo | AA34: Consu- mo das ISFLSF | AB34: Consu- mo das famílias | AC34: Forma- ção bruta de capi- tal fixo | AD34: Varia- ção de estoque | AE34: De- manda final | AH34: Agrope- cuária | AI34: Indústrias extrativas | AJ34: Indústrias de transfor- mação | AK34: Eletricida- de e gás, água, esgoto e gestão de resíduos | AL34: Cons- trução | AM34: Comércio | AN34: Trans- porte, armaze- nagem e correio | AO34: Informação e comu- nicação | AP34: Atividades financeiras, de seguros e serviços relacio- nados | AQ34: Ativi- dades imobi- liárias | AR34: Outras atividades de serviços | AS34: Adminis- tração, defesa, saúde e educação públicas e seguridade social | BH34: Agrope- cuária | BI34: Indústrias extrativas | BJ34: Indústrias de transfor- mação | BK34: Eletricida- de e gás, água, esgoto e gestão de resíduos | BL34: Cons- trução | BM34: Comércio | BN34: Trans- porte, armaze- nagem e correio | BO34: Informação e comu- nicação | BP34: Atividades financeiras, de seguros e serviços relacio- nados | BQ34: Ativi- dades imobi- liárias | BR34: Outras atividades de serviços | BS34: Adminis- tração, defesa, saúde e educação públicas e seguridade social
A39: Agropecuária | B39: =B11 -> 1 | K39: =Original!K39/Original!K$69 -> 0.058471074 | L39: =Original!L39/Original!L$69 -> 4.5245695e-06 | M39: =Original!M39/Original!M$69 -> 0.10223284 | N39: =Original!N39/Original!N$69 -> 0.00015173472 | O39: =Original!O39/Original!O$69 -> 0.0017763236 | P39: =Original!P39/Original!P$69 -> 0.012023771 | Q39: =Original!Q39/Original!Q$69 -> 0 | R39: =Original!R39/Original!R$69 -> 0 | ... W39: =Original!W39/Original!W$69 -> 0.034928532 | Y39: =Original!Y39/Original!Y$51 -> 0.19302999 | Z39: =Original!Z39/Original!Z$51 -> 0.00015011056 | AA39: =Original!AA39/Original!AA$51 -> #DIV/0! | AB39: =Original!AB39/Original!AB$51 -> 0.044265104 | AC39: =Original!AC39/Original!AC$51 -> 0.01770316 | AD39: =Original!AD39/Original!AD$51 -> 0.079520633 | AE39: =Original!AE39-Original!AB39 -> 261529 | AF39: =Original!AF39/Original!AF$51 -> 0.060475107 | AH39: =Original!K39/Original!K$71 -> 0.049552231 | AI39: =Original!L39/Original!L$71 -> 4.213711e-06 | AJ39: =Original!M39/Original!M$71 -> 0.059572443 | AK39: =Original!N39/Original!N$71 -> 0.00012945688 | AL39: =Original!O39/Original!O$71 -> 0.0015923567 | AM39: =Original!P39/Original!P$71 -> 0.11999687 | AN39: =Original!Q39/Original!Q$71 -> 0 | AO39: =Original!R39/Original!R$71 -> 0 | ... AS39: =Original!V39/Original!V$71 -> 0.0025135111 | AU39: 1 | BH39: =AU39-AH39-'Matriz consumo'!C25 -> 0.72393393 | BI39: =AV39-AI39-'Matriz consumo'!D25 -> -4.213711e-06 | BJ39: =AW39-AJ39-'Matriz consumo'!E25 -> -0.059572443 | BK39: =AX39-AK39-'Matriz consumo'!F25 -> -0.00012945688 | BL39: =AY39-AL39-'Matriz consumo'!G25 -> -0.0015923567 | BM39: =AZ39-AM39-'Matriz consumo'!H25 -> -0.11999687 | BN39: =BA39-AN39-'Matriz consumo'!I25 -> 0 | BO39: =BB39-AO39-'Matriz consumo'!J25 -> 0 | ... BS39: =BF39-AS39-'Matriz consumo'!N25 -> -0.0025135111 | BU39: {=MINVERSE(BH39:BS50)} -> 1.5055032 | BV39: 0.1180076 | BW39: 0.2949051 | BX39: 0.10110531 | BY39: 0.12262063 | BZ39: 1.5743663 | CA39: 0.19478712 | CB39: 0.077986765 | CC39: 0.053593137 | CD39: 0.043687574 | CE39: 0.12079642 | CF39: 0.045494985 | CH39: {=MMULT(BU39:CF50,AE39:AE50)} -> 938989 | CI39: =Original!AF39 -> 938989
A40: Indústrias extrativas | B40: =B12 -> 1 | K40: =Original!K40/Original!K$69 -> 0.0010983197 | L40: =Original!L40/Original!L$69 -> 0.036470293 | M40: =Original!M40/Original!M$69 -> 0.052587484 | N40: =Original!N40/Original!N$69 -> 0.02826664 | O40: =Original!O40/Original!O$69 -> 0.015655485 | P40: =Original!P40/Original!P$69 -> 8.6148527e-05 | Q40: =Original!Q40/Original!Q$69 -> 9.5404523e-06 | R40: =Original!R40/Original!R$69 -> 0 | ... W40: =Original!W40/Original!W$69 -> 0.017929463 | Y40: =Original!Y40/Original!Y$51 -> 0.20215982 | Z40: =Original!Z40/Original!Z$51 -> 0 | AA40: =Original!AA40/Original!AA$51 -> #DIV/0! | AB40: =Original!AB40/Original!AB$51 -> 0 | AC40: =Original!AC40/Original!AC$51 -> 0.0082961244 | AD40: =Original!AD40/Original!AD$51 -> 0.81176575 | AE40: =Original!AE40-Original!AB40 -> 236068 | AF40: =Original!AF40/Original!AF$51 -> 0.030569011 | AH40: =Original!K40/Original!K$71 -> 0.00093078833 | AI40: =Original!L40/Original!L$71 -> 0.033964617 | AJ40: =Original!M40/Original!M$71 -> 0.030643431 | AK40: =Original!N40/Original!N$71 -> 0.024116504 | AL40: =Original!O40/Original!O$71 -> 0.014034107 | AM40: =Original!P40/Original!P$71 -> 0.00085975969 | AN40: =Original!Q40/Original!Q$71 -> 1.0558027e-05 | AO40: =Original!R40/Original!R$71 -> 0 | ... AS40: =Original!V40/Original!V$71 -> 0.00010168698 | AV40: 1 | BH40: =AU40-AH40-'Matriz consumo'!C26 -> -0.00093078833 | BI40: =AV40-AI40-'Matriz consumo'!D26 -> 0.96603538 | BJ40: =AW40-AJ40-'Matriz consumo'!E26 -> -0.030643431 | BK40: =AX40-AK40-'Matriz consumo'!F26 -> -0.024116504 | BL40: =AY40-AL40-'Matriz consumo'!G26 -> -0.014034107 | BM40: =AZ40-AM40-'Matriz consumo'!H26 -> -0.00085975969 | BN40: =BA40-AN40-'Matriz consumo'!I26 -> -1.0558027e-05 | BO40: =BB40-AO40-'Matriz consumo'!J26 -> 0 | ... BS40: =BF40-AS40-'Matriz consumo'!N26 -> -0.00010168698 | BU40: 0.050902048 | BV40: 1.080461 | BW40: 0.11364538 | BX40: 0.10357996 | BY40: 0.062305237 | BZ40: 0.51176701 | CA40: 0.073538427 | CB40: 0.029403131 | CC40: 0.020687801 | CD40: 0.021492783 | CE40: 0.043434428 | CF40: 0.017229233 | CH40: 474641 | CI40: =Original!AF40 -> 474641
A41: Indústrias de transformação | B41: =B13 -> 1 | K41: =Original!K41/Original!K$69 -> 0.33293288 | L41: =Original!L41/Original!L$69 -> 0.26667134 | M41: =Original!M41/Original!M$69 -> 0.48223075 | N41: =Original!N41/Original!N$69 -> 0.086675712 | O41: =Original!O41/Original!O$69 -> 0.37956346 | P41: =Original!P41/Original!P$69 -> 0.10230458 | Q41: =Original!Q41/Original!Q$69 -> 0.26813123 | R41: =Original!R41/Original!R$69 -> 0.056729286 | ... W41: =Original!W41/Original!W$69 -> 0.23880486 | Y41: =Original!Y41/Original!Y$51 -> 0.48837386 | Z41: =Original!Z41/Original!Z$51 -> 0.0063411922 | AA41: =Original!AA41/Original!AA$51 -> #DIV/0! | AB41: =Original!AB41/Original!AB$51 -> 0.44718069 | AC41: =Original!AC41/Original!AC$51 -> 0.41528709 | AD41: =Original!AD41/Original!AD$51 -> 0.063994333 | AE41: =Original!AE41-Original!AB41 -> 1142372 | AF41: =Original!AF41/Original!AF$51 -> 0.41661087 | AH41: =Original!K41/Original!K$71 -> 0.28214921 | AI41: =Original!L41/Original!L$71 -> 0.24834981 | AJ41: =Original!M41/Original!M$71 -> 0.28100232 | AK41: =Original!N41/Original!N$71 -> 0.073949898 | AL41: =Original!O41/Original!O$71 -> 0.34025355 | AM41: =Original!P41/Original!P$71 -> 1.0209966 | AN41: =Original!Q41/Original!Q$71 -> 0.29672983 | AO41: =Original!R41/Original!R$71 -> 0.046147727 | ... AS41: =Original!V41/Original!V$71 -> 0.058529388 | AW41: 1 | BH41: =AU41-AH41-'Matriz consumo'!C27 -> -0.28214921 | BI41: =AV41-AI41-'Matriz consumo'!D27 -> -0.24834981 | BJ41: =AW41-AJ41-'Matriz consumo'!E27 -> 0.38682621 | BK41: =AX41-AK41-'Matriz consumo'!F27 -> -0.073949898 | BL41: =AY41-AL41-'Matriz consumo'!G27 -> -0.34025355 | BM41: =AZ41-AM41-'Matriz consumo'!H27 -> -1.0209966 | BN41: =BA41-AN41-'Matriz consumo'!I27 -> -0.29672983 | BO41: =BB41-AO41-'Matriz consumo'!J27 -> -0.046147727 | ... BS41: =BF41-AS41-'Matriz consumo'!N27 -> -0.058529388 | BU41: 1.4312586 | BV41: 1.3054817 | BW41: 3.4224757 | BX41: 1.1011722 | BY41: 1.3811254 | BZ41: 13.741392 | CA41: 2.1192819 | CB41: 0.79384158 | CC41: 0.5515202 | CD41: 0.47892931 | CE41: 1.1846347 | CF41: 0.44829911 | CH41: 6468662 | CI41: =Original!AF41 -> 6468662
A42: Eletricidade e gás, água, esgoto e gestão de resíduos | B42: =B14 -> 1 | K42: =Original!K42/Original!K$69 -> 0.023951915 | L42: =Original!L42/Original!L$69 -> 0.0094224161 | M42: =Original!M42/Original!M$69 -> 0.015270963 | N42: =Original!N42/Original!N$69 -> 0.31372364 | O42: =Original!O42/Original!O$69 -> 0.0017959154 | P42: =Original!P42/Original!P$69 -> 0.025287797 | Q42: =Original!Q42/Original!Q$69 -> 0.0083033737 | R42: =Original!R42/Original!R$69 -> 0.010177942 | ... W42: =Original!W42/Original!W$69 -> 0.026038841 | Y42: =Original!Y42/Original!Y$51 -> 1.5973816e-06 | Z42: =Original!Z42/Original!Z$51 -> 0 | AA42: =Original!AA42/Original!AA$51 -> #DIV/0! | AB42: =Original!AB42/Original!AB$51 -> 0.03882952 | AC42: =Original!AC42/Original!AC$51 -> 0 | AD42: =Original!AD42/Original!AD$51 -> 0.0017710609 | AE42: =Original!AE42-Original!AB42 -> -58 | AF42: =Original!AF42/Original!AF$51 -> 0.034327335 | AH42: =Original!K42/Original!K$71 -> 0.020298427 | AI42: =Original!L42/Original!L$71 -> 0.0087750531 | AJ42: =Original!M42/Original!M$71 -> 0.0088985945 | AK42: =Original!N42/Original!N$71 -> 0.26766242 | AL42: =Original!O42/Original!O$71 -> 0.0016099194 | AM42: =Original!P42/Original!P$71 -> 0.25237144 | AN42: =Original!Q42/Original!Q$71 -> 0.0091890028 | AO42: =Original!R42/Original!R$71 -> 0.0082794781 | ... AS42: =Original!V42/Original!V$71 -> 0.018474955 | AX42: 1 | BH42: =AU42-AH42-'Matriz consumo'!C28 -> -0.020298427 | BI42: =AV42-AI42-'Matriz consumo'!D28 -> -0.0087750531 | BJ42: =AW42-AJ42-'Matriz consumo'!E28 -> -0.0088985945 | BK42: =AX42-AK42-'Matriz consumo'!F28 -> 0.38228617 | BL42: =AY42-AL42-'Matriz consumo'!G28 -> -0.0016099194 | BM42: =AZ42-AM42-'Matriz consumo'!H28 -> -0.25237144 | BN42: =BA42-AN42-'Matriz consumo'!I28 -> -0.0091890028 | BO42: =BB42-AO42-'Matriz consumo'!J28 -> -0.0082794781 | ... BS42: =BF42-AS42-'Matriz consumo'!N28 -> -0.018474955 | BU42: 0.15323052 | BV42: 0.12856427 | BW42: 0.17542417 | BX42: 2.7131232 | BY42: 0.084798003 | BZ42: 2.5945324 | CA42: 0.21609476 | CB42: 0.13906997 | CC42: 0.10872922 | CD42: 0.079265281 | CE42: 0.20372244 | CF42: 0.096737231 | CH42: 532996 | CI42: =Original!AF42 -> 532996
A43: Construção | B43: =B15 -> 1 | K43: =Original!K43/Original!K$69 -> 0.00043480392 | L43: =Original!L43/Original!L$69 -> 0.015926485 | M43: =Original!M43/Original!M$69 -> 0.00092402562 | N43: =Original!N43/Original!N$69 -> 0.013392239 | O43: =Original!O43/Original!O$69 -> 0.10526677 | P43: =Original!P43/Original!P$69 -> 0.00091203523 | Q43: =Original!Q43/Original!Q$69 -> 0.0033518789 | R43: =Original!R43/Original!R$69 -> 0.011651609 | ... W43: =Original!W43/Original!W$69 -> 0.0092568885 | Y43: =Original!Y43/Original!Y$51 -> 0.0027802426 | Z43: =Original!Z43/Original!Z$51 -> 0 | AA43: =Original!AA43/Original!AA$51 -> #DIV/0! | AB43: =Original!AB43/Original!AB$51 -> 0 | AC43: =Original!AC43/Original!AC$51 -> 0.4416736 | AD43: =Original!AD43/Original!AD$51 -> 0 | AE43: =Original!AE43-Original!AB43 -> 560090 | AF43: =Original!AF43/Original!AF$51 -> 0.044005269 | AH43: =Original!K43/Original!K$71 -> 0.00036848142 | AI43: =Original!L43/Original!L$71 -> 0.014832263 | AJ43: =Original!M43/Original!M$71 -> 0.00053844211 | AK43: =Original!N43/Original!N$71 -> 0.011425977 | AL43: =Original!O43/Original!O$71 -> 0.094364697 | AM43: =Original!P43/Original!P$71 -> 0.009102084 | AN43: =Original!Q43/Original!Q$71 -> 0.0037093868 | AO43: =Original!R43/Original!R$71 -> 0.0094782659 | ... AS43: =Original!V43/Original!V$71 -> 0.01648148 | AY43: 1 | BH43: =AU43-AH43-'Matriz consumo'!C29 -> -0.00036848142 | BI43: =AV43-AI43-'Matriz consumo'!D29 -> -0.014832263 | BJ43: =AW43-AJ43-'Matriz consumo'!E29 -> -0.00053844211 | BK43: =AX43-AK43-'Matriz consumo'!F29 -> -0.011425977 | BL43: =AY43-AL43-'Matriz consumo'!G29 -> 0.9056353 | BM43: =AZ43-AM43-'Matriz consumo'!H29 -> -0.009102084 | BN43: =BA43-AN43-'Matriz consumo'!I29 -> -0.0037093868 | BO43: =BB43-AO43-'Matriz consumo'!J29 -> -0.0094782659 | ... BS43: =BF43-AS43-'Matriz consumo'!N29 -> -0.01648148 | BU43: 0.0069334269 | BV43: 0.024918184 | BW43: 0.011318007 | BX43: 0.041389699 | BY43: 1.1099579 | BZ43: 0.15453036 | CA43: 0.019285769 | CB43: 0.025480331 | CC43: 0.012508415 | CD43: 0.02059154 | CE43: 0.015979685 | CF43: 0.022934289 | CH43: 683264 | CI43: =Original!AF43 -> 683264
A44: Comércio | B44: =B16 -> 1 | K44: =Original!K44/Original!K$69 -> 0.00044360053 | L44: =Original!L44/Original!L$69 -> 0.0056240399 | M44: =Original!M44/Original!M$69 -> 0.011607492 | N44: =Original!N44/Original!N$69 -> 0.0028587702 | O44: =Original!O44/Original!O$69 -> 0.00080489665 | P44: =Original!P44/Original!P$69 -> 0.008831292 | Q44: =Original!Q44/Original!Q$69 -> 0.013463168 | R44: =Original!R44/Original!R$69 -> 0.0085183451 | ... W44: =Original!W44/Original!W$69 -> 0.0060234331 | Y44: =Original!Y44/Original!Y$51 -> 0.0037346781 | Z44: =Original!Z44/Original!Z$51 -> 0 | AA44: =Original!AA44/Original!AA$51 -> #DIV/0! | AB44: =Original!AB44/Original!AB$51 -> 0.011636203 | AC44: =Original!AC44/Original!AC$51 -> 0 | AD44: =Original!AD44/Original!AD$51 -> 0 | AE44: =Original!AE44-Original!AB44 -> 4676 | AF44: =Original!AF44/Original!AF$51 -> 0.0090640946 | AH44: =Original!K44/Original!K$71 -> 0.00037593625 | AI44: =Original!L44/Original!L$71 -> 0.0052376428 | AJ44: =Original!M44/Original!M$71 -> 0.0067638408 | AK44: =Original!N44/Original!N$71 -> 0.0024390427 | AL44: =Original!O44/Original!O$71 -> 0.00072153662 | AM44: =Original!P44/Original!P$71 -> 0.088136027 | AN44: =Original!Q44/Original!Q$71 -> 0.014899136 | AO44: =Original!R44/Original!R$71 -> 0.0069294414 | ... AS44: =Original!V44/Original!V$71 -> 0.0024090942 | AZ44: 1 | BH44: =AU44-AH44-'Matriz consumo'!C30 -> -0.00037593625 | BI44: =AV44-AI44-'Matriz consumo'!D30 -> -0.0052376428 | BJ44: =AW44-AJ44-'Matriz consumo'!E30 -> -0.0067638408 | BK44: =AX44-AK44-'Matriz consumo'!F30 -> -0.0024390427 | BL44: =AY44-AL44-'Matriz consumo'!G30 -> -0.00072153662 | BM44: =AZ44-AM44-'Matriz consumo'!H30 -> 0.51458394 | BN44: =BA44-AN44-'Matriz consumo'!I30 -> -0.014899136 | BO44: =BB44-AO44-'Matriz consumo'!J30 -> -0.0069294414 | ... BS44: =BF44-AS44-'Matriz consumo'!N30 -> -0.0024090942 | BU44: 0.026278063 | BV44: 0.038412554 | BW44: 0.056262943 | BX44: 0.035802438 | BY44: 0.025467087 | BZ44: 2.2783681 | CA44: 0.08486422 | CB44: 0.040413541 | CC44: 0.017124143 | CD44: 0.011010123 | CE44: 0.031295761 | CF44: 0.015206243 | CH44: 140737 | CI44: =Original!AF44 -> 140737
A45: Transporte, armazenagem e correio | B45: =B17 -> 1 | K45: =Original!K45/Original!K$69 -> 0.016210897 | L45: =Original!L45/Original!L$69 -> 0.082754377 | M45: =Original!M45/Original!M$69 -> 0.040025988 | N45: =Original!N45/Original!N$69 -> 0.011498853 | O45: =Original!O45/Original!O$69 -> 0.0049795837 | P45: =Original!P45/Original!P$69 -> 0.058286242 | Q45: =Original!Q45/Original!Q$69 -> 0.14363628 | R45: =Original!R45/Original!R$69 -> 0.0063399809 | ... W45: =Original!W45/Original!W$69 -> 0.031871311 | Y45: =Original!Y45/Original!Y$51 -> 0.027490138 | Z45: =Original!Z45/Original!Z$51 -> 0 | AA45: =Original!AA45/Original!AA$51 -> #DIV/0! | AB45: =Original!AB45/Original!AB$51 -> 0.02284764 | AC45: =Original!AC45/Original!AC$51 -> 0 | AD45: =Original!AD45/Original!AD$51 -> 0 | AE45: =Original!AE45-Original!AB45 -> 34419 | AF45: =Original!AF45/Original!AF$51 -> 0.036600298 | AH45: =Original!K45/Original!K$71 -> 0.01373818 | AI45: =Original!L45/Original!L$71 -> 0.077068774 | AJ45: =Original!M45/Original!M$71 -> 0.02332368 | AK45: =Original!N45/Original!N$71 -> 0.0098105802 | AL45: =Original!O45/Original!O$71 -> 0.0044638676 | AM45: =Original!P45/Original!P$71 -> 0.58169493 | AN45: =Original!Q45/Original!Q$71 -> 0.15895637 | AO45: =Original!R45/Original!R$71 -> 0.0051574016 | ... AS45: =Original!V45/Original!V$71 -> 0.0082946547 | BA45: 1 | BH45: =AU45-AH45-'Matriz consumo'!C31 -> -0.01373818 | BI45: =AV45-AI45-'Matriz consumo'!D31 -> -0.077068774 | BJ45: =AW45-AJ45-'Matriz consumo'!E31 -> -0.02332368 | BK45: =AX45-AK45-'Matriz consumo'!F31 -> -0.0098105802 | BL45: =AY45-AL45-'Matriz consumo'!G31 -> -0.0044638676 | BM45: =AZ45-AM45-'Matriz consumo'!H31 -> -0.58169493 | BN45: =BA45-AN45-'Matriz consumo'!I31 -> 0.64786165 | BO45: =BB45-AO45-'Matriz consumo'!J31 -> -0.0051574016 | ... BS45: =BF45-AS45-'Matriz consumo'!N31 -> -0.0082946547 | BU45: 0.12207823 | BV45: 0.22670454 | BW45: 0.20828198 | BX45: 0.14055638 | BY45: 0.098746172 | BZ45: 2.876521 | CA45: 1.7316933 | CB45: 0.10215276 | CC45: 0.085464385 | CD45: 0.047774265 | CE45: 0.12594309 | CF45: 0.055588906 | CH45: 568288 | CI45: =Original!AF45 -> 568288
A46: Informação e comunicação | B46: =B18 -> 1 | K46: =Original!K46/Original!K$69 -> 7.9169499e-05 | L46: =Original!L46/Original!L$69 -> 0.0041399811 | M46: =Original!M46/Original!M$69 -> 0.0059017726 | N46: =Original!N46/Original!N$69 -> 0.007131532 | O46: =Original!O46/Original!O$69 -> 0.0028653014 | P46: =Original!P46/Original!P$69 -> 0.017883295 | Q46: =Original!Q46/Original!Q$69 -> 0.010583542 | R46: =Original!R46/Original!R$69 -> 0.13004536 | ... W46: =Original!W46/Original!W$69 -> 0.020155343 | Y46: =Original!Y46/Original!Y$51 -> 0.012205593 | Z46: =Original!Z46/Original!Z$51 -> 0 | AA46: =Original!AA46/Original!AA$51 -> #DIV/0! | AB46: =Original!AB46/Original!AB$51 -> 0.03176064 | AC46: =Original!AC46/Original!AC$51 -> 0.080075256 | AD46: =Original!AD46/Original!AD$51 -> 0.042948226 | AE46: =Original!AE46-Original!AB46 -> 114740 | AF46: =Original!AF46/Original!AF$51 -> 0.034491244 | AH46: =Original!K46/Original!K$71 -> 6.7093438e-05 | AI46: =Original!L46/Original!L$71 -> 0.0038555456 | AJ46: =Original!M46/Original!M$71 -> 0.003439042 | AK46: =Original!N46/Original!N$71 -> 0.0060844734 | AL46: =Original!O46/Original!O$71 -> 0.0025685533 | AM46: =Original!P46/Original!P$71 -> 0.17847474 | AN46: =Original!Q46/Original!Q$71 -> 0.011712371 | AO46: =Original!R46/Original!R$71 -> 0.10578835 | ... AS46: =Original!V46/Original!V$71 -> 0.025396494 | BB46: 1 | BH46: =AU46-AH46-'Matriz consumo'!C32 -> -6.7093438e-05 | BI46: =AV46-AI46-'Matriz consumo'!D32 -> -0.0038555456 | BJ46: =AW46-AJ46-'Matriz consumo'!E32 -> -0.003439042 | BK46: =AX46-AK46-'Matriz consumo'!F32 -> -0.0060844734 | BL46: =AY46-AL46-'Matriz consumo'!G32 -> -0.0025685533 | BM46: =AZ46-AM46-'Matriz consumo'!H32 -> -0.17847474 | BN46: =BA46-AN46-'Matriz consumo'!I32 -> -0.011712371 | BO46: =BB46-AO46-'Matriz consumo'!J32 -> 0.60924747 | ... BS46: =BF46-AS46-'Matriz consumo'!N32 -> -0.025396494 | BU46: 0.047752493 | BV46: 0.079355299 | BW46: 0.091000171 | BX46: 0.10048946 | BY46: 0.052534733 | BZ46: 1.6347275 | CA46: 0.15086518 | CB46: 1.7286777 | CC46: 0.2454361 | CD46: 0.081122018 | CE46: 0.18766387 | CF46: 0.084487591 | CH46: 535541 | CI46: =Original!AF46 -> 535541
A47: Atividades financeiras, de seguros e serviços relacionados | B47: =B19 -> 1 | K47: =Original!K47/Original!K$69 -> 0.01526212 | L47: =Original!L47/Original!L$69 -> 0.019960139 | M47: =Original!M47/Original!M$69 -> 0.018067977 | N47: =Original!N47/Original!N$69 -> 0.025629974 | O47: =Original!O47/Original!O$69 -> 0.015706097 | P47: =Original!P47/Original!P$69 -> 0.027053485 | Q47: =Original!Q47/Original!Q$69 -> 0.026600371 | R47: =Original!R47/Original!R$69 -> 0.032905006 | ... W47: =Original!W47/Original!W$69 -> 0.030911081 | Y47: =Original!Y47/Original!Y$51 -> 0.0055453101 | Z47: =Original!Z47/Original!Z$51 -> 0.0014129972 | AA47: =Original!AA47/Original!AA$51 -> #DIV/0! | AB47: =Original!AB47/Original!AB$51 -> 0.079013254 | AC47: =Original!AC47/Original!AC$51 -> 0 | AD47: =Original!AD47/Original!AD$51 -> 0 | AE47: =Original!AE47-Original!AB47 -> 9108 | AF47: =Original!AF47/Original!AF$51 -> 0.051528486 | AH47: =Original!K47/Original!K$71 -> 0.012934124 | AI47: =Original!L47/Original!L$71 -> 0.018588786 | AJ47: =Original!M47/Original!M$71 -> 0.010528452 | AK47: =Original!N47/Original!N$71 -> 0.021866956 | AL47: =Original!O47/Original!O$71 -> 0.014079477 | AM47: =Original!P47/Original!P$71 -> 0.26999297 | AN47: =Original!Q47/Original!Q$71 -> 0.029437539 | AO47: =Original!R47/Original!R$71 -> 0.026767325 | ... AS47: =Original!V47/Original!V$71 -> 0.041501255 | BC47: 1 | BH47: =AU47-AH47-'Matriz consumo'!C33 -> -0.012934124 | BI47: =AV47-AI47-'Matriz consumo'!D33 -> -0.018588786 | BJ47: =AW47-AJ47-'Matriz consumo'!E33 -> -0.010528452 | BK47: =AX47-AK47-'Matriz consumo'!F33 -> -0.021866956 | BL47: =AY47-AL47-'Matriz consumo'!G33 -> -0.014079477 | BM47: =AZ47-AM47-'Matriz consumo'!H33 -> -0.26999297 | BN47: =BA47-AN47-'Matriz consumo'!I33 -> -0.029437539 | BO47: =BB47-AO47-'Matriz consumo'!J33 -> -0.026767325 | ... BS47: =BF47-AS47-'Matriz consumo'!N33 -> -0.041501255 | BU47: 0.15362147 | BV47: 0.18984006 | BW47: 0.22394836 | BX47: 0.27814824 | BY47: 0.14361444 | BZ47: 3.5015474 | CA47: 0.35648648 | CB47: 0.25133535 | CC47: 2.702519 | CD47: 0.55481293 | CE47: 0.22777671 | CF47: 0.17311415 | CH47: 800076 | CI47: =Original!AF47 -> 800076
A48: Atividades imobiliárias | B48: =B20 -> 1 | K48: =Original!K48/Original!K$69 -> 3.3929785e-05 | L48: =Original!L48/Original!L$69 -> 0.0016854022 | M48: =Original!M48/Original!M$69 -> 0.0023820919 | N48: =Original!N48/Original!N$69 -> 0.0035580693 | O48: =Original!O48/Original!O$69 -> 0.0024457103 | P48: =Original!P48/Original!P$69 -> 0.04232883 | Q48: =Original!Q48/Original!Q$69 -> 0.010195563 | R48: =Original!R48/Original!R$69 -> 0.014819304 | ... W48: =Original!W48/Original!W$69 -> 0.010907999 | Y48: =Original!Y48/Original!Y$51 -> 0.0037442624 | Z48: =Original!Z48/Original!Z$51 -> 0 | AA48: =Original!AA48/Original!AA$51 -> #DIV/0! | AB48: =Original!AB48/Original!AB$51 -> 0.13386107 | AC48: =Original!AC48/Original!AC$51 -> 0 | AD48: =Original!AD48/Original!AD$51 -> 0 | AE48: =Original!AE48-Original!AB48 -> 4688 | AF48: =Original!AF48/Original!AF$51 -> 0.051075014 | AH48: =Original!K48/Original!K$71 -> 2.875433e-05 | AI48: =Original!L48/Original!L$71 -> 0.0015696073 | AJ48: =Original!M48/Original!M$71 -> 0.0013880769 | AK48: =Original!N48/Original!N$71 -> 0.0030356701 | AL48: =Original!O48/Original!O$71 -> 0.0021924176 | AM48: =Original!P48/Original!P$71 -> 0.42244044 | AN48: =Original!Q48/Original!Q$71 -> 0.011283011 | AO48: =Original!R48/Original!R$71 -> 0.012055099 | ... AS48: =Original!V48/Original!V$71 -> 0.003260808 | BD48: 1 | BH48: =AU48-AH48-'Matriz consumo'!C34 -> -2.875433e-05 | BI48: =AV48-AI48-'Matriz consumo'!D34 -> -0.0015696073 | BJ48: =AW48-AJ48-'Matriz consumo'!E34 -> -0.0013880769 | BK48: =AX48-AK48-'Matriz consumo'!F34 -> -0.0030356701 | BL48: =AY48-AL48-'Matriz consumo'!G34 -> -0.0021924176 | BM48: =AZ48-AM48-'Matriz consumo'!H34 -> -0.42244044 | BN48: =BA48-AN48-'Matriz consumo'!I34 -> -0.011283011 | BO48: =BB48-AO48-'Matriz consumo'!J34 -> -0.012055099 | ... BS48: =BF48-AS48-'Matriz consumo'!N34 -> -0.003260808 | BU48: 0.12312792 | BV48: 0.20237888 | BW48: 0.24876816 | BX48: 0.22699151 | BY48: 0.13599561 | BZ48: 6.8274553 | CA48: 0.44493502 | CB48: 0.32486047 | CC48: 0.27596493 | CD48: 5.5011284 | CE48: 0.40175163 | CF48: 0.11500347 | CH48: 793035 | CI48: =Original!AF48 -> 793035
A49: Outras atividades de serviços | B49: =B21 -> 1 | K49: =Original!K49/Original!K$69 -> 0.0049110223 | L49: =Original!L49/Original!L$69 -> 0.11932873 | M49: =Original!M49/Original!M$69 -> 0.052900268 | N49: =Original!N49/Original!N$69 -> 0.047264267 | O49: =Original!O49/Original!O$69 -> 0.031719132 | P49: =Original!P49/Original!P$69 -> 0.11737986 | Q49: =Original!Q49/Original!Q$69 -> 0.081254442 | R49: =Original!R49/Original!R$69 -> 0.1834784 | ... W49: =Original!W49/Original!W$69 -> 0.077543331 | Y49: =Original!Y49/Original!Y$51 -> 0.060934516 | Z49: =Original!Z49/Original!Z$51 -> 0.035773304 | AA49: =Original!AA49/Original!AA$51 -> #DIV/0! | AB49: =Original!AB49/Original!AB$51 -> 0.19060588 | AC49: =Original!AC49/Original!AC$51 -> 0.036964769 | AD49: =Original!AD49/Original!AD$51 -> 0 | AE49: =Original!AE49-Original!AB49 -> 177689 | AF49: =Original!AF49/Original!AF$51 -> 0.1368826 | AH49: =Original!K49/Original!K$71 -> 0.0041619231 | AI49: =Original!L49/Original!L$71 -> 0.11113031 | AJ49: =Original!M49/Original!M$71 -> 0.030825695 | AK49: =Original!N49/Original!N$71 -> 0.04032488 | AL49: =Original!O49/Original!O$71 -> 0.028434105 | AM49: =Original!P49/Original!P$71 -> 1.1714475 | AN49: =Original!Q49/Original!Q$71 -> 0.089920956 | AO49: =Original!R49/Original!R$71 -> 0.14925468 | ... AS49: =Original!V49/Original!V$71 -> 0.089354192 | BE49: 1 | BH49: =AU49-AH49-'Matriz consumo'!C35 -> -0.0041619231 | BI49: =AV49-AI49-'Matriz consumo'!D35 -> -0.11113031 | BJ49: =AW49-AJ49-'Matriz consumo'!E35 -> -0.030825695 | BK49: =AX49-AK49-'Matriz consumo'!F35 -> -0.04032488 | BL49: =AY49-AL49-'Matriz consumo'!G35 -> -0.028434105 | BM49: =AZ49-AM49-'Matriz consumo'!H35 -> -1.1714475 | BN49: =BA49-AN49-'Matriz consumo'!I35 -> -0.089920956 | BO49: =BB49-AO49-'Matriz consumo'!J35 -> -0.14925468 | ... BS49: =BF49-AS49-'Matriz consumo'!N35 -> -0.089354192 | BU49: 0.27381905 | BV49: 0.56953947 | BW49: 0.53624397 | BX49: 0.54887912 | BY49: 0.31587107 | BZ49: 8.984651 | CA49: 0.86130433 | CB49: 0.81141749 | CC49: 0.73434905 | CD49: 0.32998146 | CE49: 2.4906023 | CF49: 0.35097316 | CH49: 2125358 | CI49: =Original!AF49 -> 2125358
A50: Administração, defesa, saúde e educação públicas e seguridade social | B50: =B22 -> 1 | K50: =Original!K50/Original!K$69 -> 0 | L50: =Original!L50/Original!L$69 -> 0 | M50: =Original!M50/Original!M$69 -> 0 | N50: =Original!N50/Original!N$69 -> 0 | O50: =Original!O50/Original!O$69 -> 0 | P50: =Original!P50/Original!P$69 -> 0 | Q50: =Original!Q50/Original!Q$69 -> 0 | R50: =Original!R50/Original!R$69 -> 0 | ... W50: =Original!W50/Original!W$69 -> 0 | Y50: =Original!Y50/Original!Y$51 -> 0 | Z50: =Original!Z50/Original!Z$51 -> 0.9563224 | AA50: =Original!AA50/Original!AA$51 -> #DIV/0! | AB50: =Original!AB50/Original!AB$51 -> 0 | AC50: =Original!AC50/Original!AC$51 -> 0 | AD50: =Original!AD50/Original!AD$51 -> 0 | AE50: =Original!AE50-Original!AB50 -> 1465281 | AF50: =Original!AF50/Original!AF$51 -> 0.094370674 | AH50: =Original!K50/Original!K$71 -> 0 | AI50: =Original!L50/Original!L$71 -> 0 | AJ50: =Original!M50/Original!M$71 -> 0 | AK50: =Original!N50/Original!N$71 -> 0 | AL50: =Original!O50/Original!O$71 -> 0 | AM50: =Original!P50/Original!P$71 -> 0 | AN50: =Original!Q50/Original!Q$71 -> 0 | AO50: =Original!R50/Original!R$71 -> 0 | ... AS50: =Original!V50/Original!V$71 -> 0 | BF50: 1 | BH50: =AU50-AH50-'Matriz consumo'!C36 -> 0 | BI50: =AV50-AI50-'Matriz consumo'!D36 -> 0 | BJ50: =AW50-AJ50-'Matriz consumo'!E36 -> 0 | BK50: =AX50-AK50-'Matriz consumo'!F36 -> 0 | BL50: =AY50-AL50-'Matriz consumo'!G36 -> 0 | BM50: =AZ50-AM50-'Matriz consumo'!H36 -> 0 | BN50: =BA50-AN50-'Matriz consumo'!I36 -> 0 | BO50: =BB50-AO50-'Matriz consumo'!J36 -> 0 | ... BS50: =BF50-AS50-'Matriz consumo'!N36 -> 1 | BU50: 0 | BV50: 0 | BW50: 0 | BX50: 0 | BY50: 0 | BZ50: 0 | CA50: 0 | CB50: 0 | CC50: 0 | CD50: 0 | CE50: 0 | CF50: 1 | CH50: 1465281 | CI50: =Original!AF50 -> 1465281
A51: Total | B51: =SUM(B39:B50) -> 12 | K51: =Original!K51/Original!K$69 -> 0.45382973 | L51: =Original!L51/Original!L$69 -> 0.56198773 | M51: =Original!M51/Original!M$69 -> 0.78413164 | N51: =Original!N51/Original!N$69 -> 0.54015143 | O51: =Original!O51/Original!O$69 -> 0.56257867 | P51: =Original!P51/Original!P$69 -> 0.41237734 | Q51: =Original!Q51/Original!Q$69 -> 0.56552939 | R51: =Original!R51/Original!R$69 -> 0.45466523 | ... W51: =Original!W51/Original!W$69 -> 0.50437108 | Y51: =SUM(Y39:Y50) -> 1 | Z51: =SUM(Z39:Z50) -> 1 | AA51: =SUM(AA39:AA50) -> #DIV/0! | AB51: =SUM(AB39:AB50) -> 1 | AC51: =SUM(AC39:AC50) -> 1 | AD51: =SUM(AD39:AD50) -> 1 | AE51: =Original!AE51-Original!AB51 -> 4010602 | AF51: =W51+AE51 -> 4010602.5
A52: Componentes do valor adicionado
A54: Valor adicionado bruto ( PIB ) | I54: =I24 -> 0.065348659 | K54: =Original!K54/Original!K$69 -> 0.54617027 | L54: =Original!L54/Original!L$69 -> 0.43801227 | M54: =Original!M54/Original!M$69 -> 0.21586836 | N54: =Original!N54/Original!N$69 -> 0.45984857 | O54: =Original!O54/Original!O$69 -> 0.43742133 | P54: =Original!P54/Original!P$69 -> 0.58762266 | Q54: =Original!Q54/Original!Q$69 -> 0.43447061 | R54: =Original!R54/Original!R$69 -> 0.54533477 | ... W54: =Original!W54/Original!W$69 -> 0.49562892 | X54: =I54+W54 -> 0.56097758
A55: Remunerações | K55: =Original!K55/Original!K$69 -> 0.070908225 | L55: =Original!L55/Original!L$69 -> 0.070198696 | M55: =Original!M55/Original!M$69 -> 0.11458316 | N55: =Original!N55/Original!N$69 -> 0.093107945 | O55: =Original!O55/Original!O$69 -> 0.17994093 | P55: =Original!P55/Original!P$69 -> 0.28782721 | Q55: =Original!Q55/Original!Q$69 -> 0.22963233 | R55: =Original!R55/Original!R$69 -> 0.24401581 | ... W55: =Original!W55/Original!W$69 -> 0.23991397 | X55: =I55+W55 -> 0.23991397 | AA55: TABELA DE RECURSOS E USOS
A56: Salários | K56: =Original!K56/Original!K$69 -> 0.060897682 | L56: =Original!L56/Original!L$69 -> 0.053265495 | M56: =Original!M56/Original!M$69 -> 0.09090762 | N56: =Original!N56/Original!N$69 -> 0.069006313 | O56: =Original!O56/Original!O$69 -> 0.14736629 | P56: =Original!P56/Original!P$69 -> 0.22933236 | Q56: =Original!Q56/Original!Q$69 -> 0.18416253 | R56: =Original!R56/Original!R$69 -> 0.19380325 | ... W56: =Original!W56/Original!W$69 -> 0.19028432 | X56: =I56+W56 -> 0.19028432
A57: Contribuições sociais efetivas | K57: =Original!K57/Original!K$69 -> 0.010010543 | L57: =Original!L57/Original!L$69 -> 0.016933202 | M57: =Original!M57/Original!M$69 -> 0.023675537 | N57: =Original!N57/Original!N$69 -> 0.024101631 | O57: =Original!O57/Original!O$69 -> 0.032574641 | P57: =Original!P57/Original!P$69 -> 0.05849485 | Q57: =Original!Q57/Original!Q$69 -> 0.045469796 | R57: =Original!R57/Original!R$69 -> 0.050212557 | ... W57: =Original!W57/Original!W$69 -> 0.042282323 | X57: =I57+W57 -> 0.042282323 | AA57: I - Tabela de recursos de bens e serviços
A58: Previdência oficial /FGTS | K58: =Original!K58/Original!K$69 -> 0.010010543 | L58: =Original!L58/Original!L$69 -> 0.014573639 | M58: =Original!M58/Original!M$69 -> 0.022693942 | N58: =Original!N58/Original!N$69 -> 0.020237894 | O58: =Original!O58/Original!O$69 -> 0.032068519 | P58: =Original!P58/Original!P$69 -> 0.057973687 | Q58: =Original!Q58/Original!Q$69 -> 0.042947936 | R58: =Original!R58/Original!R$69 -> 0.046257529 | ... W58: =Original!W58/Original!W$69 -> 0.040686375 | X58: =I58+W58 -> 0.040686375 | AB58: Oferta A = | AC58: Produção A1 + | AD58: Importação A2
A59: Previdência privada | K59: =Original!K59/Original!K$69 -> 0 | L59: =Original!L59/Original!L$69 -> 0.002359563 | M59: =Original!M59/Original!M$69 -> 0.00098159483 | N59: =Original!N59/Original!N$69 -> 0.0038637378 | O59: =Original!O59/Original!O$69 -> 0.00050612162 | P59: =Original!P59/Original!P$69 -> 0.00052116299 | Q59: =Original!Q59/Original!Q$69 -> 0.0025218596 | R59: =Original!R59/Original!R$69 -> 0.0039550279 | ... W59: =Original!W59/Original!W$69 -> 0.0015959479 | X59: =I59+W59 -> 0.0015959479
A60: Contribuições sociais imputadas | K60: =Original!K60/Original!K$69 -> 0 | L60: =Original!L60/Original!L$69 -> 0 | M60: =Original!M60/Original!M$69 -> 0 | N60: =Original!N60/Original!N$69 -> 0 | O60: =Original!O60/Original!O$69 -> 0 | P60: =Original!P60/Original!P$69 -> 0 | Q60: =Original!Q60/Original!Q$69 -> 0 | R60: =Original!R60/Original!R$69 -> 0 | ... W60: =Original!W60/Original!W$69 -> 0.0073473274 | X60: =I60+W60 -> 0.0073473274
A61: Excedente operacional bruto e rendimento misto bruto | K61: =Original!K61/Original!K$69 -> 0.47846275 | L61: =Original!L61/Original!L$69 -> 0.36187507 | M61: =Original!M61/Original!M$69 -> 0.093894056 | N61: =Original!N61/Original!N$69 -> 0.35765414 | O61: =Original!O61/Original!O$69 -> 0.25209591 | P61: =Original!P61/Original!P$69 -> 0.2905861 | Q61: =Original!Q61/Original!Q$69 -> 0.19600223 | R61: =Original!R61/Original!R$69 -> 0.2882832 | ... W61: =Original!W61/Original!W$69 -> 0.24922241 | X61: =I61+W61 -> 0.24922241 | AA61: II - Tabela de usos de bens e serviços
A62: Rendimento misto bruto | K62: =Original!K62/Original!K$69 -> 0.25550511 | L62: =Original!L62/Original!L$69 -> 0.00055652205 | M62: =Original!M62/Original!M$69 -> 0.0071624587 | N62: =Original!N62/Original!N$69 -> 0.0029511304 | O62: =Original!O62/Original!O$69 -> 0.10753289 | P62: =Original!P62/Original!P$69 -> 0.058912065 | Q62: =Original!Q62/Original!Q$69 -> 0.046571718 | R62: =Original!R62/Original!R$69 -> 0.026849658 | ... W62: =Original!W62/Original!W$69 -> 0.047599168 | X62: =I62+W62 -> 0.047599168 | AB62: Oferta A = | AC62: Consumo interme- diário B1 + | AD62: Demanda final B2
A63: Excedente operacional bruto (EOB) | K63: =Original!K63/Original!K$69 -> 0.22295765 | L63: =Original!L63/Original!L$69 -> 0.36131855 | M63: =Original!M63/Original!M$69 -> 0.086731597 | N63: =Original!N63/Original!N$69 -> 0.35470301 | O63: =Original!O63/Original!O$69 -> 0.14456303 | P63: =Original!P63/Original!P$69 -> 0.23167404 | Q63: =Original!Q63/Original!Q$69 -> 0.14943051 | R63: =Original!R63/Original!R$69 -> 0.26143354 | ... W63: =Original!W63/Original!W$69 -> 0.20162324 | X63: =I63+W63 -> 0.20162324
A64: Impostos líquidos de subsídios sobre a produção e a importação | I64: =I65+I66 -> 1014660 | K64: =Original!K64/Original!K$69 -> -0.0032007098 | L64: =Original!L64/Original!L$69 -> 0.0059384975 | M64: =Original!M64/Original!M$69 -> 0.0073911438 | N64: =Original!N64/Original!N$69 -> 0.009086491 | O64: =Original!O64/Original!O$69 -> 0.005384481 | P64: =Original!P64/Original!P$69 -> 0.0092093488 | Q64: =Original!Q64/Original!Q$69 -> 0.0088360489 | R64: =Original!R64/Original!R$69 -> 0.013035754 | ... W64: =Original!W64/Original!W$69 -> 0.0064925378 | X64: =I64+W64 -> 1014660
A65: Impostos sobre produtos | I65: 1020210 | K65: =Original!K65/Original!K$69 -> 0 | L65: =Original!L65/Original!L$69 -> 0 | M65: =Original!M65/Original!M$69 -> 0 | N65: =Original!N65/Original!N$69 -> 0 | O65: =Original!O65/Original!O$69 -> 0 | P65: =Original!P65/Original!P$69 -> 0 | Q65: =Original!Q65/Original!Q$69 -> 0 | R65: =Original!R65/Original!R$69 -> 0 | ... W65: =Original!W65/Original!W$69 -> 0 | X65: =I65+W65 -> 1020210
A66: Subsídios sobre produtos | I66: -5550 | K66: =Original!K66/Original!K$69 -> 0 | L66: =Original!L66/Original!L$69 -> 0 | M66: =Original!M66/Original!M$69 -> 0 | N66: =Original!N66/Original!N$69 -> 0 | O66: =Original!O66/Original!O$69 -> 0 | P66: =Original!P66/Original!P$69 -> 0 | Q66: =Original!Q66/Original!Q$69 -> 0 | R66: =Original!R66/Original!R$69 -> 0 | ... W66: =Original!W66/Original!W$69 -> 0 | X66: =I66+W66 -> -5550
A67: Outros impostos sobre a produção | K67: =Original!K67/Original!K$69 -> 0.0038152159 | L67: =Original!L67/Original!L$69 -> 0.0060086284 | M67: =Original!M67/Original!M$69 -> 0.0075707491 | N67: =Original!N67/Original!N$69 -> 0.0092052399 | O67: =Original!O67/Original!O$69 -> 0.0055983582 | P67: =Original!P67/Original!P$69 -> 0.0093752381 | Q67: =Original!Q67/Original!Q$69 -> 0.0098091751 | R67: =Original!R67/Original!R$69 -> 0.013088549 | ... W67: =Original!W67/Original!W$69 -> 0.0071010512 | X67: =I67+W67 -> 0.0071010512 | AB67: Componentes do valor adicionado C
A68: Outros subsídios à produção | K68: =Original!K68/Original!K$69 -> -0.0070159256 | L68: =Original!L68/Original!L$69 -> -7.0130828e-05 | M68: =Original!M68/Original!M$69 -> -0.00017960532 | N68: =Original!N68/Original!N$69 -> -0.00011874891 | O68: =Original!O68/Original!O$69 -> -0.0002138772 | P68: =Original!P68/Original!P$69 -> -0.00016588931 | Q68: =Original!Q68/Original!Q$69 -> -0.00097312614 | R68: =Original!R68/Original!R$69 -> -5.2794917e-05 | ... W68: =Original!W68/Original!W$69 -> -0.00060851337 | X68: =I68+W68 -> -0.00060851337
A69: Valor da produção | K69: =Original!K69/Original!K$69 -> 1 | L69: =Original!L69/Original!L$69 -> 1 | M69: =Original!M69/Original!M$69 -> 1 | N69: =Original!N69/Original!N$69 -> 1 | O69: =Original!O69/Original!O$69 -> 1 | P69: =Original!P69/Original!P$69 -> 1 | Q69: =Original!Q69/Original!Q$69 -> 1 | R69: =Original!R69/Original!R$69 -> 1 | ... W69: =Original!W69/Original!W$69 -> 1 | X69: =I69+W69 -> 1
A70: Fator trabalho (ocupações) | K70: 12560399 | L70: 212274 | M70: 10560359 | N70: 742087 | O70: 7047825 | P70: 17613390 | Q70: 4932125 | R70: 1405295 | S70: 1410816 | T70: 502337 | U70: 30453062 | V70: 11814707 | W70: =SUM(K70:V70) -> 99254676 | X70: =I70+W70 -> 99254676
A72: Fonte: IBGE, Diretoria de Pesquisas, Coordenação de Contas Nacionais. | K72: {=TRANSPOSE(Original!B39:B51)} -> 938989 | L72: 474641 | M72: 6468662 | N72: 532996 | O72: 683264 | P72: 140737 | Q72: 568288 | R72: 535541 | S72: 800076 | T72: 793035 | U72: 2125358 | V72: 1465281 | W72: 15526868
A73: (1) O PIB corresponde à soma do valor adicionado a preços básicos das atividades econômicas mais o total dos impostos, líquido de subsídios, sobre produtos. (2) Importação de bens e serviços líquida de ajuste CIF/FOB. (3) Exportação de bens e serviços acrescida de ajuste CIF/FOB.

Sheet Matriz consumo
C2: Agrope- cuária | D2: Indústrias extrativas | E2: Indústrias de transfor- mação | F2: Eletricida- de e gás, água, esgoto e gestão de resíduos | G2: Cons- trução | H2: Comércio | I2: Trans- porte, armaze- nagem e correio | J2: Informação e comu- nicação | K2: Atividades financeiras, de seguros e serviços relacio- nados | L2: Ativi- dades imobi- liárias | M2: Outras atividades de serviços | N2: Adminis- tração, defesa, saúde e educação públicas e seguridade social
B6: Agropecuária | C6: =Original!AB39 -> 212694
B7: Indústrias extrativas | D7: =Original!AB40 -> 0
B8: Indústrias de transformação | E8: =Original!AB41 -> 2148705
B9: Eletricidade e gás, água, esgoto e gestão de resíduos | F9: =Original!AB42 -> 186576
B10: Construção | G10: =Original!AB43 -> 0
B11: Comércio | H11: =Original!AB44 -> 55912
B12: Transporte, armazenagem e correio | I12: =Original!AB45 -> 109783
B13: Informação e comunicação | J13: =Original!AB46 -> 152610
B14: Atividades financeiras, de seguros e serviços relacionados | K14: =Original!AB47 -> 379659
B15: Atividades imobiliárias | L15: =Original!AB48 -> 643203
B16: Outras atividades de serviços | M16: =Original!AB49 -> 915862
B17: Administração, defesa, saúde e educação públicas e seguridade social | N17: =Original!AB50 -> 0
B19: Total | C19: =Original!K71 -> 938989 | D19: =Original!L71 -> 474641 | E19: =Original!M71 -> 6468662 | F19: =Original!N71 -> 532996 | G19: =Original!O71 -> 683264 | H19: =Original!P71 -> 140737 | I19: =Original!Q71 -> 568288 | J19: =Original!R71 -> 535541 | ... N19: =Original!V71 -> 1465281
C21: Agrope- cuária | D21: Indústrias extrativas | E21: Indústrias de transfor- mação | F21: Eletricida- de e gás, água, esgoto e gestão de resíduos | G21: Cons- trução | H21: Comércio | I21: Trans- porte, armaze- nagem e correio | J21: Informação e comu- nicação | K21: Atividades financeiras, de seguros e serviços relacio- nados | L21: Ativi- dades imobi- liárias | M21: Outras atividades de serviços | N21: Adminis- tração, defesa, saúde e educação públicas e seguridade social
B25: Agropecuária | C25: =C6/C$19 -> 0.22651384 | D25: =D6/D$19 -> 0 | E25: =E6/E$19 -> 0 | F25: =F6/F$19 -> 0 | G25: =G6/G$19 -> 0 | H25: =H6/H$19 -> 0 | I25: =I6/I$19 -> 0 | J25: =J6/J$19 -> 0 | ... N25: =N6/N$19 -> 0
B26: Indústrias extrativas | C26: =C7/C$19 -> 0 | D26: =D7/D$19 -> 0 | E26: =E7/E$19 -> 0 | F26: =F7/F$19 -> 0 | G26: =G7/G$19 -> 0 | H26: =H7/H$19 -> 0 | I26: =I7/I$19 -> 0 | J26: =J7/J$19 -> 0 | ... N26: =N7/N$19 -> 0
B27: Indústrias de transformação | C27: =C8/C$19 -> 0 | D27: =D8/D$19 -> 0 | E27: =E8/E$19 -> 0.33217148 | F27: =F8/F$19 -> 0 | G27: =G8/G$19 -> 0 | H27: =H8/H$19 -> 0 | I27: =I8/I$19 -> 0 | J27: =J8/J$19 -> 0 | ... N27: =N8/N$19 -> 0
B28: Eletricidade e gás, água, esgoto e gestão de resíduos | C28: =C9/C$19 -> 0 | D28: =D9/D$19 -> 0 | E28: =E9/E$19 -> 0 | F28: =F9/F$19 -> 0.35005141 | G28: =G9/G$19 -> 0 | H28: =H9/H$19 -> 0 | I28: =I9/I$19 -> 0 | J28: =J9/J$19 -> 0 | ... N28: =N9/N$19 -> 0
B29: Construção | C29: =C10/C$19 -> 0 | D29: =D10/D$19 -> 0 | E29: =E10/E$19 -> 0 | F29: =F10/F$19 -> 0 | G29: =G10/G$19 -> 0 | H29: =H10/H$19 -> 0 | I29: =I10/I$19 -> 0 | J29: =J10/J$19 -> 0 | ... N29: =N10/N$19 -> 0
B30: Comércio | C30: =C11/C$19 -> 0 | D30: =D11/D$19 -> 0 | E30: =E11/E$19 -> 0 | F30: =F11/F$19 -> 0 | G30: =G11/G$19 -> 0 | H30: =H11/H$19 -> 0.39728003 | I30: =I11/I$19 -> 0 | J30: =J11/J$19 -> 0 | ... N30: =N11/N$19 -> 0
B31: Transporte, armazenagem e correio | C31: =C12/C$19 -> 0 | D31: =D12/D$19 -> 0 | E31: =E12/E$19 -> 0 | F31: =F12/F$19 -> 0 | G31: =G12/G$19 -> 0 | H31: =H12/H$19 -> 0 | I31: =I12/I$19 -> 0.19318198 | J31: =J12/J$19 -> 0 | ... N31: =N12/N$19 -> 0
B32: Informação e comunicação | C32: =C13/C$19 -> 0 | D32: =D13/D$19 -> 0 | E32: =E13/E$19 -> 0 | F32: =F13/F$19 -> 0 | G32: =G13/G$19 -> 0 | H32: =H13/H$19 -> 0 | I32: =I13/I$19 -> 0 | J32: =J13/J$19 -> 0.28496418 | ... N32: =N13/N$19 -> 0
B33: Atividades financeiras, de seguros e serviços relacionados | C33: =C14/C$19 -> 0 | D33: =D14/D$19 -> 0 | E33: =E14/E$19 -> 0 | F33: =F14/F$19 -> 0 | G33: =G14/G$19 -> 0 | H33: =H14/H$19 -> 0 | I33: =I14/I$19 -> 0 | J33: =J14/J$19 -> 0 | ... N33: =N14/N$19 -> 0
B34: Atividades imobiliárias | C34: =C15/C$19 -> 0 | D34: =D15/D$19 -> 0 | E34: =E15/E$19 -> 0 | F34: =F15/F$19 -> 0 | G34: =G15/G$19 -> 0 | H34: =H15/H$19 -> 0 | I34: =I15/I$19 -> 0 | J34: =J15/J$19 -> 0 | ... N34: =N15/N$19 -> 0
B35: Outras atividades de serviços | C35: =C16/C$19 -> 0 | D35: =D16/D$19 -> 0 | E35: =E16/E$19 -> 0 | F35: =F16/F$19 -> 0 | G35: =G16/G$19 -> 0 | H35: =H16/H$19 -> 0 | I35: =I16/I$19 -> 0 | J35: =J16/J$19 -> 0 | ... N35: =N16/N$19 -> 0
B36: Administração, defesa, saúde e educação públicas e seguridade social | C36: =C17/C$19 -> 0 | D36: =D17/D$19 -> 0 | E36: =E17/E$19 -> 0 | F36: =F17/F$19 -> 0 | G36: =G17/G$19 -> 0 | H36: =H17/H$19 -> 0 | I36: =I17/I$19 -> 0 | J36: =J17/J$19 -> 0 | ... N36: =N17/N$19 -> 0
B38: Total | C38: =Original!K90 -> 0 | D38: =Original!L90 -> 0 | E38: =Original!M90 -> 0 | F38: =Original!N90 -> 0 | G38: =Original!O90 -> 0 | H38: =Original!P90 -> 0 | I38: =Original!Q90 -> 0 | J38: =Original!R90 -> 0 | ... N38: =Original!V90 -> 0

Sheet SimulCEI
R1: Consumo resolvido supondo consumo como proporção da demanda total. Método tradicional de INPUT-OUTPUT. Questão: % não é constante em relação à renda da família.
C2: S.14 Famílias | E2: S.13 Governo Geral | G2: S.12 Empresas finan- ceiras | I2: S.11 Empresas não- finan- ceiras | K2: Setor externo
P3: Saldo Governo | R3: Expor- tação de bens e serviços (3) | S3: Consu- mo do governo | T3: Consu- mo das ISFLSF | U3: Consu- mo das famílias | V3: Forma- ção bruta de capi- tal fixo | W3: Varia- ção de estoque | X3: Demanda autônoma | Y3: Demanda induzida | Z3: Demanda final | AA3: De- manda TOTAL | AD3: Expor- tação de bens e serviços (3) | AE3: Consu- mo do governo | AF3: Consu- mo das ISFLSF | AG3: Consu- mo das famílias | AH3: Forma- ção bruta de capi- tal fixo | AI3: Varia- ção de estoque | AJ3: Demanda autônoma | AK3: Demanda induzida | AL3: Demanda final | AM3: De- manda TOTAL
P4: =E28/N7 -> -0.12063832
C6: Entrada | D6: Saída | E6: Entrada | F6: Saída | G6: Entrada | H6: Saída | I6: Entrada | J6: Saída | K6: Entrada (Importações) | L6: Saída (Exportações) | N6: VA preço mercado | O6: VA preço básico | P6: Saldo Bal.Comercial e Serv
B7: Valor adicionado bruto/Produto interno bruto (1) | C7: =CEIResumida!D80 -> 0 | D7: =CEIResumida!E80 -> 0 | E7: =CEIResumida!F80 -> 0 | F7: =CEIResumida!G80 -> 0 | G7: =SimulTRU!S54 -> 454550 | H7: 0 | I7: =SimulTRU!X54-SimulTRU!S54 -> 7155047 | J7: 0 | K7: =SimulTRU!Y24 -> 1206009 | L7: =R20 -> 1252049 | M7: =G7+I7+K7-L7 -> 7563557 | N7: =G7+I7 -> 7609597 | O7: =N7-J11 -> 6662425 | P7: =(L7-K7)/N7 -> 0.0060502547
A8: Tabela de Usos e Recursos - específico por setor - geração de renda | B8: Salários | C8: =SimulTRU!W56 -> 2531961 | D8: =CEIResumida!E81 -> 0 | E8: =CEIResumida!F81 -> 0 | F8: =CEIResumida!G81 -> 0 | G8: =CEIResumida!H81 -> 0 | H8: =SimulTRU!S56 -> 140274 | I8: =CEIResumida!J81 -> 0 | J8: =SimulTRU!W56-SimulTRU!S56 -> 2391687 | K8: =CEIResumida!L81 -> 0 | L8: =CEIResumida!M81 -> 0 | M8: =C8+E8+G8+I8+K8-L8-J8-H8-F8-D8 -> 2.910383e-11 | R8: 241683 | S8: 230 | U8: =Y8 -> 212694 | V8: 22310 | W8: -2694 | X8: =R8+S8+V8+W8 -> 261529 | Y8: =SimulTRU!CL39 -> 212694 | Z8: =X8+Y8 -> 474223 | AA8: =SimulTRU!CH39 -> 938989 | AB8: =SimulTRU!CK39 -> 464766 | AD8: =IFERROR(R8/R47-1,0) -> 0 | AE8: =IFERROR(S8/S47-1,0) -> 0 | AF8: =IFERROR(T8/T47-1,0) -> 0 | AG8: =IFERROR(U8/U47-1,0) -> -1.110223e-16 | AH8: =IFERROR(V8/V47-1,0) -> 0 | AI8: =IFERROR(W8/W47-1,0) -> 0 | AJ8: =IFERROR(X8/X47-1,0) -> 0 | AK8: =IFERROR(Y8/Y47-1,0) -> 0 | ... AM8: =IFERROR(AA8/AA47-1,0) -> 0
B9: Contribuições sociais efetivas | C9: =SimulTRU!W57 -> 562617 | D9: =CEIResumida!E82 -> 0 | E9: =CEIResumida!F82 -> 0 | F9: =CEIResumida!G82 -> 0 | G9: =CEIResumida!H82 -> 0 | H9: =SimulTRU!S57 -> 41011 | I9: =CEIResumida!J82 -> 0 | J9: =SimulTRU!W57-SimulTRU!S57 -> 521606 | K9: =CEIResumida!L82 -> 0 | L9: =CEIResumida!M82 -> 0 | M9: =C9+E9+G9+I9+K9-L9-J9-H9-F9-D9 -> 1.4551915e-11 | R9: =253114 -> 253114 | S9: 0 | U9: =Y9 -> 0 | V9: 10455 | W9: -27501 | X9: =R9+S9+V9+W9 -> 236068 | Y9: =SimulTRU!CL40 -> 0 | Z9: =X9+Y9 -> 236068 | AA9: =SimulTRU!CH40 -> 474641 | AB9: =SimulTRU!CK40 -> 238573 | AD9: =IFERROR(R9/R48-1,0) -> 0 | AE9: =IFERROR(S9/S48-1,0) -> 0 | AF9: =IFERROR(T9/T48-1,0) -> 0 | AG9: =IFERROR(U9/U48-1,0) -> 0 | AH9: =IFERROR(V9/V48-1,0) -> 0 | AI9: =IFERROR(W9/W48-1,0) -> 0 | AJ9: =IFERROR(X9/X48-1,0) -> 0 | AK9: =IFERROR(Y9/Y48-1,0) -> 0 | ... AM9: =IFERROR(AA9/AA48-1,0) -> 0
B10: Contribuições sociais inputadas | C10: =CEIResumida!D83 -> 0 | D10: =CEIResumida!E83 -> 0 | E10: =CEIResumida!F83 -> 0 | F10: =CEIResumida!G83 -> 0 | G10: =CEIResumida!H83 -> 0 | H10: =CEIResumida!I83 -> 0 | I10: =CEIResumida!J83 -> 0 | J10: =CEIResumida!K83 -> 0 | ... L10: =CEIResumida!M83 -> 0 | M10: =C10+E10+G10+I10+K10-L10-J10-H10-F10-D10 -> 0 | R10: =611468*1 -> 611468 | S10: 9716 | U10: =Y10 -> 2148705 | V10: 523356 | W10: -2168 | X10: =R10+S10+V10+W10 -> 1142372 | Y10: =SimulTRU!CL41 -> 2148705 | Z10: =X10+Y10 -> 3291077 | AA10: =SimulTRU!CH41 -> 6468662 | AB10: =SimulTRU!CK41 -> 3177585 | AD10: =IFERROR(R10/R49-1,0) -> 0 | AE10: =IFERROR(S10/S49-1,0) -> 0 | AF10: =IFERROR(T10/T49-1,0) -> 0 | AG10: =IFERROR(U10/U49-1,0) -> -2.220446e-16 | AH10: =IFERROR(V10/V49-1,0) -> 0 | AI10: =IFERROR(W10/W49-1,0) -> 0 | AJ10: =IFERROR(X10/X49-1,0) -> 0 | AK10: =IFERROR(Y10/Y49-1,0) -> -2.220446e-16 | ... AM10: =IFERROR(AA10/AA49-1,0) -> 0
B11: Impostos, líquidos de subsídios, sobre produtos | C11: =CEIResumida!D84 -> 0 | D11: =CEIResumida!E84 -> 0 | E11: =SimulTRU!I24 -> 1014660 | F11: =CEIResumida!G84 -> 0 | G11: =CEIResumida!H84 -> 0 | H11: =SimulTRU!I19 -> 67488 | I11: =CEIResumida!J84 -> 0 | J11: =SimulTRU!I24-SimulTRU!I19 -> 947172 | K11: =CEIResumida!L84 -> 0 | L11: =CEIResumida!M84 -> 0 | M11: =C11+E11+G11+I11+K11-L11-J11-H11-F11-D11 -> 1.4551915e-11 | R11: 2 | S11: 0 | U11: =Y11 -> 186576 | V11: 0 | W11: -60 | X11: =R11+S11+V11+W11 -> -58 | Y11: =SimulTRU!CL42 -> 186576 | Z11: =X11+Y11 -> 186518 | AA11: =SimulTRU!CH42 -> 532996 | AB11: =SimulTRU!CK42 -> 346478 | AD11: =IFERROR(R11/R50-1,0) -> 0 | AE11: =IFERROR(S11/S50-1,0) -> 0 | AF11: =IFERROR(T11/T50-1,0) -> 0 | AG11: =IFERROR(U11/U50-1,0) -> -4.4408921e-16 | AH11: =IFERROR(V11/V50-1,0) -> 0 | AI11: =IFERROR(W11/W50-1,0) -> 0 | AJ11: =IFERROR(X11/X50-1,0) -> 0 | AK11: =IFERROR(Y11/Y50-1,0) -> -4.4408921e-16 | ... AM11: =IFERROR(AA11/AA50-1,0) -> 0
B12: Outros impostos, líquidos de subsídios, sobre a produção | C12: =CEIResumida!D85 -> 0 | D12: =CEIResumida!E85 -> 0 | E12: =SimulTRU!W64 -> 86391 | F12: =CEIResumida!G85 -> 0 | G12: =CEIResumida!H85 -> 0 | H12: =SimulTRU!S64 -> 9262 | I12: =CEIResumida!J85 -> 0 | J12: =SimulTRU!W64-SimulTRU!S64 -> 77129 | K12: =CEIResumida!L85 -> 0 | L12: =CEIResumida!M85 -> 0 | M12: =C12+E12+G12+I12+K12-L12-J12-H12-F12-D12 -> 1.8189894e-12 | R12: 3481 | S12: 0 | U12: =Y12 -> 0 | V12: 556609 | W12: 0 | X12: =R12+S12+V12+W12 -> 560090 | Y12: =SimulTRU!CL43 -> 0 | Z12: =X12+Y12 -> 560090 | AA12: =SimulTRU!CH43 -> 683264 | AB12: =SimulTRU!CK43 -> 123174 | AD12: =IFERROR(R12/R51-1,0) -> 0 | AE12: =IFERROR(S12/S51-1,0) -> 0 | AF12: =IFERROR(T12/T51-1,0) -> 0 | AG12: =IFERROR(U12/U51-1,0) -> 0 | AH12: =IFERROR(V12/V51-1,0) -> 0 | AI12: =IFERROR(W12/W51-1,0) -> 0 | AJ12: =IFERROR(X12/X51-1,0) -> 0 | AK12: =IFERROR(Y12/Y51-1,0) -> 0 | ... AM12: =IFERROR(AA12/AA51-1,0) -> 0
A13: Alocação primária do excedente | B13: Juros | C13: =CEIResumida!D86 -> 249546 | D13: =CEIResumida!E86 -> 205143 | E13: =CEIResumida!F86 -> 191053 | F13: =CEIResumida!G86 -> 446981 | G13: =CEIResumida!H86 -> 1235025 | H13: =CEIResumida!I86 -> 1060460 | I13: =CEIResumida!J86 -> 246213 | J13: =CEIResumida!K86 -> 282899 | ... L13: =CEIResumida!M86 -> 32573 | M13: =C13+E13+G13+I13+K13-L13-J13-H13-F13-D13 -> 0 | R13: 4676 | S13: 0 | U13: =Y13 -> 55912 | V13: 0 | W13: 0 | X13: =R13+S13+V13+W13 -> 4676 | Y13: =SimulTRU!CL44 -> 55912 | Z13: =X13+Y13 -> 60588 | AA13: =SimulTRU!CH44 -> 140737 | AB13: =SimulTRU!CK44 -> 80149 | AD13: =IFERROR(R13/R52-1,0) -> 0 | AE13: =IFERROR(S13/S52-1,0) -> 0 | AF13: =IFERROR(T13/T52-1,0) -> 0 | AG13: =IFERROR(U13/U52-1,0) -> -5.5511151e-16 | AH13: =IFERROR(V13/V52-1,0) -> 0 | AI13: =IFERROR(W13/W52-1,0) -> 0 | AJ13: =IFERROR(X13/X52-1,0) -> 0 | AK13: =IFERROR(Y13/Y52-1,0) -> -5.5511151e-16 | ... AM13: =IFERROR(AA13/AA52-1,0) -> 0
B14: Rendas distribuídas das empresas | C14: =CEIResumida!D87 -> 1888670 | D14: =CEIResumida!E87 -> 0 | E14: =CEIResumida!F87 -> 0 | F14: =CEIResumida!G87 -> 0 | G14: =CEIResumida!H87 -> 0 | H14: =CEIResumida!I87 -> 153250 | I14: =CEIResumida!J87 -> 0 | J14: =CEIResumida!K87 -> 1821126 | ... L14: =CEIResumida!M87 -> 0 | M14: =C14+E14+G14+I14+K14-L14-J14-H14-F14-D14 -> 0 | R14: 34419 | S14: 0 | U14: =Y14 -> 109783 | V14: 0 | W14: 0 | X14: =R14+S14+V14+W14 -> 34419 | Y14: =SimulTRU!CL45 -> 109783 | Z14: =X14+Y14 -> 144202 | AA14: =SimulTRU!CH45 -> 568288 | AB14: =SimulTRU!CK45 -> 424086 | AD14: =IFERROR(R14/R53-1,0) -> 0 | AE14: =IFERROR(S14/S53-1,0) -> 0 | AF14: =IFERROR(T14/T53-1,0) -> 0 | AG14: =IFERROR(U14/U53-1,0) -> -4.4408921e-16 | AH14: =IFERROR(V14/V53-1,0) -> 0 | AI14: =IFERROR(W14/W53-1,0) -> 0 | AJ14: =IFERROR(X14/X53-1,0) -> 0 | AK14: =IFERROR(Y14/Y53-1,0) -> -4.4408921e-16 | ... AM14: =IFERROR(AA14/AA53-1,0) -> 0
B15: Lucros reinvestidos de investimento estrangeiro direto | C15: =CEIResumida!D88 -> 0 | D15: =CEIResumida!E88 -> 0 | E15: =CEIResumida!F88 -> 0 | F15: =CEIResumida!G88 -> 0 | G15: =CEIResumida!H88 -> 0 | H15: =CEIResumida!I88 -> 0 | I15: =CEIResumida!J88 -> 0 | J15: =CEIResumida!K88 -> 0 | ... L15: =CEIResumida!M88 -> 0 | M15: =C15+E15+G15+I15+K15-L15-J15-H15-F15-D15 -> 0 | R15: 15282 | S15: 0 | U15: =Y15 -> 152610 | V15: 100913 | W15: -1455 | X15: =R15+S15+V15+W15 -> 114740 | Y15: =SimulTRU!CL46 -> 152610 | Z15: =X15+Y15 -> 267350 | AA15: =SimulTRU!CH46 -> 535541 | AB15: =SimulTRU!CK46 -> 268191 | AD15: =IFERROR(R15/R54-1,0) -> 0 | AE15: =IFERROR(S15/S54-1,0) -> 0 | AF15: =IFERROR(T15/T54-1,0) -> 0 | AG15: =IFERROR(U15/U54-1,0) -> -3.3306691e-16 | AH15: =IFERROR(V15/V54-1,0) -> 0 | AI15: =IFERROR(W15/W54-1,0) -> 0 | AJ15: =IFERROR(X15/X54-1,0) -> 0 | AK15: =IFERROR(Y15/Y54-1,0) -> -3.3306691e-16 | ... AM15: =IFERROR(AA15/AA54-1,0) -> 0
B16: Desembolsos por rendas de investimentos | C16: =CEIResumida!D89 -> 0 | D16: =CEIResumida!E89 -> 0 | E16: =CEIResumida!F89 -> 0 | F16: =CEIResumida!G89 -> 0 | G16: =CEIResumida!H89 -> 0 | H16: =CEIResumida!I89 -> 0 | I16: =CEIResumida!J89 -> 0 | J16: =CEIResumida!K89 -> 0 | ... L16: =CEIResumida!M89 -> 0 | M16: =C16+E16+G16+I16+K16-L16-J16-H16-F16-D16 -> 0 | R16: 6943 | S16: 2165 | U16: =Y16 -> 379659 | V16: 0 | W16: 0 | X16: =R16+S16+V16+W16 -> 9108 | Y16: =SimulTRU!CL47 -> 379659 | Z16: =X16+Y16 -> 388767 | AA16: =SimulTRU!CH47 -> 800076 | AB16: =SimulTRU!CK47 -> 411309 | AD16: =IFERROR(R16/R55-1,0) -> 0 | AE16: =IFERROR(S16/S55-1,0) -> 0 | AF16: =IFERROR(T16/T55-1,0) -> 0 | AG16: =IFERROR(U16/U55-1,0) -> -3.3306691e-16 | AH16: =IFERROR(V16/V55-1,0) -> 0 | AI16: =IFERROR(W16/W55-1,0) -> 0 | AJ16: =IFERROR(X16/X55-1,0) -> 0 | AK16: =IFERROR(Y16/Y55-1,0) -> -3.3306691e-16 | ... AM16: =IFERROR(AA16/AA55-1,0) -> 0
B17: Renda de recursos naturais | C17: =CEIResumida!D90 -> 0 | D17: =CEIResumida!E90 -> 0 | E17: =CEIResumida!F90 -> 0 | F17: =CEIResumida!G90 -> 0 | G17: =CEIResumida!H90 -> 0 | H17: =CEIResumida!I90 -> 0 | I17: =CEIResumida!J90 -> 0 | J17: =CEIResumida!K90 -> 0 | ... L17: =CEIResumida!M90 -> 0 | M17: =C17+E17+G17+I17+K17-L17-J17-H17-F17-D17 -> 0 | R17: 4688 | S17: 0 | U17: =Y17 -> 643203 | V17: 0 | W17: 0 | X17: =R17+S17+V17+W17 -> 4688 | Y17: =SimulTRU!CL48 -> 643203 | Z17: =X17+Y17 -> 647891 | AA17: =SimulTRU!CH48 -> 793035 | AB17: =SimulTRU!CK48 -> 145144 | AD17: =IFERROR(R17/R56-1,0) -> 0 | AE17: =IFERROR(S17/S56-1,0) -> 0 | AF17: =IFERROR(T17/T56-1,0) -> 0 | AG17: =IFERROR(U17/U56-1,0) -> 2.220446e-16 | AH17: =IFERROR(V17/V56-1,0) -> 0 | AI17: =IFERROR(W17/W56-1,0) -> 0 | AJ17: =IFERROR(X17/X56-1,0) -> 0 | AK17: =IFERROR(Y17/Y56-1,0) -> 2.220446e-16 | ... AM17: =IFERROR(AA17/AA56-1,0) -> 0
A18: Alocação secundária | B18: Impostos correntes sobre a renda, patrimônio, // Contribuições sociais // Outras transferências | C18: =CEIResumida!D91 -> 0 | D18: =CEIResumida!E91 -> 362776 | E18: =D18+H18+J18 -> 917257 | F18: =CEIResumida!G91 -> 0 | G18: =CEIResumida!H91 -> 0 | H18: =CEIResumida!I91 -> 42715 | I18: =CEIResumida!J91 -> 0 | J18: =CEIResumida!K91 -> 511766 | K18: =CEIResumida!L91 -> 0 | L18: =CEIResumida!M91 -> 0 | M18: =C18+E18+G18+I18+K18-L18-J18-H18-F18-D18 -> 0 | R18: 76293 | S18: =54812 -> 54812 | U18: =Y18 -> 915862 | V18: 46584 | W18: 0 | X18: =R18+S18+V18+W18 -> 177689 | Y18: =SimulTRU!CL49 -> 915862 | Z18: =X18+Y18 -> 1093551 | AA18: =SimulTRU!CH49 -> 2125358 | AB18: =SimulTRU!CK49 -> 1031807 | AD18: =IFERROR(R18/R57-1,0) -> 0 | AE18: =IFERROR(S18/S57-1,0) -> 0 | AF18: =IFERROR(T18/T57-1,0) -> 0 | AG18: =IFERROR(U18/U57-1,0) -> 0 | AH18: =IFERROR(V18/V57-1,0) -> 0 | AI18: =IFERROR(W18/W57-1,0) -> 0 | AJ18: =IFERROR(X18/X57-1,0) -> 0 | AK18: =IFERROR(Y18/Y57-1,0) -> 0 | ... AM18: =IFERROR(AA18/AA57-1,0) -> 0
B19: Contribuições sociais | C19: =CEIResumida!D92 -> 0 | D19: =CEIResumida!E92 -> 895266 | E19: =CEIResumida!F92 -> 800730 | F19: =CEIResumida!G92 -> 0 | G19: =CEIResumida!H92 -> 94536 | H19: =CEIResumida!I92 -> 0 | I19: =CEIResumida!J92 -> 0 | J19: =CEIResumida!K92 -> 0 | ... L19: =CEIResumida!M92 -> 0 | M19: =C19+E19+G19+I19+K19-L19-J19-H19-F19-D19 -> 0 | R19: 0 | S19: =1465281*1 -> 1465281 | U19: =Y19 -> 0 | V19: 0 | W19: 0 | X19: =R19+S19+V19+W19 -> 1465281 | Y19: =SimulTRU!CL50 -> 0 | Z19: =X19+Y19 -> 1465281 | AA19: =SimulTRU!CH50 -> 1465281 | AB19: =SimulTRU!CK50 -> 0 | AD19: =IFERROR(R19/R58-1,0) -> 0 | AE19: =IFERROR(S19/S58-1,0) -> 0 | AF19: =IFERROR(T19/T58-1,0) -> 0 | AG19: =IFERROR(U19/U58-1,0) -> 0 | AH19: =IFERROR(V19/V58-1,0) -> 0 | AI19: =IFERROR(W19/W58-1,0) -> 0 | AJ19: =IFERROR(X19/X58-1,0) -> 0 | AK19: =IFERROR(Y19/Y58-1,0) -> 0 | ... AM19: =IFERROR(AA19/AA58-1,0) -> 0
B20: Benefícios de seguridade social em numerário // Seguro desemprego, bolsa família | C20: =CEIResumida!D93 -> 1254637 | D20: =CEIResumida!E93 -> 0 | E20: =CEIResumida!F93 -> 0 | F20: =CEIResumida!G93 -> 1254637 | G20: =CEIResumida!H93 -> 0 | H20: =CEIResumida!I93 -> 0 | I20: =CEIResumida!J93 -> 0 | J20: =CEIResumida!K93 -> 0 | ... L20: =CEIResumida!M93 -> 0 | M20: =C20+E20+G20+I20+K20-L20-J20-H20-F20-D20 -> 0 | R20: =SUM(R8:R19) -> 1252049 | S20: =SUM(S8:S19) -> 1532204 | T20: =SUM(T8:T19) -> 0 | U20: =SUM(U8:U19) -> 4805004 | V20: =SUM(V8:V19) -> 1260227 | W20: =SUM(W8:W19) -> -33878 | X20: =SUM(X8:X19) -> 4010602 | Y20: =SUM(Y8:Y19) -> 4805004 | ... AA20: =SUM(AA8:AA19) -> 15526868 | AD20: =IFERROR(R20/R59-1,0) -> 0 | AE20: =IFERROR(S20/S59-1,0) -> 0 | AF20: =IFERROR(T20/T59-1,0) -> 0 | AG20: =IFERROR(U20/U59-1,0) -> 0 | AH20: =IFERROR(V20/V59-1,0) -> 0 | AI20: =IFERROR(W20/W59-1,0) -> 0 | AJ20: =IFERROR(X20/X59-1,0) -> 0 | AK20: =IFERROR(Y20/Y59-1,0) -> 0 | ... AM20: =IFERROR(AA20/AA59-1,0) -> 0
B21: Outros benefícios de seguro social // Previdência | C21: =CEIResumida!D94 -> 717798 | D21: =CEIResumida!E94 -> 0 | E21: =CEIResumida!F94 -> 0 | F21: =CEIResumida!G94 -> 624646 | G21: =CEIResumida!H94 -> 0 | H21: =CEIResumida!I94 -> 93152 | I21: =CEIResumida!J94 -> 0 | J21: =CEIResumida!K94 -> 0 | ... L21: =CEIResumida!M94 -> 0 | M21: =C21+E21+G21+I21+K21-L21-J21-H21-F21-D21 -> 0
B22: Outras transferências correntes | C22: =CEIResumida!D95 -> 35242 | D22: =CEIResumida!E95 -> 0 | E22: =CEIResumida!F95 -> 70054 | F22: =CEIResumida!G95 -> 0 | G22: =CEIResumida!H95 -> 0 | H22: =CEIResumida!I95 -> 13352 | I22: =CEIResumida!J95 -> 0 | J22: =CEIResumida!K95 -> 59170 | ... L22: =CEIResumida!M95 -> 32774 | M22: =C22+E22+G22+I22+K22-L22-J22-H22-F22-D22 -> 0 | O22: Demanda final | R22: Expor- tação de bens e serviços (3) | S22: Consu- mo do governo | U22: Consu- mo das famílias | V22: Forma- ção bruta de capi- tal fixo | W22: Varia- ção de estoque | X22: Demanda autônoma | Y22: Demanda induzida | Z22: Demanda final | AA22: De- manda TOTAL | AD22: Expor- tação de bens e serviços (3) | AE22: Consu- mo do governo | AG22: Consu- mo das famílias | AH22: Forma- ção bruta de capi- tal fixo | AI22: Varia- ção de estoque | AJ22: Demanda autônoma | AK22: Demanda induzida | AL22: Demanda final | AM22: De- manda TOTAL
A23: Usos da renda | B23: Consumo final efetivo | C23: =CEIResumida!D96 -> 0 | D23: =U20 -> 4805004 | E23: =CEIResumida!F96 -> 0 | F23: =S20 -> 1532204 | G23: =CEIResumida!H96 -> 0 | H23: =CEIResumida!I96 -> 0 | I23: =CEIResumida!J96 -> 0 | J23: =CEIResumida!K96 -> 0 | K23: =CEIResumida!L96 -> 0 | L23: =CEIResumida!M96 -> 0 | M23: =C23+E23+G23+I23+K23-L23-J23-H23-F23-D23 -> -6337208 | O23: =D23+D25+F23+F25+H25+J25+J26+L7 -> 8815606
B24: Ajustamento pela variação dos direitos de pensão | C24: =CEIResumida!D97 -> 0 | D24: =CEIResumida!E97 -> 0 | E24: =CEIResumida!F97 -> 0 | F24: =CEIResumida!G97 -> 0 | G24: =CEIResumida!H97 -> 0 | H24: =CEIResumida!I97 -> 0 | I24: =CEIResumida!J97 -> 0 | J24: =CEIResumida!K97 -> 0 | ... L24: =CEIResumida!M97 -> 0 | M24: =C24+E24+G24+I24+K24-L24-J24-H24-F24-D24 -> 0
B25: Formação bruta de capital fixo | C25: =CEIResumida!D98 -> 0 | D25: =(SUM(C8:C22)-SUM(D8:D22))*ParâmetrosCEI!D58 -> 410010 | E25: =CEIResumida!F98 -> 0 | F25: =CEIResumida!G98 -> 139686 | G25: =CEIResumida!H98 -> 0 | H25: =CEIResumida!I98 -> 13718 | I25: =CEIResumida!J98 -> 0 | J25: =CEIResumida!K98 -> 696813 | K25: =CEIResumida!L98 -> 0 | L25: =CEIResumida!M98 -> 0 | M25: =C25+E25+G25+I25+K25-L25-J25-H25-F25-D25 -> -1260227 | N25: Multiplicador | O25: =Z20 -> 8815606
B26: Variação de estoques | C26: =CEIResumida!D99 -> 0 | D26: =CEIResumida!E99 -> 0 | E26: =CEIResumida!F99 -> 0 | F26: =CEIResumida!G99 -> 0 | G26: =CEIResumida!H99 -> 0 | H26: =CEIResumida!I99 -> 0 | I26: =CEIResumida!J99 -> 0 | J26: =CEIResumida!K99 -> -33878 | ... L26: =CEIResumida!M99 -> 0 | M26: =C26+E26+G26+I26+K26-L26-J26-H26-F26-D26 -> 33878 | N26: Por % | O26: =Z39 -> 8815606
B27: Aquisições líquidas de cessões de ativos não-produzidos | C27: =CEIResumida!D100 -> 0 | D27: =CEIResumida!E100 -> 0 | E27: =CEIResumida!F100 -> 0 | F27: =CEIResumida!G100 -> 0 | G27: =CEIResumida!H100 -> 0 | H27: =CEIResumida!I100 -> 0 | I27: =CEIResumida!J100 -> 0 | J27: =CEIResumida!K100 -> 0 | ... L27: =CEIResumida!M100 -> 0 | M27: =C27+E27+G27+I27+K27-L27-J27-H27-F27-D27 -> 0 | N27: Correto | O27: =Original!AE51 -> 8815606 | R27: =R8 -> 241683 | S27: =S8 -> 230 | U27: =U8 -> 212694 | V27: 22310 | W27: -2694 | X27: =R27+S27+V27+W27 -> 261529 | Y27: =Z27-X27 -> 212694 | Z27: =SUM(R27:W27) -> 474223 | AA27: =Z27+AB27 -> 938989 | AB27: =SimulTRU!CK39 -> 464766 | AD27: =IFERROR(R27/R47-1,0) -> 0 | AE27: =IFERROR(S27/S47-1,0) -> 0 | AF27: =IFERROR(T27/T47-1,0) -> 0 | AG27: =IFERROR(U27/U47-1,0) -> -1.110223e-16 | AH27: =IFERROR(V27/V47-1,0) -> 0 | AI27: =IFERROR(W27/W47-1,0) -> 0 | AJ27: =IFERROR(X27/X47-1,0) -> 0 | AK27: =IFERROR(Y27/Y47-1,0) -> 0 | ... AM27: =IFERROR(AA27/AA47-1,0) -> 0
B28: Capacidade (+) / Necessidade(-) líquida de financiamento | C28: =SUM(C7:C27)-SUM(D7:D27) -> 562272 | E28: =SUM(E7:E27)-SUM(F7:F27) -> -918009 | G28: =SUM(G7:G27)-SUM(H7:H27) -> 149429 | I28: =SUM(I7:I27)-SUM(J7:J27) -> 125770 | K28: =-SUM(C28:J28) -> 80538 | M28: =C28+E28+G28+I28+K28-L28-J28-H28-F28-D28 -> 0 | R28: =R9 -> 253114 | S28: =S9 -> 0 | U28: =U9 -> 0 | V28: 10455 | W28: -27501 | X28: =R28+S28+V28+W28 -> 236068 | Y28: =Z28-X28 -> 0 | Z28: =SUM(R28:W28) -> 236068 | AA28: =Z28+AB28 -> 474641 | AB28: =SimulTRU!CK40 -> 238573 | AD28: =IFERROR(R28/R48-1,0) -> 0 | AE28: =IFERROR(S28/S48-1,0) -> 0 | AF28: =IFERROR(T28/T48-1,0) -> 0 | AG28: =IFERROR(U28/U48-1,0) -> 0 | AH28: =IFERROR(V28/V48-1,0) -> 0 | AI28: =IFERROR(W28/W48-1,0) -> 0 | AJ28: =IFERROR(X28/X48-1,0) -> 0 | AK28: =IFERROR(Y28/Y48-1,0) -> 0 | ... AM28: =IFERROR(AA28/AA48-1,0) -> 2.220446e-16
B29: Check | C29: 562272 | E29: -918009 | G29: 149429 | I29: 125770 | K29: 80538 | M29: =C29+E29+G29+I29+K29-L29-J29-H29-F29-D29 -> 0 | R29: =R10 -> 611468 | S29: =S10 -> 9716 | U29: =U10 -> 2148705 | V29: 523356 | W29: -2168 | X29: =R29+S29+V29+W29 -> 1142372 | Y29: =Z29-X29 -> 2148705 | Z29: =SUM(R29:W29) -> 3291077 | AA29: =Z29+AB29 -> 6468662 | AB29: =SimulTRU!CK41 -> 3177585 | AD29: =IFERROR(R29/R49-1,0) -> 0 | AE29: =IFERROR(S29/S49-1,0) -> 0 | AF29: =IFERROR(T29/T49-1,0) -> 0 | AG29: =IFERROR(U29/U49-1,0) -> -2.220446e-16 | AH29: =IFERROR(V29/V49-1,0) -> 0 | AI29: =IFERROR(W29/W49-1,0) -> 0 | AJ29: =IFERROR(X29/X49-1,0) -> 0 | AK29: =IFERROR(Y29/Y49-1,0) -> -2.220446e-16 | ... AM29: =IFERROR(AA29/AA49-1,0) -> 2.220446e-16
R30: =R11 -> 2 | S30: =S11 -> 0 | U30: =U11 -> 186576 | V30: 0 | W30: -60 | X30: =R30+S30+V30+W30 -> -58 | Y30: =Z30-X30 -> 186576 | Z30: =SUM(R30:W30) -> 186518 | AA30: =Z30+AB30 -> 532996 | AB30: =SimulTRU!CK42 -> 346478 | AD30: =IFERROR(R30/R50-1,0) -> 0 | AE30: =IFERROR(S30/S50-1,0) -> 0 | AF30: =IFERROR(T30/T50-1,0) -> 0 | AG30: =IFERROR(U30/U50-1,0) -> -4.4408921e-16 | AH30: =IFERROR(V30/V50-1,0) -> 0 | AI30: =IFERROR(W30/W50-1,0) -> 0 | AJ30: =IFERROR(X30/X50-1,0) -> 0 | AK30: =IFERROR(Y30/Y50-1,0) -> -4.4408921e-16 | ... AM30: =IFERROR(AA30/AA50-1,0) -> 2.220446e-16
D31: =C28/C29-1 -> 0 | F31: =E28/E29-1 -> 0 | H31: =G28/G29-1 -> 0 | J31: =I28/I29-1 -> 0 | L31: =K28/K29-1 -> 0 | R31: =R12 -> 3481 | S31: =S12 -> 0 | U31: =U12 -> 0 | V31: 556609 | W31: 0 | X31: =R31+S31+V31+W31 -> 560090 | Y31: =Z31-X31 -> 0 | Z31: =SUM(R31:W31) -> 560090 | AA31: =Z31+AB31 -> 683264 | AB31: =SimulTRU!CK43 -> 123174 | AD31: =IFERROR(R31/R51-1,0) -> 0 | AE31: =IFERROR(S31/S51-1,0) -> 0 | AF31: =IFERROR(T31/T51-1,0) -> 0 | AG31: =IFERROR(U31/U51-1,0) -> 0 | AH31: =IFERROR(V31/V51-1,0) -> 0 | AI31: =IFERROR(W31/W51-1,0) -> 0 | AJ31: =IFERROR(X31/X51-1,0) -> 0 | AK31: =IFERROR(Y31/Y51-1,0) -> 0 | ... AM31: =IFERROR(AA31/AA51-1,0) -> -5.5511151e-16
R32: =R13 -> 4676 | S32: =S13 -> 0 | U32: =U13 -> 55912 | V32: 0 | W32: 0 | X32: =R32+S32+V32+W32 -> 4676 | Y32: =Z32-X32 -> 55912 | Z32: =SUM(R32:W32) -> 60588 | AA32: =Z32+AB32 -> 140737 | AB32: =SimulTRU!CK44 -> 80149 | AD32: =IFERROR(R32/R52-1,0) -> 0 | AE32: =IFERROR(S32/S52-1,0) -> 0 | AF32: =IFERROR(T32/T52-1,0) -> 0 | AG32: =IFERROR(U32/U52-1,0) -> -5.5511151e-16 | AH32: =IFERROR(V32/V52-1,0) -> 0 | AI32: =IFERROR(W32/W52-1,0) -> 0 | AJ32: =IFERROR(X32/X52-1,0) -> 0 | AK32: =IFERROR(Y32/Y52-1,0) -> -5.5511151e-16 | ... AM32: =IFERROR(AA32/AA52-1,0) -> 0
R33: =R14 -> 34419 | S33: =S14 -> 0 | U33: =U14 -> 109783 | V33: 0 | W33: 0 | X33: =R33+S33+V33+W33 -> 34419 | Y33: =Z33-X33 -> 109783 | Z33: =SUM(R33:W33) -> 144202 | AA33: =Z33+AB33 -> 568288 | AB33: =SimulTRU!CK45 -> 424086 | AD33: =IFERROR(R33/R53-1,0) -> 0 | AE33: =IFERROR(S33/S53-1,0) -> 0 | AF33: =IFERROR(T33/T53-1,0) -> 0 | AG33: =IFERROR(U33/U53-1,0) -> -4.4408921e-16 | AH33: =IFERROR(V33/V53-1,0) -> 0 | AI33: =IFERROR(W33/W53-1,0) -> 0 | AJ33: =IFERROR(X33/X53-1,0) -> 0 | AK33: =IFERROR(Y33/Y53-1,0) -> -5.5511151e-16 | ... AM33: =IFERROR(AA33/AA53-1,0) -> 0
C34: S.14 Famílias | E34: S.13 Governo Geral | G34: S.12 Empresas finan- ceiras | I34: S.11 Empresas não- finan- ceiras | K34: Setor externo | R34: =R15 -> 15282 | S34: =S15 -> 0 | U34: =U15 -> 152610 | V34: 100913 | W34: -1455 | X34: =R34+S34+V34+W34 -> 114740 | Y34: =Z34-X34 -> 152610 | Z34: =SUM(R34:W34) -> 267350 | AA34: =Z34+AB34 -> 535541 | AB34: =SimulTRU!CK46 -> 268191 | AD34: =IFERROR(R34/R54-1,0) -> 0 | AE34: =IFERROR(S34/S54-1,0) -> 0 | AF34: =IFERROR(T34/T54-1,0) -> 0 | AG34: =IFERROR(U34/U54-1,0) -> -3.3306691e-16 | AH34: =IFERROR(V34/V54-1,0) -> 0 | AI34: =IFERROR(W34/W54-1,0) -> 0 | AJ34: =IFERROR(X34/X54-1,0) -> 0 | AK34: =IFERROR(Y34/Y54-1,0) -> -3.3306691e-16 | ... AM34: =IFERROR(AA34/AA54-1,0) -> 2.220446e-16
R35: =R16 -> 6943 | S35: =S16 -> 2165 | U35: =U16 -> 379659 | V35: 0 | W35: 0 | X35: =R35+S35+V35+W35 -> 9108 | Y35: =Z35-X35 -> 379659 | Z35: =SUM(R35:W35) -> 388767 | AA35: =Z35+AB35 -> 800076 | AB35: =SimulTRU!CK47 -> 411309 | AD35: =IFERROR(R35/R55-1,0) -> 0 | AE35: =IFERROR(S35/S55-1,0) -> 0 | AF35: =IFERROR(T35/T55-1,0) -> 0 | AG35: =IFERROR(U35/U55-1,0) -> -3.3306691e-16 | AH35: =IFERROR(V35/V55-1,0) -> 0 | AI35: =IFERROR(W35/W55-1,0) -> 0 | AJ35: =IFERROR(X35/X55-1,0) -> 0 | AK35: =IFERROR(Y35/Y55-1,0) -> -3.3306691e-16 | ... AM35: =IFERROR(AA35/AA55-1,0) -> 0
R36: =R17 -> 4688 | S36: =S17 -> 0 | U36: =U17 -> 643203 | V36: 0 | W36: 0 | X36: =R36+S36+V36+W36 -> 4688 | Y36: =Z36-X36 -> 643203 | Z36: =SUM(R36:W36) -> 647891 | AA36: =Z36+AB36 -> 793035 | AB36: =SimulTRU!CK48 -> 145144 | AD36: =IFERROR(R36/R56-1,0) -> 0 | AE36: =IFERROR(S36/S56-1,0) -> 0 | AF36: =IFERROR(T36/T56-1,0) -> 0 | AG36: =IFERROR(U36/U56-1,0) -> 2.220446e-16 | AH36: =IFERROR(V36/V56-1,0) -> 0 | AI36: =IFERROR(W36/W56-1,0) -> 0 | AJ36: =IFERROR(X36/X56-1,0) -> 0 | AK36: =IFERROR(Y36/Y56-1,0) -> 2.220446e-16 | ... AM36: =IFERROR(AA36/AA56-1,0) -> 0
R37: =R18 -> 76293 | S37: =S18 -> 54812 | U37: =U18 -> 915862 | V37: 46584 | W37: 0 | X37: =R37+S37+V37+W37 -> 177689 | Y37: =Z37-X37 -> 915862 | Z37: =SUM(R37:W37) -> 1093551 | AA37: =Z37+AB37 -> 2125358 | AB37: =SimulTRU!CK49 -> 1031807 | AD37: =IFERROR(R37/R57-1,0) -> 0 | AE37: =IFERROR(S37/S57-1,0) -> 0 | AF37: =IFERROR(T37/T57-1,0) -> 0 | AG37: =IFERROR(U37/U57-1,0) -> 0 | AH37: =IFERROR(V37/V57-1,0) -> 0 | AI37: =IFERROR(W37/W57-1,0) -> 0 | AJ37: =IFERROR(X37/X57-1,0) -> 0 | AK37: =IFERROR(Y37/Y57-1,0) -> 0 | ... AM37: =IFERROR(AA37/AA57-1,0) -> 0
C38: Entrada | D38: Saída | E38: Entrada | F38: Saída | G38: Entrada | H38: Saída | I38: Entrada | J38: Saída | K38: Entrada (Importações) | L38: Saída (Exportações) | N38: VA preço mercado | O38: VA preço básico | P38: Saldo Bal.Comercial e Serv | R38: =R19 -> 0 | S38: =S19 -> 1465281 | U38: =U19 -> 0 | V38: 0 | W38: 0 | X38: =R38+S38+V38+W38 -> 1465281 | Y38: =Z38-X38 -> 0 | Z38: =SUM(R38:W38) -> 1465281 | AA38: =Z38+AB38 -> 1465281 | AB38: =SimulTRU!CK50 -> 0 | AD38: =IFERROR(R38/R58-1,0) -> 0 | AE38: =IFERROR(S38/S58-1,0) -> 0 | AF38: =IFERROR(T38/T58-1,0) -> 0 | AG38: =IFERROR(U38/U58-1,0) -> 0 | AH38: =IFERROR(V38/V58-1,0) -> 0 | AI38: =IFERROR(W38/W58-1,0) -> 0 | AJ38: =IFERROR(X38/X58-1,0) -> 0 | AK38: =IFERROR(Y38/Y58-1,0) -> 0 | ... AM38: =IFERROR(AA38/AA58-1,0) -> 0
B39: Valor adicionado bruto/Produto interno bruto (1) | C39: =IFERROR(C7/C71-1,0) -> 0 | D39: =IFERROR(D7/D71-1,0) -> 0 | E39: =IFERROR(E7/E71-1,0) -> 0 | F39: =IFERROR(F7/F71-1,0) -> 0 | G39: =IFERROR(G7/G71-1,0) -> 0 | H39: =IFERROR(H7/H71-1,0) -> 0 | I39: =IFERROR(I7/I71-1,0) -> 0 | J39: =IFERROR(J7/J71-1,0) -> 0 | ... O39: =IFERROR(O7/O71-1,0) -> 0 | P39: =P7-P71 -> 0 | R39: =SUM(R27:R38) -> 1252049 | S39: =SUM(S27:S38) -> 1532204 | U39: =SUM(U27:U38) -> 4805004 | V39: =SUM(V27:V38) -> 1260227 | W39: =SUM(W27:W38) -> -33878 | X39: =SUM(X27:X38) -> 4010602 | Y39: =SUM(Y27:Y38) -> 4805004 | Z39: =SUM(Z27:Z38) -> 8815606 | AA39: =SUM(AA27:AA38) -> 15526868 | AD39: =IFERROR(R39/R59-1,0) -> 0 | AE39: =IFERROR(S39/S59-1,0) -> 0 | AF39: =IFERROR(T39/T59-1,0) -> 0 | AG39: =IFERROR(U39/U59-1,0) -> 0 | AH39: =IFERROR(V39/V59-1,0) -> 0 | AI39: =IFERROR(W39/W59-1,0) -> 0 | AJ39: =IFERROR(X39/X59-1,0) -> 0 | AK39: =IFERROR(Y39/Y59-1,0) -> 0 | ... AM39: =IFERROR(AA39/AA59-1,0) -> 2.220446e-16
A40: Tabela de Usos e Recursos - específico por setor - geração de renda | B40: Salários | C40: =IFERROR(C8/C72-1,0) -> 0 | D40: =IFERROR(D8/D72-1,0) -> 0 | E40: =IFERROR(E8/E72-1,0) -> 0 | F40: =IFERROR(F8/F72-1,0) -> 0 | G40: =IFERROR(G8/G72-1,0) -> 0 | H40: =IFERROR(H8/H72-1,0) -> 0 | I40: =IFERROR(I8/I72-1,0) -> 0 | J40: =IFERROR(J8/J72-1,0) -> 0 | ... L40: =IFERROR(L8/L72-1,0) -> 0 | M40: 2.910383e-11
B41: Contribuições sociais efetivas | C41: =IFERROR(C9/C73-1,0) -> 0 | D41: =IFERROR(D9/D73-1,0) -> 0 | E41: =IFERROR(E9/E73-1,0) -> 0 | F41: =IFERROR(F9/F73-1,0) -> 0 | G41: =IFERROR(G9/G73-1,0) -> 0 | H41: =IFERROR(H9/H73-1,0) -> 0 | I41: =IFERROR(I9/I73-1,0) -> 0 | J41: =IFERROR(J9/J73-1,0) -> 0 | ... L41: =IFERROR(L9/L73-1,0) -> 0 | M41: 1.4551915e-11
B42: Contribuições sociais inputadas | C42: =IFERROR(C10/C74-1,0) -> 0 | D42: =IFERROR(D10/D74-1,0) -> 0 | E42: =IFERROR(E10/E74-1,0) -> 0 | F42: =IFERROR(F10/F74-1,0) -> 0 | G42: =IFERROR(G10/G74-1,0) -> 0 | H42: =IFERROR(H10/H74-1,0) -> 0 | I42: =IFERROR(I10/I74-1,0) -> 0 | J42: =IFERROR(J10/J74-1,0) -> 0 | ... L42: =IFERROR(L10/L74-1,0) -> 0 | M42: 0 | R42: Expor- tação de bens e serviços (3) | S42: Consu- mo do governo | U42: Consu- mo das famílias | V42: Forma- ção bruta de capi- tal fixo | W42: Varia- ção de estoque | X42: Demanda autônoma | Y42: Demanda induzida | Z42: Demanda final | AA42: De- manda TOTAL
B43: Impostos, líquidos de subsídios, sobre produtos | C43: =IFERROR(C11/C75-1,0) -> 0 | D43: =IFERROR(D11/D75-1,0) -> 0 | E43: =IFERROR(E11/E75-1,0) -> 0 | F43: =IFERROR(F11/F75-1,0) -> 0 | G43: =IFERROR(G11/G75-1,0) -> 0 | H43: =IFERROR(H11/H75-1,0) -> 0 | I43: =IFERROR(I11/I75-1,0) -> 0 | J43: =IFERROR(J11/J75-1,0) -> 0 | ... L43: =IFERROR(L11/L75-1,0) -> 0 | M43: 1.4551915e-11
B44: Outros impostos, líquidos de subsídios, sobre a produção | C44: =IFERROR(C12/C76-1,0) -> 0 | D44: =IFERROR(D12/D76-1,0) -> 0 | E44: =IFERROR(E12/E76-1,0) -> 0 | F44: =IFERROR(F12/F76-1,0) -> 0 | G44: =IFERROR(G12/G76-1,0) -> 0 | H44: =IFERROR(H12/H76-1,0) -> 0 | I44: =IFERROR(I12/I76-1,0) -> 0 | J44: =IFERROR(J12/J76-1,0) -> 0 | ... L44: =IFERROR(L12/L76-1,0) -> 0 | M44: 1.8189894e-12
A45: Alocação primária do excedente | B45: Juros | C45: =IFERROR(C13/C77-1,0) -> 0 | D45: =IFERROR(D13/D77-1,0) -> 0 | E45: =IFERROR(E13/E77-1,0) -> 0 | F45: =IFERROR(F13/F77-1,0) -> 0 | G45: =IFERROR(G13/G77-1,0) -> 0 | H45: =IFERROR(H13/H77-1,0) -> 0 | I45: =IFERROR(I13/I77-1,0) -> 0 | J45: =IFERROR(J13/J77-1,0) -> 0 | ... L45: =IFERROR(L13/L77-1,0) -> 0 | M45: 0
B46: Rendas distribuídas das empresas | C46: =IFERROR(C14/C78-1,0) -> 0 | D46: =IFERROR(D14/D78-1,0) -> 0 | E46: =IFERROR(E14/E78-1,0) -> 0 | F46: =IFERROR(F14/F78-1,0) -> 0 | G46: =IFERROR(G14/G78-1,0) -> 0 | H46: =IFERROR(H14/H78-1,0) -> 0 | I46: =IFERROR(I14/I78-1,0) -> 0 | J46: =IFERROR(J14/J78-1,0) -> 0 | ... L46: =IFERROR(L14/L78-1,0) -> 0 | M46: 0
B47: Lucros reinvestidos de investimento estrangeiro direto | C47: =IFERROR(C15/C79-1,0) -> 0 | D47: =IFERROR(D15/D79-1,0) -> 0 | E47: =IFERROR(E15/E79-1,0) -> 0 | F47: =IFERROR(F15/F79-1,0) -> 0 | G47: =IFERROR(G15/G79-1,0) -> 0 | H47: =IFERROR(H15/H79-1,0) -> 0 | I47: =IFERROR(I15/I79-1,0) -> 0 | J47: =IFERROR(J15/J79-1,0) -> 0 | ... L47: =IFERROR(L15/L79-1,0) -> 0 | M47: 0 | R47: 241683 | S47: 230 | U47: 212694 | V47: 22310 | W47: -2694 | X47: 261529 | Y47: 212694 | Z47: 474223 | AA47: 938989
B48: Desembolsos por rendas de investimentos | C48: =IFERROR(C16/C80-1,0) -> 0 | D48: =IFERROR(D16/D80-1,0) -> 0 | E48: =IFERROR(E16/E80-1,0) -> 0 | F48: =IFERROR(F16/F80-1,0) -> 0 | G48: =IFERROR(G16/G80-1,0) -> 0 | H48: =IFERROR(H16/H80-1,0) -> 0 | I48: =IFERROR(I16/I80-1,0) -> 0 | J48: =IFERROR(J16/J80-1,0) -> 0 | ... L48: =IFERROR(L16/L80-1,0) -> 0 | M48: 0 | R48: 253114 | S48: 0 | U48: 0 | V48: 10455 | W48: -27501 | X48: 236068 | Y48: 0 | Z48: 236068 | AA48: 474641
B49: Renda de recursos naturais | C49: =IFERROR(C17/C81-1,0) -> 0 | D49: =IFERROR(D17/D81-1,0) -> 0 | E49: =IFERROR(E17/E81-1,0) -> 0 | F49: =IFERROR(F17/F81-1,0) -> 0 | G49: =IFERROR(G17/G81-1,0) -> 0 | H49: =IFERROR(H17/H81-1,0) -> 0 | I49: =IFERROR(I17/I81-1,0) -> 0 | J49: =IFERROR(J17/J81-1,0) -> 0 | ... L49: =IFERROR(L17/L81-1,0) -> 0 | M49: 0 | R49: 611468 | S49: 9716 | U49: 2148705 | V49: 523356 | W49: -2168 | X49: 1142372 | Y49: 2148705 | Z49: 3291077 | AA49: 6468662
A50: Alocação secundária | B50: Impostos correntes sobre a renda, patrimônio, // Contribuições sociais // Outras transferências | C50: =IFERROR(C18/C82-1,0) -> 0 | D50: =IFERROR(D18/D82-1,0) -> 0 | E50: =IFERROR(E18/E82-1,0) -> 0 | F50: =IFERROR(F18/F82-1,0) -> 0 | G50: =IFERROR(G18/G82-1,0) -> 0 | H50: =IFERROR(H18/H82-1,0) -> 0 | I50: =IFERROR(I18/I82-1,0) -> 0 | J50: =IFERROR(J18/J82-1,0) -> -1.110223e-16 | ... L50: =IFERROR(L18/L82-1,0) -> 0 | M50: 0 | R50: 2 | S50: 0 | U50: 186576 | V50: 0 | W50: -60 | X50: -58 | Y50: 186576 | Z50: 186518 | AA50: 532996
B51: Contribuições sociais | C51: =IFERROR(C19/C83-1,0) -> 0 | D51: =IFERROR(D19/D83-1,0) -> 0 | E51: =IFERROR(E19/E83-1,0) -> 0 | F51: =IFERROR(F19/F83-1,0) -> 0 | G51: =IFERROR(G19/G83-1,0) -> 0 | H51: =IFERROR(H19/H83-1,0) -> 0 | I51: =IFERROR(I19/I83-1,0) -> 0 | J51: =IFERROR(J19/J83-1,0) -> 0 | ... L51: =IFERROR(L19/L83-1,0) -> 0 | M51: 0 | R51: 3481 | S51: 0 | U51: 0 | V51: 556609 | W51: 0 | X51: 560090 | Y51: 0 | Z51: 560090 | AA51: 683264
B52: Benefícios de seguridade social em numerário // Seguro desemprego, bolsa família | C52: =IFERROR(C20/C84-1,0) -> 0 | D52: =IFERROR(D20/D84-1,0) -> 0 | E52: =IFERROR(E20/E84-1,0) -> 0 | F52: =IFERROR(F20/F84-1,0) -> 0 | G52: =IFERROR(G20/G84-1,0) -> 0 | H52: =IFERROR(H20/H84-1,0) -> 0 | I52: =IFERROR(I20/I84-1,0) -> 0 | J52: =IFERROR(J20/J84-1,0) -> 0 | ... L52: =IFERROR(L20/L84-1,0) -> 0 | M52: 0 | R52: 4676 | S52: 0 | U52: 55912 | V52: 0 | W52: 0 | X52: 4676 | Y52: 55912 | Z52: 60588 | AA52: 140737
B53: Outros benefícios de seguro social // Previdência | C53: =IFERROR(C21/C85-1,0) -> 0 | D53: =IFERROR(D21/D85-1,0) -> 0 | E53: =IFERROR(E21/E85-1,0) -> 0 | F53: =IFERROR(F21/F85-1,0) -> 0 | G53: =IFERROR(G21/G85-1,0) -> 0 | H53: =IFERROR(H21/H85-1,0) -> 0 | I53: =IFERROR(I21/I85-1,0) -> 0 | J53: =IFERROR(J21/J85-1,0) -> 0 | ... L53: =IFERROR(L21/L85-1,0) -> 0 | M53: 0 | R53: 34419 | S53: 0 | U53: 109783 | V53: 0 | W53: 0 | X53: 34419 | Y53: 109783 | Z53: 144202 | AA53: 568288
B54: Outras transferências correntes | C54: =IFERROR(C22/C86-1,0) -> 0 | D54: =IFERROR(D22/D86-1,0) -> 0 | E54: =IFERROR(E22/E86-1,0) -> 0 | F54: =IFERROR(F22/F86-1,0) -> 0 | G54: =IFERROR(G22/G86-1,0) -> 0 | H54: =IFERROR(H22/H86-1,0) -> 0 | I54: =IFERROR(I22/I86-1,0) -> 0 | J54: =IFERROR(J22/J86-1,0) -> 0 | ... L54: =IFERROR(L22/L86-1,0) -> 0 | M54: 0 | O54: Demanda final | R54: 15282 | S54: 0 | U54: 152610 | V54: 100913 | W54: -1455 | X54: 114740 | Y54: 152610 | Z54: 267350 | AA54: 535541
A55: Usos da renda | B55: Consumo final efetivo | C55: =IFERROR(C23/C87-1,0) -> 0 | D55: =IFERROR(D23/D87-1,0) -> 0 | E55: =IFERROR(E23/E87-1,0) -> 0 | F55: =IFERROR(F23/F87-1,0) -> 0 | G55: =IFERROR(G23/G87-1,0) -> 0 | H55: =IFERROR(H23/H87-1,0) -> 0 | I55: =IFERROR(I23/I87-1,0) -> 0 | J55: =IFERROR(J23/J87-1,0) -> 0 | ... M55: =IFERROR(M23/M87-1,0) -> 0 | O55: =IFERROR(O23/O87-1,0) -> 0 | R55: 6943 | S55: 2165 | U55: 379659 | V55: 0 | W55: 0 | X55: 9108 | Y55: 379659 | Z55: 388767 | AA55: 800076
B56: Ajustamento pela variação dos direitos de pensão | C56: =IFERROR(C24/C88-1,0) -> 0 | D56: =IFERROR(D24/D88-1,0) -> 0 | E56: =IFERROR(E24/E88-1,0) -> 0 | F56: =IFERROR(F24/F88-1,0) -> 0 | G56: =IFERROR(G24/G88-1,0) -> 0 | H56: =IFERROR(H24/H88-1,0) -> 0 | I56: =IFERROR(I24/I88-1,0) -> 0 | J56: =IFERROR(J24/J88-1,0) -> 0 | ... L56: =IFERROR(L24/L88-1,0) -> 0 | M56: 0 | R56: 4688 | S56: 0 | U56: 643203 | V56: 0 | W56: 0 | X56: 4688 | Y56: 643203 | Z56: 647891 | AA56: 793035
B57: Formação bruta de capital fixo | C57: =IFERROR(C25/C89-1,0) -> 0 | D57: =IFERROR(D25/D89-1,0) -> 0 | E57: =IFERROR(E25/E89-1,0) -> 0 | F57: =IFERROR(F25/F89-1,0) -> 0 | G57: =IFERROR(G25/G89-1,0) -> 0 | H57: =IFERROR(H25/H89-1,0) -> 0 | I57: =IFERROR(I25/I89-1,0) -> 0 | J57: =IFERROR(J25/J89-1,0) -> 0 | ... M57: =IFERROR(M25/M89-1,0) -> 0 | R57: 76293 | S57: 54812 | U57: 915862 | V57: 46584 | W57: 0 | X57: 177689 | Y57: 915862 | Z57: 1093551 | AA57: 2125358
B58: Variação de estoques | C58: =IFERROR(C26/C90-1,0) -> 0 | D58: =IFERROR(D26/D90-1,0) -> 0 | E58: =IFERROR(E26/E90-1,0) -> 0 | F58: =IFERROR(F26/F90-1,0) -> 0 | G58: =IFERROR(G26/G90-1,0) -> 0 | H58: =IFERROR(H26/H90-1,0) -> 0 | I58: =IFERROR(I26/I90-1,0) -> 0 | J58: =IFERROR(J26/J90-1,0) -> 0 | ... M58: =IFERROR(M26/M90-1,0) -> 0 | R58: 0 | S58: 1465281 | U58: 0 | V58: 0 | W58: 0 | X58: 1465281 | Y58: 0 | Z58: 1465281 | AA58: 1465281
B59: Aquisições líquidas de cessões de ativos não-produzidos | C59: =IFERROR(C27/C91-1,0) -> 0 | D59: =IFERROR(D27/D91-1,0) -> 0 | E59: =IFERROR(E27/E91-1,0) -> 0 | F59: =IFERROR(F27/F91-1,0) -> 0 | G59: =IFERROR(G27/G91-1,0) -> 0 | H59: =IFERROR(H27/H91-1,0) -> 0 | I59: =IFERROR(I27/I91-1,0) -> 0 | J59: =IFERROR(J27/J91-1,0) -> 0 | ... L59: =IFERROR(L27/L91-1,0) -> 0 | M59: 0 | R59: 1252049 | S59: 1532204 | U59: 4805004 | V59: 1260227 | W59: -33878 | X59: 4010602 | Y59: 4805004 | Z59: 8815606 | AA59: 15526868
B60: Capacidade (+) / Necessidade(-) líquida de financiamento | C60: =C28/C29-1 -> 0 | E60: =E28/E29-1 -> 0 | G60: =G28/G29-1 -> 0 | I60: =I28/I29-1 -> 0 | K60: =K28/K29-1 -> 0 | M60: 0
B61: Check | C61: 562272 | E61: -918009 | G61: 149429 | I61: 125770 | K61: 80538 | M61: 0
D63: 0 | F63: 0 | H63: 0 | J63: 0 | L63: 0
C66: S.14 Famílias | E66: S.13 Governo Geral | G66: S.12 Empresas finan- ceiras | I66: S.11 Empresas não- finan- ceiras | K66: Setor externo
S68: S
C70: Entrada | D70: Saída | E70: Entrada | F70: Saída | G70: Entrada | H70: Saída | I70: Entrada | J70: Saída | K70: Entrada (Importações) | L70: Saída (Exportações) | N70: VA preço mercado | O70: VA preço básico | P70: Saldo Bal.Comercial e Serv
B71: Valor adicionado bruto/Produto interno bruto (1) | C71: 0 | D71: 0 | E71: 0 | F71: 0 | G71: 454550 | H71: 0 | I71: 7155047 | J71: 0 | K71: 1206009 | L71: 1252049 | M71: 7563557 | N71: 7609597 | O71: 6662425 | P71: =(L71-K71)/N71 -> 0.0060502547
A72: Tabela de Usos e Recursos - específico por setor - geração de renda | B72: Salários | C72: 2531961 | D72: 0 | E72: 0 | F72: 0 | G72: 0 | H72: 140274 | I72: 0 | J72: 2391687 | K72: 0 | L72: 0 | M72: 2.910383e-11
B73: Contribuições sociais efetivas | C73: 562617 | D73: 0 | E73: 0 | F73: 0 | G73: 0 | H73: 41011 | I73: 0 | J73: 521606 | K73: 0 | L73: 0 | M73: 1.4551915e-11
B74: Contribuições sociais inputadas | C74: 0 | D74: 0 | E74: 0 | F74: 0 | G74: 0 | H74: 0 | I74: 0 | J74: 0 | K74: 0 | L74: 0 | M74: 0
B75: Impostos, líquidos de subsídios, sobre produtos | C75: 0 | D75: 0 | E75: 1014660 | F75: 0 | G75: 0 | H75: 67488 | I75: 0 | J75: 947172 | K75: 0 | L75: 0 | M75: 1.4551915e-11
B76: Outros impostos, líquidos de subsídios, sobre a produção | C76: 0 | D76: 0 | E76: 86391 | F76: 0 | G76: 0 | H76: 9262 | I76: 0 | J76: 77129 | K76: 0 | L76: 0 | M76: 1.8189894e-12
A77: Alocação primária do excedente | B77: Juros | C77: 249546 | D77: 205143 | E77: 191053 | F77: 446981 | G77: 1235025 | H77: 1060460 | I77: 246213 | J77: 282899 | K77: 106219 | L77: 32573 | M77: 0
B78: Rendas distribuídas das empresas | C78: 1888670 | D78: 0 | E78: 0 | F78: 0 | G78: 0 | H78: 153250 | I78: 0 | J78: 1821126 | K78: 85706 | L78: 0 | M78: 0
B79: Lucros reinvestidos de investimento estrangeiro direto | C79: 0 | D79: 0 | E79: 0 | F79: 0 | G79: 0 | H79: 0 | I79: 0 | J79: 0 | K79: 0 | L79: 0 | M79: 0
B80: Desembolsos por rendas de investimentos | C80: 0 | D80: 0 | E80: 0 | F80: 0 | G80: 0 | H80: 0 | I80: 0 | J80: 0 | K80: 0 | L80: 0 | M80: 0
B81: Renda de recursos naturais | C81: 0 | D81: 0 | E81: 0 | F81: 0 | G81: 0 | H81: 0 | I81: 0 | J81: 0 | K81: 0 | L81: 0 | M81: 0
A82: Alocação secundária | B82: Impostos correntes sobre a renda, patrimônio, // Contribuições sociais // Outras transferências | C82: 0 | D82: 362776 | E82: 917257 | F82: 0 | G82: 0 | H82: 42715 | I82: 0 | J82: 511766 | K82: 0 | L82: 0 | M82: 0
B83: Contribuições sociais | C83: 0 | D83: 895266 | E83: 800730 | F83: 0 | G83: 94536 | H83: 0 | I83: 0 | J83: 0 | K83: 0 | L83: 0 | M83: 0
B84: Benefícios de seguridade social em numerário // Seguro desemprego, bolsa família | C84: 1254637 | D84: 0 | E84: 0 | F84: 1254637 | G84: 0 | H84: 0 | I84: 0 | J84: 0 | K84: 0 | L84: 0 | M84: 0
B85: Outros benefícios de seguro social // Previdência | C85: 717798 | D85: 0 | E85: 0 | F85: 624646 | G85: 0 | H85: 93152 | I85: 0 | J85: 0 | K85: 0 | L85: 0 | M85: 0
B86: Outras transferências correntes | C86: 35242 | D86: 0 | E86: 70054 | F86: 0 | G86: 0 | H86: 13352 | I86: 0 | J86: 59170 | K86: 0 | L86: 32774 | M86: 0 | O86: Demanda final
A87: Usos da renda | B87: Consumo final efetivo | C87: 0 | D87: 4805004 | E87: 0 | F87: 1532204 | G87: 0 | H87: 0 | I87: 0 | J87: 0 | K87: 0 | L87: 0 | M87: -6337208 | O87: 8815606
B88: Ajustamento pela variação dos direitos de pensão | C88: 0 | D88: 0 | E88: 0 | F88: 0 | G88: 0 | H88: 0 | I88: 0 | J88: 0 | K88: 0 | L88: 0 | M88: 0
B89: Formação bruta de capital fixo | C89: 0 | D89: 410010 | E89: 0 | F89: 139686 | G89: 0 | H89: 13718 | I89: 0 | J89: 696813 | K89: 0 | L89: 0 | M89: -1260227
B90: Variação de estoques | C90: 0 | D90: 0 | E90: 0 | F90: 0 | G90: 0 | H90: 0 | I90: 0 | J90: -33878 | K90: 0 | L90: 0 | M90: 33878
B91: Aquisições líquidas de cessões de ativos não-produzidos | C91: 0 | D91: 0 | E91: 0 | F91: 0 | G91: 0 | H91: 0 | I91: 0 | J91: 0 | K91: 0 | L91: 0 | M91: 0
B92: Capacidade (+) / Necessidade(-) líquida de financiamento | C92: 562272 | E92: -918009 | G92: 149429 | I92: 125770 | K92: 80538 | M92: 0
B93: Check | C93: 562272 | E93: -918009 | G93: 149429 | I93: 125770 | K93: 80538 | M93: 0
D95: 0 | F95: 0 | H95: 0 | J95: 0 | L95: 0

Sheet SimulCEI2
R1: Consumo resolvido supondo uma proporão da renda. Preciso resolver por método iterativo, até que Demanda total 1 = Demanda total 2. Célula laranja precisa ser 0! Aplicar solver sobre o valor do consumo inicial
C2: S.14 Famílias | E2: S.13 Governo Geral | G2: S.12 Empresas finan- ceiras | I2: S.11 Empresas não- finan- ceiras | K2: Setor externo | AC2: =(AA20-AA39)^2*1000 -> 3.469447e-15
P3: Saldo Governo | R3: Expor- tação de bens e serviços (3) | S3: Consu- mo do governo | T3: Consu- mo das ISFLSF | U3: Consu- mo das famílias INICIAL | V3: Forma- ção bruta de capi- tal fixo | W3: Varia- ção de estoque | X3: Demanda autônoma | Y3: Demanda induzida | Z3: Demanda final | AA3: Demanda TOTAL 1 | AD3: Expor- tação de bens e serviços (3) | AE3: Consu- mo do governo | AF3: Consu- mo das ISFLSF | AG3: Consu- mo das famílias | AH3: Forma- ção bruta de capi- tal fixo | AI3: Varia- ção de estoque | AJ3: Demanda autônoma | AK3: Demanda induzida | AL3: Demanda final | AM3: De- manda TOTAL
P4: =E28/N7 -> -0.12063832
AB5: Consumo intermediário
C6: Entrada | D6: Saída | E6: Entrada | F6: Saída | G6: Entrada | H6: Saída | I6: Entrada | J6: Saída | K6: Entrada (Importações) | L6: Saída (Exportações) | N6: VA preço mercado | O6: VA preço básico | P6: Saldo Bal.Comercial e Serv
B7: Valor adicionado bruto/Produto interno bruto (1) | C7: =CEIResumida!D80 -> 0 | D7: =CEIResumida!E80 -> 0 | E7: =CEIResumida!F80 -> 0 | F7: =CEIResumida!G80 -> 0 | G7: =SimulTRU2!S54 -> 454550 | H7: =CEIResumida!I80 -> 0 | I7: =SimulTRU2!X54-SimulTRU2!S54 -> 7155047 | J7: =CEIResumida!K80 -> 0 | K7: =SimulTRU2!Y24 -> 1206009 | L7: =R20 -> 1252049 | M7: =G7+I7+K7-L7 -> 7563557 | N7: =G7+I7 -> 7609597 | O7: =N7-J11 -> 6662425 | P7: =(L7-K7)/N7 -> 0.0060502547
A8: Tabela de Usos e Recursos - específico por setor - geração de renda | B8: Salários | C8: =SimulTRU2!W56 -> 2531961 | D8: =CEIResumida!E81 -> 0 | E8: =CEIResumida!F81 -> 0 | F8: =CEIResumida!G81 -> 0 | G8: =CEIResumida!H81 -> 0 | H8: =SimulTRU2!S56 -> 140274 | I8: =CEIResumida!J81 -> 0 | J8: =SimulTRU2!W56-SimulTRU2!S56 -> 2391687 | K8: =CEIResumida!L81 -> 0 | L8: =CEIResumida!M81 -> 0 | M8: =C8+E8+G8+I8+K8-L8-J8-H8-F8-D8 -> -8.7311491e-11 | R8: 241683 | S8: 230 | U8: =$U$20*ParâmeetrosTRU!AB39 -> 212694 | V8: 22310 | W8: -2694 | X8: =R8+S8+V8+W8 -> 261529 | Y8: =U8 -> 212694 | Z8: =X8+Y8 -> 474223 | AA8: =SimulTRU2!CH39 -> 938989 | AB8: =SimulTRU2!CK39 -> 464766 | AD8: =IFERROR(R8/R47-1,0) -> 0 | AE8: =IFERROR(S8/S47-1,0) -> 0 | AF8: =IFERROR(T8/T47-1,0) -> 0 | AG8: =IFERROR(U8/U47-1,0) -> 4.4408921e-16 | AH8: =IFERROR(V8/V47-1,0) -> 0 | AI8: =IFERROR(W8/W47-1,0) -> 0 | AJ8: =IFERROR(X8/X47-1,0) -> 0 | AK8: =IFERROR(Y8/Y47-1,0) -> 6.6613381e-16 | ... AM8: =IFERROR(AA8/AA47-1,0) -> 2.220446e-16
B9: Contribuições sociais efetivas | C9: =SimulTRU2!W57 -> 562617 | D9: =CEIResumida!E82 -> 0 | E9: =CEIResumida!F82 -> 0 | F9: =CEIResumida!G82 -> 0 | G9: =CEIResumida!H82 -> 0 | H9: =SimulTRU2!S57 -> 41011 | I9: =CEIResumida!J82 -> 0 | J9: =SimulTRU2!W57-SimulTRU2!S57 -> 521606 | K9: =CEIResumida!L82 -> 0 | L9: =CEIResumida!M82 -> 0 | M9: =C9+E9+G9+I9+K9-L9-J9-H9-F9-D9 -> -2.910383e-11 | R9: =253114 -> 253114 | S9: 0 | U9: =$U$20*ParâmeetrosTRU!AB40 -> 0 | V9: 10455 | W9: -27501 | X9: =R9+S9+V9+W9 -> 236068 | Y9: =U9 -> 0 | Z9: =X9+Y9 -> 236068 | AA9: =SimulTRU2!CH40 -> 474641 | AB9: =SimulTRU2!CK40 -> 238573 | AD9: =IFERROR(R9/R48-1,0) -> 0 | AE9: =IFERROR(S9/S48-1,0) -> 0 | AF9: =IFERROR(T9/T48-1,0) -> 0 | AG9: =IFERROR(U9/U48-1,0) -> 0 | AH9: =IFERROR(V9/V48-1,0) -> 0 | AI9: =IFERROR(W9/W48-1,0) -> 0 | AJ9: =IFERROR(X9/X48-1,0) -> 0 | AK9: =IFERROR(Y9/Y48-1,0) -> 0 | ... AM9: =IFERROR(AA9/AA48-1,0) -> 2.220446e-16
B10: Contribuições sociais inputadas | C10: =CEIResumida!D83 -> 0 | D10: =CEIResumida!E83 -> 0 | E10: =CEIResumida!F83 -> 0 | F10: =CEIResumida!G83 -> 0 | G10: =CEIResumida!H83 -> 0 | H10: =CEIResumida!I83 -> 0 | I10: =CEIResumida!J83 -> 0 | J10: =CEIResumida!K83 -> 0 | ... L10: =CEIResumida!M83 -> 0 | M10: =C10+E10+G10+I10+K10-L10-J10-H10-F10-D10 -> 0 | R10: =611468*1 -> 611468 | S10: 9716 | U10: =$U$20*ParâmeetrosTRU!AB41 -> 2148705 | V10: 523356 | W10: -2168 | X10: =R10+S10+V10+W10 -> 1142372 | Y10: =U10 -> 2148705 | Z10: =X10+Y10 -> 3291077 | AA10: =SimulTRU2!CH41 -> 6468662 | AB10: =SimulTRU2!CK41 -> 3177585 | AD10: =IFERROR(R10/R49-1,0) -> 0 | AE10: =IFERROR(S10/S49-1,0) -> 0 | AF10: =IFERROR(T10/T49-1,0) -> 0 | AG10: =IFERROR(U10/U49-1,0) -> 6.6613381e-16 | AH10: =IFERROR(V10/V49-1,0) -> 0 | AI10: =IFERROR(W10/W49-1,0) -> 0 | AJ10: =IFERROR(X10/X49-1,0) -> 0 | AK10: =IFERROR(Y10/Y49-1,0) -> 6.6613381e-16 | ... AM10: =IFERROR(AA10/AA49-1,0) -> 6.6613381e-16
B11: Impostos, líquidos de subsídios, sobre produtos | C11: =CEIResumida!D84 -> 0 | D11: =CEIResumida!E84 -> 0 | E11: =CEIResumida!F84 -> 1014660 | F11: =CEIResumida!G84 -> 0 | G11: =CEIResumida!H84 -> 0 | H11: =SimulTRU2!I19 -> 67488 | I11: =CEIResumida!J84 -> 0 | J11: =SimulTRU2!I24-SimulTRU2!I19 -> 947172 | K11: =CEIResumida!L84 -> 0 | L11: =CEIResumida!M84 -> 0 | M11: =C11+E11+G11+I11+K11-L11-J11-H11-F11-D11 -> -3.9290171e-10 | R11: 2 | S11: 0 | U11: =$U$20*ParâmeetrosTRU!AB42 -> 186576 | V11: 0 | W11: -60 | X11: =R11+S11+V11+W11 -> -58 | Y11: =U11 -> 186576 | Z11: =X11+Y11 -> 186518 | AA11: =SimulTRU2!CH42 -> 532996 | AB11: =SimulTRU2!CK42 -> 346478 | AD11: =IFERROR(R11/R50-1,0) -> 0 | AE11: =IFERROR(S11/S50-1,0) -> 0 | AF11: =IFERROR(T11/T50-1,0) -> 0 | AG11: =IFERROR(U11/U50-1,0) -> 6.6613381e-16 | AH11: =IFERROR(V11/V50-1,0) -> 0 | AI11: =IFERROR(W11/W50-1,0) -> 0 | AJ11: =IFERROR(X11/X50-1,0) -> 0 | AK11: =IFERROR(Y11/Y50-1,0) -> 6.6613381e-16 | ... AM11: =IFERROR(AA11/AA50-1,0) -> 6.6613381e-16
B12: Outros impostos, líquidos de subsídios, sobre a produção | C12: =CEIResumida!D85 -> 0 | D12: =CEIResumida!E85 -> 0 | E12: =CEIResumida!F85 -> 86391 | F12: =CEIResumida!G85 -> 0 | G12: =CEIResumida!H85 -> 0 | H12: =SimulTRU2!S64 -> 9262 | I12: =CEIResumida!J85 -> 0 | J12: =SimulTRU2!W64-SimulTRU2!S64 -> 77129 | K12: =CEIResumida!L85 -> 0 | L12: =CEIResumida!M85 -> 0 | M12: =C12+E12+G12+I12+K12-L12-J12-H12-F12-D12 -> -6.5483619e-11 | R12: 3481 | S12: 0 | U12: =$U$20*ParâmeetrosTRU!AB43 -> 0 | V12: 556609 | W12: 0 | X12: =R12+S12+V12+W12 -> 560090 | Y12: =U12 -> 0 | Z12: =X12+Y12 -> 560090 | AA12: =SimulTRU2!CH43 -> 683264 | AB12: =SimulTRU2!CK43 -> 123174 | AD12: =IFERROR(R12/R51-1,0) -> 0 | AE12: =IFERROR(S12/S51-1,0) -> 0 | AF12: =IFERROR(T12/T51-1,0) -> 0 | AG12: =IFERROR(U12/U51-1,0) -> 0 | AH12: =IFERROR(V12/V51-1,0) -> 0 | AI12: =IFERROR(W12/W51-1,0) -> 0 | AJ12: =IFERROR(X12/X51-1,0) -> 0 | AK12: =IFERROR(Y12/Y51-1,0) -> 0 | ... AM12: =IFERROR(AA12/AA51-1,0) -> -6.6613381e-16
A13: Alocação primária do excedente | B13: Juros | C13: =CEIResumida!D86 -> 249546 | D13: =CEIResumida!E86 -> 205143 | E13: =CEIResumida!F86 -> 191053 | F13: =CEIResumida!G86 -> 446981 | G13: =CEIResumida!H86 -> 1235025 | H13: =CEIResumida!I86 -> 1060460 | I13: =CEIResumida!J86 -> 246213 | J13: =CEIResumida!K86 -> 282899 | ... L13: =CEIResumida!M86 -> 32573 | M13: =C13+E13+G13+I13+K13-L13-J13-H13-F13-D13 -> 0 | R13: 4676 | S13: 0 | U13: =$U$20*ParâmeetrosTRU!AB44 -> 55912 | V13: 0 | W13: 0 | X13: =R13+S13+V13+W13 -> 4676 | Y13: =U13 -> 55912 | Z13: =X13+Y13 -> 60588 | AA13: =SimulTRU2!CH44 -> 140737 | AB13: =SimulTRU2!CK44 -> 80149 | AD13: =IFERROR(R13/R52-1,0) -> 0 | AE13: =IFERROR(S13/S52-1,0) -> 0 | AF13: =IFERROR(T13/T52-1,0) -> 0 | AG13: =IFERROR(U13/U52-1,0) -> 6.6613381e-16 | AH13: =IFERROR(V13/V52-1,0) -> 0 | AI13: =IFERROR(W13/W52-1,0) -> 0 | AJ13: =IFERROR(X13/X52-1,0) -> 0 | AK13: =IFERROR(Y13/Y52-1,0) -> 6.6613381e-16 | ... AM13: =IFERROR(AA13/AA52-1,0) -> 1.9984014e-15
B14: Rendas distribuídas das empresas | C14: =CEIResumida!D87 -> 1888670 | D14: =CEIResumida!E87 -> 0 | E14: =CEIResumida!F87 -> 0 | F14: =CEIResumida!G87 -> 0 | G14: =CEIResumida!H87 -> 0 | H14: =CEIResumida!I87 -> 153250 | I14: =CEIResumida!J87 -> 0 | J14: =CEIResumida!K87 -> 1821126 | ... L14: =CEIResumida!M87 -> 0 | M14: =C14+E14+G14+I14+K14-L14-J14-H14-F14-D14 -> 0 | R14: 34419 | S14: 0 | U14: =$U$20*ParâmeetrosTRU!AB45 -> 109783 | V14: 0 | W14: 0 | X14: =R14+S14+V14+W14 -> 34419 | Y14: =U14 -> 109783 | Z14: =X14+Y14 -> 144202 | AA14: =SimulTRU2!CH45 -> 568288 | AB14: =SimulTRU2!CK45 -> 424086 | AD14: =IFERROR(R14/R53-1,0) -> 0 | AE14: =IFERROR(S14/S53-1,0) -> 0 | AF14: =IFERROR(T14/T53-1,0) -> 0 | AG14: =IFERROR(U14/U53-1,0) -> 6.6613381e-16 | AH14: =IFERROR(V14/V53-1,0) -> 0 | AI14: =IFERROR(W14/W53-1,0) -> 0 | AJ14: =IFERROR(X14/X53-1,0) -> 0 | AK14: =IFERROR(Y14/Y53-1,0) -> 6.6613381e-16 | ... AM14: =IFERROR(AA14/AA53-1,0) -> 1.110223e-15
B15: Lucros reinvestidos de investimento estrangeiro direto | C15: =CEIResumida!D88 -> 0 | D15: =CEIResumida!E88 -> 0 | E15: =CEIResumida!F88 -> 0 | F15: =CEIResumida!G88 -> 0 | G15: =CEIResumida!H88 -> 0 | H15: =CEIResumida!I88 -> 0 | I15: =CEIResumida!J88 -> 0 | J15: =CEIResumida!K88 -> 0 | ... L15: =CEIResumida!M88 -> 0 | M15: =C15+E15+G15+I15+K15-L15-J15-H15-F15-D15 -> 0 | R15: 15282 | S15: 0 | U15: =$U$20*ParâmeetrosTRU!AB46 -> 152610 | V15: 100913 | W15: -1455 | X15: =R15+S15+V15+W15 -> 114740 | Y15: =U15 -> 152610 | Z15: =X15+Y15 -> 267350 | AA15: =SimulTRU2!CH46 -> 535541 | AB15: =SimulTRU2!CK46 -> 268191 | AD15: =IFERROR(R15/R54-1,0) -> 0 | AE15: =IFERROR(S15/S54-1,0) -> 0 | AF15: =IFERROR(T15/T54-1,0) -> 0 | AG15: =IFERROR(U15/U54-1,0) -> 6.6613381e-16 | AH15: =IFERROR(V15/V54-1,0) -> 0 | AI15: =IFERROR(W15/W54-1,0) -> 0 | AJ15: =IFERROR(X15/X54-1,0) -> 0 | AK15: =IFERROR(Y15/Y54-1,0) -> 6.6613381e-16 | ... AM15: =IFERROR(AA15/AA54-1,0) -> 8.8817842e-16
B16: Desembolsos por rendas de investimentos | C16: =CEIResumida!D89 -> 0 | D16: =CEIResumida!E89 -> 0 | E16: =CEIResumida!F89 -> 0 | F16: =CEIResumida!G89 -> 0 | G16: =CEIResumida!H89 -> 0 | H16: =CEIResumida!I89 -> 0 | I16: =CEIResumida!J89 -> 0 | J16: =CEIResumida!K89 -> 0 | ... L16: =CEIResumida!M89 -> 0 | M16: =C16+E16+G16+I16+K16-L16-J16-H16-F16-D16 -> 0 | R16: 6943 | S16: 2165 | U16: =$U$20*ParâmeetrosTRU!AB47 -> 379659 | V16: 0 | W16: 0 | X16: =R16+S16+V16+W16 -> 9108 | Y16: =U16 -> 379659 | Z16: =X16+Y16 -> 388767 | AA16: =SimulTRU2!CH47 -> 800076 | AB16: =SimulTRU2!CK47 -> 411309 | AD16: =IFERROR(R16/R55-1,0) -> 0 | AE16: =IFERROR(S16/S55-1,0) -> 0 | AF16: =IFERROR(T16/T55-1,0) -> 0 | AG16: =IFERROR(U16/U55-1,0) -> 6.6613381e-16 | AH16: =IFERROR(V16/V55-1,0) -> 0 | AI16: =IFERROR(W16/W55-1,0) -> 0 | AJ16: =IFERROR(X16/X55-1,0) -> 0 | AK16: =IFERROR(Y16/Y55-1,0) -> 6.6613381e-16 | ... AM16: =IFERROR(AA16/AA55-1,0) -> 8.8817842e-16
B17: Renda de recursos naturais | C17: =CEIResumida!D90 -> 0 | D17: =CEIResumida!E90 -> 0 | E17: =CEIResumida!F90 -> 0 | F17: =CEIResumida!G90 -> 0 | G17: =CEIResumida!H90 -> 0 | H17: =CEIResumida!I90 -> 0 | I17: =CEIResumida!J90 -> 0 | J17: =CEIResumida!K90 -> 0 | ... L17: =CEIResumida!M90 -> 0 | M17: =C17+E17+G17+I17+K17-L17-J17-H17-F17-D17 -> 0 | R17: 4688 | S17: 0 | U17: =$U$20*ParâmeetrosTRU!AB48 -> 643203 | V17: 0 | W17: 0 | X17: =R17+S17+V17+W17 -> 4688 | Y17: =U17 -> 643203 | Z17: =X17+Y17 -> 647891 | AA17: =SimulTRU2!CH48 -> 793035 | AB17: =SimulTRU2!CK48 -> 145144 | AD17: =IFERROR(R17/R56-1,0) -> 0 | AE17: =IFERROR(S17/S56-1,0) -> 0 | AF17: =IFERROR(T17/T56-1,0) -> 0 | AG17: =IFERROR(U17/U56-1,0) -> 4.4408921e-16 | AH17: =IFERROR(V17/V56-1,0) -> 0 | AI17: =IFERROR(W17/W56-1,0) -> 0 | AJ17: =IFERROR(X17/X56-1,0) -> 0 | AK17: =IFERROR(Y17/Y56-1,0) -> 4.4408921e-16 | ... AM17: =IFERROR(AA17/AA56-1,0) -> 4.4408921e-16
A18: Alocação secundária | B18: Impostos correntes sobre a renda, patrimônio, // Contribuições sociais // Outras transferências | C18: =CEIResumida!D91 -> 0 | D18: =CEIResumida!E91 -> 362776 | E18: =CEIResumida!F91 -> 917257 | F18: =CEIResumida!G91 -> 0 | G18: =CEIResumida!H91 -> 0 | H18: =CEIResumida!I91 -> 42715 | I18: =CEIResumida!J91 -> 0 | J18: =CEIResumida!K91 -> 511766 | ... L18: =CEIResumida!M91 -> 0 | M18: =C18+E18+G18+I18+K18-L18-J18-H18-F18-D18 -> 0 | R18: 76293 | S18: =54812*1 -> 54812 | U18: =$U$20*ParâmeetrosTRU!AB49 -> 915862 | V18: 46584 | W18: 0 | X18: =R18+S18+V18+W18 -> 177689 | Y18: =U18 -> 915862 | Z18: =X18+Y18 -> 1093551 | AA18: =SimulTRU2!CH49 -> 2125358 | AB18: =SimulTRU2!CK49 -> 1031807 | AD18: =IFERROR(R18/R57-1,0) -> 0 | AE18: =IFERROR(S18/S57-1,0) -> 0 | AF18: =IFERROR(T18/T57-1,0) -> 0 | AG18: =IFERROR(U18/U57-1,0) -> 6.6613381e-16 | AH18: =IFERROR(V18/V57-1,0) -> 0 | AI18: =IFERROR(W18/W57-1,0) -> 0 | AJ18: =IFERROR(X18/X57-1,0) -> 0 | AK18: =IFERROR(Y18/Y57-1,0) -> 6.6613381e-16 | ... AM18: =IFERROR(AA18/AA57-1,0) -> 6.6613381e-16
B19: Contribuições sociais | C19: =CEIResumida!D92 -> 0 | D19: =CEIResumida!E92 -> 895266 | E19: =CEIResumida!F92 -> 800730 | F19: =CEIResumida!G92 -> 0 | G19: =CEIResumida!H92 -> 94536 | H19: =CEIResumida!I92 -> 0 | I19: =CEIResumida!J92 -> 0 | J19: =CEIResumida!K92 -> 0 | ... L19: =CEIResumida!M92 -> 0 | M19: =C19+E19+G19+I19+K19-L19-J19-H19-F19-D19 -> 0 | R19: 0 | S19: =1465281*1 -> 1465281 | U19: =$U$20*ParâmeetrosTRU!AB50 -> 0 | V19: 0 | W19: 0 | X19: =R19+S19+V19+W19 -> 1465281 | Y19: =U19 -> 0 | Z19: =X19+Y19 -> 1465281 | AA19: =SimulTRU2!CH50 -> 1465281 | AB19: =SimulTRU2!CK50 -> 0 | AD19: =IFERROR(R19/R58-1,0) -> 0 | AE19: =IFERROR(S19/S58-1,0) -> 0 | AF19: =IFERROR(T19/T58-1,0) -> 0 | AG19: =IFERROR(U19/U58-1,0) -> 0 | AH19: =IFERROR(V19/V58-1,0) -> 0 | AI19: =IFERROR(W19/W58-1,0) -> 0 | AJ19: =IFERROR(X19/X58-1,0) -> 0 | AK19: =IFERROR(Y19/Y58-1,0) -> 0 | ... AM19: =IFERROR(AA19/AA58-1,0) -> 0
B20: Benefícios de seguridade social em numerário // Seguro desemprego, bolsa família | C20: =CEIResumida!D93 -> 1254637 | D20: =CEIResumida!E93 -> 0 | E20: =CEIResumida!F93 -> 0 | F20: =CEIResumida!G93 -> 1254637 | G20: =CEIResumida!H93 -> 0 | H20: =CEIResumida!I93 -> 0 | I20: =CEIResumida!J93 -> 0 | J20: =CEIResumida!K93 -> 0 | ... L20: =CEIResumida!M93 -> 0 | M20: =C20+E20+G20+I20+K20-L20-J20-H20-F20-D20 -> 0 | R20: =SUM(R8:R19) -> 1252049 | S20: =SUM(S8:S19) -> 1532204 | T20: =SUM(T8:T19) -> 0 | U20: 4805004 | V20: =SUM(V8:V19) -> 1260227 | W20: =SUM(W8:W19) -> -33878 | X20: =SUM(X8:X19) -> 4010602 | Y20: =SUM(Y8:Y19) -> 4805004 | Z20: =SUM(Z8:Z19) -> 8815606 | AA20: =SUM(AA8:AA19) -> 15526868 | AD20: =IFERROR(R20/R59-1,0) -> 0 | AE20: =IFERROR(S20/S59-1,0) -> 0 | AF20: =IFERROR(T20/T59-1,0) -> 0 | AG20: =IFERROR(U20/U59-1,0) -> 6.6613381e-16 | AH20: =IFERROR(V20/V59-1,0) -> 0 | AI20: =IFERROR(W20/W59-1,0) -> 0 | AJ20: =IFERROR(X20/X59-1,0) -> 0 | AK20: =IFERROR(Y20/Y59-1,0) -> 6.6613381e-16 | ... AM20: =IFERROR(AA20/AA59-1,0) -> 4.4408921e-16
B21: Outros benefícios de seguro social // Previdência | C21: =CEIResumida!D94 -> 717798 | D21: =CEIResumida!E94 -> 0 | E21: =CEIResumida!F94 -> 0 | F21: =CEIResumida!G94 -> 624646 | G21: =CEIResumida!H94 -> 0 | H21: =CEIResumida!I94 -> 93152 | I21: =CEIResumida!J94 -> 0 | J21: =CEIResumida!K94 -> 0 | ... L21: =CEIResumida!M94 -> 0 | M21: =C21+E21+G21+I21+K21-L21-J21-H21-F21-D21 -> 0
B22: Outras transferências correntes | C22: =CEIResumida!D95 -> 35242 | D22: =CEIResumida!E95 -> 0 | E22: =CEIResumida!F95 -> 70054 | F22: =CEIResumida!G95 -> 0 | G22: =CEIResumida!H95 -> 0 | H22: =CEIResumida!I95 -> 13352 | I22: =CEIResumida!J95 -> 0 | J22: =CEIResumida!K95 -> 59170 | ... L22: =CEIResumida!M95 -> 32774 | M22: =C22+E22+G22+I22+K22-L22-J22-H22-F22-D22 -> 0 | O22: Demanda final | R22: Expor- tação de bens e serviços (3) | S22: Consu- mo do governo | U22: Consu- mo das famílias | V22: Forma- ção bruta de capi- tal fixo | W22: Varia- ção de estoque | X22: Demanda autônoma | Y22: Demanda induzida | Z22: Demanda final | AA22: Demanda TOTAL 2 | AD22: Expor- tação de bens e serviços (3) | AE22: Consu- mo do governo | AG22: Consu- mo das famílias | AH22: Forma- ção bruta de capi- tal fixo | AI22: Varia- ção de estoque | AJ22: Demanda autônoma | AK22: Demanda induzida | AL22: Demanda final | AM22: De- manda TOTAL
A23: Usos da renda | B23: Consumo final efetivo | C23: =CEIResumida!D96 -> 0 | D23: =(SUM(C8:C22)-SUM(D8:D22))*ParâmetrosCEI!D56 -> 4805004 | E23: =CEIResumida!F96 -> 0 | F23: =S20 -> 1532204 | G23: =CEIResumida!H96 -> 0 | H23: =CEIResumida!I96 -> 0 | I23: =CEIResumida!J96 -> 0 | J23: =CEIResumida!K96 -> 0 | K23: =CEIResumida!L96 -> 0 | L23: =CEIResumida!M96 -> 0 | M23: =C23+E23+G23+I23+K23-L23-J23-H23-F23-D23 -> -6337208 | O23: =D23+D25+F23+F25+H25+J25+J26+L7 -> 8815606 | AB23: Consumo intermediário
B24: Ajustamento pela variação dos direitos de pensão | C24: =CEIResumida!D97 -> 0 | D24: =CEIResumida!E97 -> 0 | E24: =CEIResumida!F97 -> 0 | F24: =CEIResumida!G97 -> 0 | G24: =CEIResumida!H97 -> 0 | H24: =CEIResumida!I97 -> 0 | I24: =CEIResumida!J97 -> 0 | J24: =CEIResumida!K97 -> 0 | ... L24: =CEIResumida!M97 -> 0 | M24: =C24+E24+G24+I24+K24-L24-J24-H24-F24-D24 -> 0
B25: Formação bruta de capital fixo | C25: =CEIResumida!D98 -> 0 | D25: =(SUM(C8:C22)-SUM(D8:D22))*ParâmetrosCEI!D58 -> 410010 | E25: =CEIResumida!F98 -> 0 | F25: =CEIResumida!G98 -> 139686 | G25: =CEIResumida!H98 -> 0 | H25: =CEIResumida!I98 -> 13718 | I25: =CEIResumida!J98 -> 0 | J25: =CEIResumida!K98 -> 696813 | K25: =CEIResumida!L98 -> 0 | L25: =CEIResumida!M98 -> 0 | M25: =C25+E25+G25+I25+K25-L25-J25-H25-F25-D25 -> -1260227 | N25: Multiplicador | O25: =Z20 -> 8815606
B26: Variação de estoques | C26: =CEIResumida!D99 -> 0 | D26: =CEIResumida!E99 -> 0 | E26: =CEIResumida!F99 -> 0 | F26: =CEIResumida!G99 -> 0 | G26: =CEIResumida!H99 -> 0 | H26: =CEIResumida!I99 -> 0 | I26: =CEIResumida!J99 -> 0 | J26: =CEIResumida!K99 -> -33878 | ... L26: =CEIResumida!M99 -> 0 | M26: =C26+E26+G26+I26+K26-L26-J26-H26-F26-D26 -> 33878 | N26: Por % | O26: =Z39 -> 8815606
B27: Aquisições líquidas de cessões de ativos não-produzidos | C27: =CEIResumida!D100 -> 0 | D27: =CEIResumida!E100 -> 0 | E27: =CEIResumida!F100 -> 0 | F27: =CEIResumida!G100 -> 0 | G27: =CEIResumida!H100 -> 0 | H27: =CEIResumida!I100 -> 0 | I27: =CEIResumida!J100 -> 0 | J27: =CEIResumida!K100 -> 0 | ... L27: =CEIResumida!M100 -> 0 | M27: =C27+E27+G27+I27+K27-L27-J27-H27-F27-D27 -> 0 | N27: Correto | O27: =Original!AE51 -> 8815606 | R27: =R8 -> 241683 | S27: =S8 -> 230 | U27: =$D$23*ParâmeetrosTRU!AB39 -> 212694 | V27: 22310 | W27: -2694 | X27: =R27+S27+V27+W27 -> 261529 | Y27: =Z27-X27 -> 212694 | Z27: =SUM(R27:W27) -> 474223 | AA27: =Z27+AB27 -> 938989 | AB27: =SimulTRU2!CK39 -> 464766 | AD27: =IFERROR(R27/R47-1,0) -> 0 | AE27: =IFERROR(S27/S47-1,0) -> 0 | AF27: =IFERROR(T27/T47-1,0) -> 0 | AG27: =IFERROR(U27/U47-1,0) -> 2.220446e-16 | AH27: =IFERROR(V27/V47-1,0) -> 0 | AI27: =IFERROR(W27/W47-1,0) -> 0 | AJ27: =IFERROR(X27/X47-1,0) -> 0 | AK27: =IFERROR(Y27/Y47-1,0) -> 2.220446e-16 | ... AM27: =IFERROR(AA27/AA47-1,0) -> 2.220446e-16
B28: Capacidade (+) / Necessidade(-) líquida de financiamento | C28: =SUM(C7:C27)-SUM(D7:D27) -> 562272 | E28: =SUM(E7:E27)-SUM(F7:F27) -> -918009 | G28: =SUM(G7:G27)-SUM(H7:H27) -> 149429 | I28: =SUM(I7:I27)-SUM(J7:J27) -> 125770 | K28: =-SUM(C28:J28) -> 80538 | M28: =C28+E28+G28+I28+K28-L28-J28-H28-F28-D28 -> 0 | R28: =R9 -> 253114 | S28: =S9 -> 0 | U28: =$D$23*ParâmeetrosTRU!AB40 -> 0 | V28: 10455 | W28: -27501 | X28: =R28+S28+V28+W28 -> 236068 | Y28: =Z28-X28 -> 0 | Z28: =SUM(R28:W28) -> 236068 | AA28: =Z28+AB28 -> 474641 | AB28: =SimulTRU2!CK40 -> 238573 | AD28: =IFERROR(R28/R48-1,0) -> 0 | AE28: =IFERROR(S28/S48-1,0) -> 0 | AF28: =IFERROR(T28/T48-1,0) -> 0 | AG28: =IFERROR(U28/U48-1,0) -> 0 | AH28: =IFERROR(V28/V48-1,0) -> 0 | AI28: =IFERROR(W28/W48-1,0) -> 0 | AJ28: =IFERROR(X28/X48-1,0) -> 0 | AK28: =IFERROR(Y28/Y48-1,0) -> 0 | ... AM28: =IFERROR(AA28/AA48-1,0) -> 4.4408921e-16
B29: Check | C29: 562272 | E29: -918009 | G29: 149429 | I29: 125770 | K29: 80538 | M29: =C29+E29+G29+I29+K29-L29-J29-H29-F29-D29 -> 0 | R29: =R10 -> 611468 | S29: =S10 -> 9716 | U29: =$D$23*ParâmeetrosTRU!AB41 -> 2148705 | V29: 523356 | W29: -2168 | X29: =R29+S29+V29+W29 -> 1142372 | Y29: =Z29-X29 -> 2148705 | Z29: =SUM(R29:W29) -> 3291077 | AA29: =Z29+AB29 -> 6468662 | AB29: =SimulTRU2!CK41 -> 3177585 | AD29: =IFERROR(R29/R49-1,0) -> 0 | AE29: =IFERROR(S29/S49-1,0) -> 0 | AF29: =IFERROR(T29/T49-1,0) -> 0 | AG29: =IFERROR(U29/U49-1,0) -> 2.220446e-16 | AH29: =IFERROR(V29/V49-1,0) -> 0 | AI29: =IFERROR(W29/W49-1,0) -> 0 | AJ29: =IFERROR(X29/X49-1,0) -> 0 | AK29: =IFERROR(Y29/Y49-1,0) -> 2.220446e-16 | ... AM29: =IFERROR(AA29/AA49-1,0) -> 4.4408921e-16
R30: =R11 -> 2 | S30: =S11 -> 0 | U30: =$D$23*ParâmeetrosTRU!AB42 -> 186576 | V30: 0 | W30: -60 | X30: =R30+S30+V30+W30 -> -58 | Y30: =Z30-X30 -> 186576 | Z30: =SUM(R30:W30) -> 186518 | AA30: =Z30+AB30 -> 532996 | AB30: =SimulTRU2!CK42 -> 346478 | AD30: =IFERROR(R30/R50-1,0) -> 0 | AE30: =IFERROR(S30/S50-1,0) -> 0 | AF30: =IFERROR(T30/T50-1,0) -> 0 | AG30: =IFERROR(U30/U50-1,0) -> 2.220446e-16 | AH30: =IFERROR(V30/V50-1,0) -> 0 | AI30: =IFERROR(W30/W50-1,0) -> 0 | AJ30: =IFERROR(X30/X50-1,0) -> 0 | AK30: =IFERROR(Y30/Y50-1,0) -> 2.220446e-16 | ... AM30: =IFERROR(AA30/AA50-1,0) -> 8.8817842e-16
D31: =C28/C29-1 -> 0 | F31: =E28/E29-1 -> 0 | H31: =G28/G29-1 -> 0 | J31: =I28/I29-1 -> 1.4876989e-14 | L31: =K28/K29-1 -> -2.5979219e-14 | R31: =R12 -> 3481 | S31: =S12 -> 0 | U31: =$D$23*ParâmeetrosTRU!AB43 -> 0 | V31: 556609 | W31: 0 | X31: =R31+S31+V31+W31 -> 560090 | Y31: =Z31-X31 -> 0 | Z31: =SUM(R31:W31) -> 560090 | AA31: =Z31+AB31 -> 683264 | AB31: =SimulTRU2!CK43 -> 123174 | AD31: =IFERROR(R31/R51-1,0) -> 0 | AE31: =IFERROR(S31/S51-1,0) -> 0 | AF31: =IFERROR(T31/T51-1,0) -> 0 | AG31: =IFERROR(U31/U51-1,0) -> 0 | AH31: =IFERROR(V31/V51-1,0) -> 0 | AI31: =IFERROR(W31/W51-1,0) -> 0 | AJ31: =IFERROR(X31/X51-1,0) -> 0 | AK31: =IFERROR(Y31/Y51-1,0) -> 0 | ... AM31: =IFERROR(AA31/AA51-1,0) -> -5.5511151e-16
R32: =R13 -> 4676 | S32: =S13 -> 0 | U32: =$D$23*ParâmeetrosTRU!AB44 -> 55912 | V32: 0 | W32: 0 | X32: =R32+S32+V32+W32 -> 4676 | Y32: =Z32-X32 -> 55912 | Z32: =SUM(R32:W32) -> 60588 | AA32: =Z32+AB32 -> 140737 | AB32: =SimulTRU2!CK44 -> 80149 | AD32: =IFERROR(R32/R52-1,0) -> 0 | AE32: =IFERROR(S32/S52-1,0) -> 0 | AF32: =IFERROR(T32/T52-1,0) -> 0 | AG32: =IFERROR(U32/U52-1,0) -> 2.220446e-16 | AH32: =IFERROR(V32/V52-1,0) -> 0 | AI32: =IFERROR(W32/W52-1,0) -> 0 | AJ32: =IFERROR(X32/X52-1,0) -> 0 | AK32: =IFERROR(Y32/Y52-1,0) -> 2.220446e-16 | ... AM32: =IFERROR(AA32/AA52-1,0) -> 8.8817842e-16
R33: =R14 -> 34419 | S33: =S14 -> 0 | U33: =$D$23*ParâmeetrosTRU!AB45 -> 109783 | V33: 0 | W33: 0 | X33: =R33+S33+V33+W33 -> 34419 | Y33: =Z33-X33 -> 109783 | Z33: =SUM(R33:W33) -> 144202 | AA33: =Z33+AB33 -> 568288 | AB33: =SimulTRU2!CK45 -> 424086 | AD33: =IFERROR(R33/R53-1,0) -> 0 | AE33: =IFERROR(S33/S53-1,0) -> 0 | AF33: =IFERROR(T33/T53-1,0) -> 0 | AG33: =IFERROR(U33/U53-1,0) -> 2.220446e-16 | AH33: =IFERROR(V33/V53-1,0) -> 0 | AI33: =IFERROR(W33/W53-1,0) -> 0 | AJ33: =IFERROR(X33/X53-1,0) -> 0 | AK33: =IFERROR(Y33/Y53-1,0) -> 2.220446e-16 | ... AM33: =IFERROR(AA33/AA53-1,0) -> 8.8817842e-16
